Workbook

Sheet Daily Grid
A1: Date | B1: Year | C1: Month | D1: Weekday | E1: AEP | F1: MA_OEP / GEP | G1: SEP_Notes | H1: Has_Event | I1: Event_Detail
A2: 45292 | B2: =YEAR($A2) -> 2024 | C2: =MONTH($A2) -> 1 | D2: =TEXT($A2,"ddd") -> Mon | E2: =IF(OR(AND(MONTH($A2)=10,DAY($A2)>=15),MONTH($A2)=11,AND(MONTH($A2)=12,DAY($A2)<=7)),1,0) -> 0 | F2: =IF(MONTH($A2)<=3,1,0) -> 1 | G2: {=_xlfn.TEXTJOIN(" | ",TRUE(),IF('FEMA Disasters'!$F$2:$F$1000=$A2,'FEMA Disasters'!$D$2:$D$1000&" begin: ["&'FEMA Disasters'!$B$2:$B$1000&"] "&'FEMA Disasters'!$C$2:$C$1000&"-"&'FEMA Disasters'!$A$2:$A$1000,""),IF('FEMA Disasters'!$G$2:$G$1000=$A2,'FEMA Disasters'!$D$2:$D$1000&" ended: ["&'FEMA Disasters'!$B$2:$B$1000&"] "&'FEMA Disasters'!$C$2:$C$1000&"-"&'FEMA Disasters'!$A$2:$A$1000,""),IF('FEMA Disasters'!$K$2:$K$1000=$A2,"Disaster SEP opens: "&'FEMA Disasters'!$D$2:$D$1000&" ["&'FEMA Disasters'!$B$2:$B$1000&"] "&'FEMA Disasters'!$C$2:$C$1000&"-"&'FEMA Disasters'!$A$2:$A$1000,""),IF('FEMA Disasters'!$L$2:$L$1000=$A2,"Disaster SEP ended: "&'FEMA Disasters'!$D$2:$D$1000&" ["&'FEMA Disasters'!$B$2:$B$1000&"] "&'FEMA Disasters'!$C$2:$C$1000&"-"&'FEMA Disasters'!$A$2:$A$1000,""))} | H2: =COUNTIF(Events!$A$2:$A$397,$A2) -> 2 | I2: {=_xlfn.TEXTJOIN(" | ",TRUE(),IF(Events!$A$2:$A$397=$A2,Events!$E$2:$E$397&IF(Events!$G$2:$G$397="National",""," ["&Events!$G$2:$G$397&"]"),""))} -> IRA phase-in: 5% coinsurance in Part D catastrophic phase eliminated; full Low-Income Subsidy (Extra Help) expanded to 150% FPL | Kentucky Medigap birthday rule takes effect (2023 HB 345, Ch. 182; KRS 304.14-525): enrollees may switch to another insurer's same-letter policy within 60 days after their birthday, no medical underwriting; law also added under-65 open enrollment protections [KY]
A3: 45293 | B3: =YEAR($A3) -> 2024 | C3: =MONTH($A3) -> 1 | D3: =TEXT($A3,"ddd") -> Tue | E3: =IF(OR(AND(MONTH($A3)=10,DAY($A3)>=15),MONTH($A3)=11,AND(MONTH($A3)=12,DAY($A3)<=7)),1,0) -> 0 | F3: =IF(MONTH($A3)<=3,1,0) -> 1 | G3: {=_xlfn.TEXTJOIN(" | ",TRUE(),IF('FEMA Disasters'!$F$2:$F$1000=$A3,'FEMA Disasters'!$D$2:$D$1000&" begin: ["&'FEMA Disasters'!$B$2:$B$1000&"] "&'FEMA Disasters'!$C$2:$C$1000&"-"&'FEMA Disasters'!$A$2:$A$1000,""),IF('FEMA Disasters'!$G$2:$G$1000=$A3,'FEMA Disasters'!$D$2:$D$1000&" ended: ["&'FEMA Disasters'!$B$2:$B$1000&"] "&'FEMA Disasters'!$C$2:$C$1000&"-"&'FEMA Disasters'!$A$2:$A$1000,""),IF('FEMA Disasters'!$K$2:$K$1000=$A3,"Disaster SEP opens: "&'FEMA Disasters'!$D$2:$D$1000&" ["&'FEMA Disasters'!$B$2:$B$1000&"] "&'FEMA Disasters'!$C$2:$C$1000&"-"&'FEMA Disasters'!$A$2:$A$1000,""),IF('FEMA Disasters'!$L$2:$L$1000=$A3,"Disaster SEP ended: "&'FEMA Disasters'!$D$2:$D$1000&" ["&'FEMA Disasters'!$B$2:$B$1000&"] "&'FEMA Disasters'!$C$2:$C$1000&"-"&'FEMA Disasters'!$A$2:$A$1000,""))} | H3: =COUNTIF(Events!$A$2:$A$397,$A3) -> 0 | I3: {=_xlfn.TEXTJOIN(" | ",TRUE(),IF(Events!$A$2:$A$397=$A3,Events!$E$2:$E$397&IF(Events!$G$2:$G$397="National",""," ["&Events!$G$2:$G$397&"]"),""))}
A4: 45294 | B4: =YEAR($A4) -> 2024 | C4: =MONTH($A4) -> 1 | D4: =TEXT($A4,"ddd") -> Wed | E4: =IF(OR(AND(MONTH($A4)=10,DAY($A4)>=15),MONTH($A4)=11,AND(MONTH($A4)=12,DAY($A4)<=7)),1,0) -> 0 | F4: =IF(MONTH($A4)<=3,1,0) -> 1 | G4: {=_xlfn.TEXTJOIN(" | ",TRUE(),IF('FEMA Disasters'!$F$2:$F$1000=$A4,'FEMA Disasters'!$D$2:$D$1000&" begin: ["&'FEMA Disasters'!$B$2:$B$1000&"] "&'FEMA Disasters'!$C$2:$C$1000&"-"&'FEMA Disasters'!$A$2:$A$1000,""),IF('FEMA Disasters'!$G$2:$G$1000=$A4,'FEMA Disasters'!$D$2:$D$1000&" ended: ["&'FEMA Disasters'!$B$2:$B$1000&"] "&'FEMA Disasters'!$C$2:$C$1000&"-"&'FEMA Disasters'!$A$2:$A$1000,""),IF('FEMA Disasters'!$K$2:$K$1000=$A4,"Disaster SEP opens: "&'FEMA Disasters'!$D$2:$D$1000&" ["&'FEMA Disasters'!$B$2:$B$1000&"] "&'FEMA Disasters'!$C$2:$C$1000&"-"&'FEMA Disasters'!$A$2:$A$1000,""),IF('FEMA Disasters'!$L$2:$L$1000=$A4,"Disaster SEP ended: "&'FEMA Disasters'!$D$2:$D$1000&" ["&'FEMA Disasters'!$B$2:$B$1000&"] "&'FEMA Disasters'!$C$2:$C$1000&"-"&'FEMA Disasters'!$A$2:$A$1000,""))} | H4: =COUNTIF(Events!$A$2:$A$397,$A4) -> 0 | I4: {=_xlfn.TEXTJOIN(" | ",TRUE(),IF(Events!$A$2:$A$397=$A4,Events!$E$2:$E$397&IF(Events!$G$2:$G$397="National",""," ["&Events!$G$2:$G$397&"]"),""))}
A5: 45295 | B5: =YEAR($A5) -> 2024 | C5: =MONTH($A5) -> 1 | D5: =TEXT($A5,"ddd") -> Thu | E5: =IF(OR(AND(MONTH($A5)=10,DAY($A5)>=15),MONTH($A5)=11,AND(MONTH($A5)=12,DAY($A5)<=7)),1,0) -> 0 | F5: =IF(MONTH($A5)<=3,1,0) -> 1 | G5: {=_xlfn.TEXTJOIN(" | ",TRUE(),IF('FEMA Disasters'!$F$2:$F$1000=$A5,'FEMA Disasters'!$D$2:$D$1000&" begin: ["&'FEMA Disasters'!$B$2:$B$1000&"] "&'FEMA Disasters'!$C$2:$C$1000&"-"&'FEMA Disasters'!$A$2:$A$1000,""),IF('FEMA Disasters'!$G$2:$G$1000=$A5,'FEMA Disasters'!$D$2:$D$1000&" ended: ["&'FEMA Disasters'!$B$2:$B$1000&"] "&'FEMA Disasters'!$C$2:$C$1000&"-"&'FEMA Disasters'!$A$2:$A$1000,""),IF('FEMA Disasters'!$K$2:$K$1000=$A5,"Disaster SEP opens: "&'FEMA Disasters'!$D$2:$D$1000&" ["&'FEMA Disasters'!$B$2:$B$1000&"] "&'FEMA Disasters'!$C$2:$C$1000&"-"&'FEMA Disasters'!$A$2:$A$1000,""),IF('FEMA Disasters'!$L$2:$L$1000=$A5,"Disaster SEP ended: "&'FEMA Disasters'!$D$2:$D$1000&" ["&'FEMA Disasters'!$B$2:$B$1000&"] "&'FEMA Disasters'!$C$2:$C$1000&"-"&'FEMA Disasters'!$A$2:$A$1000,""))} | H5: =COUNTIF(Events!$A$2:$A$397,$A5) -> 0 | I5: {=_xlfn.TEXTJOIN(" | ",TRUE(),IF(Events!$A$2:$A$397=$A5,Events!$E$2:$E$397&IF(Events!$G$2:$G$397="National",""," ["&Events!$G$2:$G$397&"]"),""))}
A6: 45296 | B6: =YEAR($A6) -> 2024 | C6: =MONTH($A6) -> 1 | D6: =TEXT($A6,"ddd") -> Fri | E6: =IF(OR(AND(MONTH($A6)=10,DAY($A6)>=15),MONTH($A6)=11,AND(MONTH($A6)=12,DAY($A6)<=7)),1,0) -> 0 | F6: =IF(MONTH($A6)<=3,1,0) -> 1 | G6: {=_xlfn.TEXTJOIN(" | ",TRUE(),IF('FEMA Disasters'!$F$2:$F$1000=$A6,'FEMA Disasters'!$D$2:$D$1000&" begin: ["&'FEMA Disasters'!$B$2:$B$1000&"] "&'FEMA Disasters'!$C$2:$C$1000&"-"&'FEMA Disasters'!$A$2:$A$1000,""),IF('FEMA Disasters'!$G$2:$G$1000=$A6,'FEMA Disasters'!$D$2:$D$1000&" ended: ["&'FEMA Disasters'!$B$2:$B$1000&"] "&'FEMA Disasters'!$C$2:$C$1000&"-"&'FEMA Disasters'!$A$2:$A$1000,""),IF('FEMA Disasters'!$K$2:$K$1000=$A6,"Disaster SEP opens: "&'FEMA Disasters'!$D$2:$D$1000&" ["&'FEMA Disasters'!$B$2:$B$1000&"] "&'FEMA Disasters'!$C$2:$C$1000&"-"&'FEMA Disasters'!$A$2:$A$1000,""),IF('FEMA Disasters'!$L$2:$L$1000=$A6,"Disaster SEP ended: "&'FEMA Disasters'!$D$2:$D$1000&" ["&'FEMA Disasters'!$B$2:$B$1000&"] "&'FEMA Disasters'!$C$2:$C$1000&"-"&'FEMA Disasters'!$A$2:$A$1000,""))} -> Severe Storm begin: [WA] DR-4775 | Disaster SEP opens: Severe Storm [WA] DR-4775 | H6: =COUNTIF(Events!$A$2:$A$397,$A6) -> 0 | I6: {=_xlfn.TEXTJOIN(" | ",TRUE(),IF(Events!$A$2:$A$397=$A6,Events!$E$2:$E$397&IF(Events!$G$2:$G$397="National",""," ["&Events!$G$2:$G$397&"]"),""))}
A7: 45297 | B7: =YEAR($A7) -> 2024 | C7: =MONTH($A7) -> 1 | D7: =TEXT($A7,"ddd") -> Sat | E7: =IF(OR(AND(MONTH($A7)=10,DAY($A7)>=15),MONTH($A7)=11,AND(MONTH($A7)=12,DAY($A7)<=7)),1,0) -> 0 | F7: =IF(MONTH($A7)<=3,1,0) -> 1 | G7: {=_xlfn.TEXTJOIN(" | ",TRUE(),IF('FEMA Disasters'!$F$2:$F$1000=$A7,'FEMA Disasters'!$D$2:$D$1000&" begin: ["&'FEMA Disasters'!$B$2:$B$1000&"] "&'FEMA Disasters'!$C$2:$C$1000&"-"&'FEMA Disasters'!$A$2:$A$1000,""),IF('FEMA Disasters'!$G$2:$G$1000=$A7,'FEMA Disasters'!$D$2:$D$1000&" ended: ["&'FEMA Disasters'!$B$2:$B$1000&"] "&'FEMA Disasters'!$C$2:$C$1000&"-"&'FEMA Disasters'!$A$2:$A$1000,""),IF('FEMA Disasters'!$K$2:$K$1000=$A7,"Disaster SEP opens: "&'FEMA Disasters'!$D$2:$D$1000&" ["&'FEMA Disasters'!$B$2:$B$1000&"] "&'FEMA Disasters'!$C$2:$C$1000&"-"&'FEMA Disasters'!$A$2:$A$1000,""),IF('FEMA Disasters'!$L$2:$L$1000=$A7,"Disaster SEP ended: "&'FEMA Disasters'!$D$2:$D$1000&" ["&'FEMA Disasters'!$B$2:$B$1000&"] "&'FEMA Disasters'!$C$2:$C$1000&"-"&'FEMA Disasters'!$A$2:$A$1000,""))} | H7: =COUNTIF(Events!$A$2:$A$397,$A7) -> 0 | I7: {=_xlfn.TEXTJOIN(" | ",TRUE(),IF(Events!$A$2:$A$397=$A7,Events!$E$2:$E$397&IF(Events!$G$2:$G$397="National",""," ["&Events!$G$2:$G$397&"]"),""))}
A8: 45298 | B8: =YEAR($A8) -> 2024 | C8: =MONTH($A8) -> 1 | D8: =TEXT($A8,"ddd") -> Sun | E8: =IF(OR(AND(MONTH($A8)=10,DAY($A8)>=15),MONTH($A8)=11,AND(MONTH($A8)=12,DAY($A8)<=7)),1,0) -> 0 | F8: =IF(MONTH($A8)<=3,1,0) -> 1 | G8: {=_xlfn.TEXTJOIN(" | ",TRUE(),IF('FEMA Disasters'!$F$2:$F$1000=$A8,'FEMA Disasters'!$D$2:$D$1000&" begin: ["&'FEMA Disasters'!$B$2:$B$1000&"] "&'FEMA Disasters'!$C$2:$C$1000&"-"&'FEMA Disasters'!$A$2:$A$1000,""),IF('FEMA Disasters'!$G$2:$G$1000=$A8,'FEMA Disasters'!$D$2:$D$1000&" ended: ["&'FEMA Disasters'!$B$2:$B$1000&"] "&'FEMA Disasters'!$C$2:$C$1000&"-"&'FEMA Disasters'!$A$2:$A$1000,""),IF('FEMA Disasters'!$K$2:$K$1000=$A8,"Disaster SEP opens: "&'FEMA Disasters'!$D$2:$D$1000&" ["&'FEMA Disasters'!$B$2:$B$1000&"] "&'FEMA Disasters'!$C$2:$C$1000&"-"&'FEMA Disasters'!$A$2:$A$1000,""),IF('FEMA Disasters'!$L$2:$L$1000=$A8,"Disaster SEP ended: "&'FEMA Disasters'!$D$2:$D$1000&" ["&'FEMA Disasters'!$B$2:$B$1000&"] "&'FEMA Disasters'!$C$2:$C$1000&"-"&'FEMA Disasters'!$A$2:$A$1000,""))} | H8: =COUNTIF(Events!$A$2:$A$397,$A8) -> 0 | I8: {=_xlfn.TEXTJOIN(" | ",TRUE(),IF(Events!$A$2:$A$397=$A8,Events!$E$2:$E$397&IF(Events!$G$2:$G$397="National",""," ["&Events!$G$2:$G$397&"]"),""))}
A9: 45299 | B9: =YEAR($A9) -> 2024 | C9: =MONTH($A9) -> 1 | D9: =TEXT($A9,"ddd") -> Mon | E9: =IF(OR(AND(MONTH($A9)=10,DAY($A9)>=15),MONTH($A9)=11,AND(MONTH($A9)=12,DAY($A9)<=7)),1,0) -> 0 | F9: =IF(MONTH($A9)<=3,1,0) -> 1 | G9: {=_xlfn.TEXTJOIN(" | ",TRUE(),IF('FEMA Disasters'!$F$2:$F$1000=$A9,'FEMA Disasters'!$D$2:$D$1000&" begin: ["&'FEMA Disasters'!$B$2:$B$1000&"] "&'FEMA Disasters'!$C$2:$C$1000&"-"&'FEMA Disasters'!$A$2:$A$1000,""),IF('FEMA Disasters'!$G$2:$G$1000=$A9,'FEMA Disasters'!$D$2:$D$1000&" ended: ["&'FEMA Disasters'!$B$2:$B$1000&"] "&'FEMA Disasters'!$C$2:$C$1000&"-"&'FEMA Disasters'!$A$2:$A$1000,""),IF('FEMA Disasters'!$K$2:$K$1000=$A9,"Disaster SEP opens: "&'FEMA Disasters'!$D$2:$D$1000&" ["&'FEMA Disasters'!$B$2:$B$1000&"] "&'FEMA Disasters'!$C$2:$C$1000&"-"&'FEMA Disasters'!$A$2:$A$1000,""),IF('FEMA Disasters'!$L$2:$L$1000=$A9,"Disaster SEP ended: "&'FEMA Disasters'!$D$2:$D$1000&" ["&'FEMA Disasters'!$B$2:$B$1000&"] "&'FEMA Disasters'!$C$2:$C$1000&"-"&'FEMA Disasters'!$A$2:$A$1000,""))} -> Winter Storm begin: [KS] DR-4774 | Disaster SEP opens: Winter Storm [KS] DR-4774 | H9: =COUNTIF(Events!$A$2:$A$397,$A9) -> 0 | I9: {=_xlfn.TEXTJOIN(" | ",TRUE(),IF(Events!$A$2:$A$397=$A9,Events!$E$2:$E$397&IF(Events!$G$2:$G$397="National",""," ["&Events!$G$2:$G$397&"]"),""))}
A10: 45300 | B10: =YEAR($A10) -> 2024 | C10: =MONTH($A10) -> 1 | D10: =TEXT($A10,"ddd") -> Tue | E10: =IF(OR(AND(MONTH($A10)=10,DAY($A10)>=15),MONTH($A10)=11,AND(MONTH($A10)=12,DAY($A10)<=7)),1,0) -> 0 | F10: =IF(MONTH($A10)<=3,1,0) -> 1 | G10: {=_xlfn.TEXTJOIN(" | ",TRUE(),IF('FEMA Disasters'!$F$2:$F$1000=$A10,'FEMA Disasters'!$D$2:$D$1000&" begin: ["&'FEMA Disasters'!$B$2:$B$1000&"] "&'FEMA Disasters'!$C$2:$C$1000&"-"&'FEMA Disasters'!$A$2:$A$1000,""),IF('FEMA Disasters'!$G$2:$G$1000=$A10,'FEMA Disasters'!$D$2:$D$1000&" ended: ["&'FEMA Disasters'!$B$2:$B$1000&"] "&'FEMA Disasters'!$C$2:$C$1000&"-"&'FEMA Disasters'!$A$2:$A$1000,""),IF('FEMA Disasters'!$K$2:$K$1000=$A10,"Disaster SEP opens: "&'FEMA Disasters'!$D$2:$D$1000&" ["&'FEMA Disasters'!$B$2:$B$1000&"] "&'FEMA Disasters'!$C$2:$C$1000&"-"&'FEMA Disasters'!$A$2:$A$1000,""),IF('FEMA Disasters'!$L$2:$L$1000=$A10,"Disaster SEP ended: "&'FEMA Disasters'!$D$2:$D$1000&" ["&'FEMA Disasters'!$B$2:$B$1000&"] "&'FEMA Disasters'!$C$2:$C$1000&"-"&'FEMA Disasters'!$A$2:$A$1000,""))} -> Severe Storm begin: [ME] DR-4764 | Severe Storm begin: [RI] DR-4766 | Severe Storm begin: [VT] DR-4770 | Severe Storm begin: [NH] DR-4771 | Disaster SEP opens: Severe Storm [ME] DR-4764 | Disaster SEP opens: Severe Storm [RI] DR-4766 | Disaster SEP opens: Severe Storm [VT] DR-4770 | Disaster SEP opens: Severe Storm [NH] DR-4771 | H10: =COUNTIF(Events!$A$2:$A$397,$A10) -> 0 | I10: {=_xlfn.TEXTJOIN(" | ",TRUE(),IF(Events!$A$2:$A$397=$A10,Events!$E$2:$E$397&IF(Events!$G$2:$G$397="National",""," ["&Events!$G$2:$G$397&"]"),""))}
A11: 45301 | B11: =YEAR($A11) -> 2024 | C11: =MONTH($A11) -> 1 | D11: =TEXT($A11,"ddd") -> Wed | E11: =IF(OR(AND(MONTH($A11)=10,DAY($A11)>=15),MONTH($A11)=11,AND(MONTH($A11)=12,DAY($A11)<=7)),1,0) -> 0 | F11: =IF(MONTH($A11)<=3,1,0) -> 1 | G11: {=_xlfn.TEXTJOIN(" | ",TRUE(),IF('FEMA Disasters'!$F$2:$F$1000=$A11,'FEMA Disasters'!$D$2:$D$1000&" begin: ["&'FEMA Disasters'!$B$2:$B$1000&"] "&'FEMA Disasters'!$C$2:$C$1000&"-"&'FEMA Disasters'!$A$2:$A$1000,""),IF('FEMA Disasters'!$G$2:$G$1000=$A11,'FEMA Disasters'!$D$2:$D$1000&" ended: ["&'FEMA Disasters'!$B$2:$B$1000&"] "&'FEMA Disasters'!$C$2:$C$1000&"-"&'FEMA Disasters'!$A$2:$A$1000,""),IF('FEMA Disasters'!$K$2:$K$1000=$A11,"Disaster SEP opens: "&'FEMA Disasters'!$D$2:$D$1000&" ["&'FEMA Disasters'!$B$2:$B$1000&"] "&'FEMA Disasters'!$C$2:$C$1000&"-"&'FEMA Disasters'!$A$2:$A$1000,""),IF('FEMA Disasters'!$L$2:$L$1000=$A11,"Disaster SEP ended: "&'FEMA Disasters'!$D$2:$D$1000&" ["&'FEMA Disasters'!$B$2:$B$1000&"] "&'FEMA Disasters'!$C$2:$C$1000&"-"&'FEMA Disasters'!$A$2:$A$1000,""))} -> Severe Storm begin: [CT] EM-3604 | Severe Storm begin: [OR] DR-4768 | Disaster SEP opens: Severe Storm [CT] EM-3604 | Disaster SEP opens: Severe Storm [OR] DR-4768 | H11: =COUNTIF(Events!$A$2:$A$397,$A11) -> 0 | I11: {=_xlfn.TEXTJOIN(" | ",TRUE(),IF(Events!$A$2:$A$397=$A11,Events!$E$2:$E$397&IF(Events!$G$2:$G$397="National",""," ["&Events!$G$2:$G$397&"]"),""))}
A12: 45302 | B12: =YEAR($A12) -> 2024 | C12: =MONTH($A12) -> 1 | D12: =TEXT($A12,"ddd") -> Thu | E12: =IF(OR(AND(MONTH($A12)=10,DAY($A12)>=15),MONTH($A12)=11,AND(MONTH($A12)=12,DAY($A12)<=7)),1,0) -> 0 | F12: =IF(MONTH($A12)<=3,1,0) -> 1 | G12: {=_xlfn.TEXTJOIN(" | ",TRUE(),IF('FEMA Disasters'!$F$2:$F$1000=$A12,'FEMA Disasters'!$D$2:$D$1000&" begin: ["&'FEMA Disasters'!$B$2:$B$1000&"] "&'FEMA Disasters'!$C$2:$C$1000&"-"&'FEMA Disasters'!$A$2:$A$1000,""),IF('FEMA Disasters'!$G$2:$G$1000=$A12,'FEMA Disasters'!$D$2:$D$1000&" ended: ["&'FEMA Disasters'!$B$2:$B$1000&"] "&'FEMA Disasters'!$C$2:$C$1000&"-"&'FEMA Disasters'!$A$2:$A$1000,""),IF('FEMA Disasters'!$K$2:$K$1000=$A12,"Disaster SEP opens: "&'FEMA Disasters'!$D$2:$D$1000&" ["&'FEMA Disasters'!$B$2:$B$1000&"] "&'FEMA Disasters'!$C$2:$C$1000&"-"&'FEMA Disasters'!$A$2:$A$1000,""),IF('FEMA Disasters'!$L$2:$L$1000=$A12,"Disaster SEP ended: "&'FEMA Disasters'!$D$2:$D$1000&" ["&'FEMA Disasters'!$B$2:$B$1000&"] "&'FEMA Disasters'!$C$2:$C$1000&"-"&'FEMA Disasters'!$A$2:$A$1000,""))} | H12: =COUNTIF(Events!$A$2:$A$397,$A12) -> 0 | I12: {=_xlfn.TEXTJOIN(" | ",TRUE(),IF(Events!$A$2:$A$397=$A12,Events!$E$2:$E$397&IF(Events!$G$2:$G$397="National",""," ["&Events!$G$2:$G$397&"]"),""))}
A13: 45303 | B13: =YEAR($A13) -> 2024 | C13: =MONTH($A13) -> 1 | D13: =TEXT($A13,"ddd") -> Fri | E13: =IF(OR(AND(MONTH($A13)=10,DAY($A13)>=15),MONTH($A13)=11,AND(MONTH($A13)=12,DAY($A13)<=7)),1,0) -> 0 | F13: =IF(MONTH($A13)<=3,1,0) -> 1 | G13: {=_xlfn.TEXTJOIN(" | ",TRUE(),IF('FEMA Disasters'!$F$2:$F$1000=$A13,'FEMA Disasters'!$D$2:$D$1000&" begin: ["&'FEMA Disasters'!$B$2:$B$1000&"] "&'FEMA Disasters'!$C$2:$C$1000&"-"&'FEMA Disasters'!$A$2:$A$1000,""),IF('FEMA Disasters'!$G$2:$G$1000=$A13,'FEMA Disasters'!$D$2:$D$1000&" ended: ["&'FEMA Disasters'!$B$2:$B$1000&"] "&'FEMA Disasters'!$C$2:$C$1000&"-"&'FEMA Disasters'!$A$2:$A$1000,""),IF('FEMA Disasters'!$K$2:$K$1000=$A13,"Disaster SEP opens: "&'FEMA Disasters'!$D$2:$D$1000&" ["&'FEMA Disasters'!$B$2:$B$1000&"] "&'FEMA Disasters'!$C$2:$C$1000&"-"&'FEMA Disasters'!$A$2:$A$1000,""),IF('FEMA Disasters'!$L$2:$L$1000=$A13,"Disaster SEP ended: "&'FEMA Disasters'!$D$2:$D$1000&" ["&'FEMA Disasters'!$B$2:$B$1000&"] "&'FEMA Disasters'!$C$2:$C$1000&"-"&'FEMA Disasters'!$A$2:$A$1000,""))} | H13: =COUNTIF(Events!$A$2:$A$397,$A13) -> 0 | I13: {=_xlfn.TEXTJOIN(" | ",TRUE(),IF(Events!$A$2:$A$397=$A13,Events!$E$2:$E$397&IF(Events!$G$2:$G$397="National",""," ["&Events!$G$2:$G$397&"]"),""))}
... A883: 46173 | B883: =YEAR($A883) -> 2026 | C883: =MONTH($A883) -> 5 | D883: =TEXT($A883,"ddd") -> Sun | E883: =IF(OR(AND(MONTH($A883)=10,DAY($A883)>=15),MONTH($A883)=11,AND(MONTH($A883)=12,DAY($A883)<=7)),1,0) -> 0 | F883: =IF(MONTH($A883)<=3,1,0) -> 0 | G883: {=_xlfn.TEXTJOIN(" | ",TRUE(),IF('FEMA Disasters'!$F$2:$F$1000=$A883,'FEMA Disasters'!$D$2:$D$1000&" begin: ["&'FEMA Disasters'!$B$2:$B$1000&"] "&'FEMA Disasters'!$C$2:$C$1000&"-"&'FEMA Disasters'!$A$2:$A$1000,""),IF('FEMA Disasters'!$G$2:$G$1000=$A883,'FEMA Disasters'!$D$2:$D$1000&" ended: ["&'FEMA Disasters'!$B$2:$B$1000&"] "&'FEMA Disasters'!$C$2:$C$1000&"-"&'FEMA Disasters'!$A$2:$A$1000,""),IF('FEMA Disasters'!$K$2:$K$1000=$A883,"Disaster SEP opens: "&'FEMA Disasters'!$D$2:$D$1000&" ["&'FEMA Disasters'!$B$2:$B$1000&"] "&'FEMA Disasters'!$C$2:$C$1000&"-"&'FEMA Disasters'!$A$2:$A$1000,""),IF('FEMA Disasters'!$L$2:$L$1000=$A883,"Disaster SEP ended: "&'FEMA Disasters'!$D$2:$D$1000&" ["&'FEMA Disasters'!$B$2:$B$1000&"] "&'FEMA Disasters'!$C$2:$C$1000&"-"&'FEMA Disasters'!$A$2:$A$1000,""))} -> Disaster SEP opens: Other [DC] EM-3643 | Disaster SEP opens: Flood [HI] DR-4909 | Disaster SEP opens: Severe Storm [ID] DR-4917 | Disaster SEP opens: Fire [NE] FM-5623 | Disaster SEP opens: Fire [OK] FM-5624 | Disaster SEP ended: Winter Storm [SC] EM-3632 | Disaster SEP ended: Winter Storm [NC] EM-3637 | Disaster SEP ended: Winter Storm [SC] DR-4908 | Disaster SEP ended: Winter Storm [VA] EM-3631 | Disaster SEP ended: Winter Storm [TN] EM-3635 | Disaster SEP ended: Winter Storm [GA] EM-3642 | Disaster SEP ended: Winter Storm [TN] DR-4898 | Disaster SEP ended: Winter Storm [KY] EM-3633 | Disaster SEP ended: Winter Storm [MD] EM-3634 | Disaster SEP ended: Winter Storm [AR] EM-3636 | Disaster SEP ended: Winter Storm [LA] EM-3638 | Disaster SEP ended: Winter Storm [WV] EM-3639 | Disaster SEP ended: Winter Storm [MS] EM-3640 | Disaster SEP ended: Winter Storm [IN] EM-3641 | Disaster SEP ended: Winter Storm [MS] DR-4899 | Disaster SEP ended: Winter Storm [LA] DR-4900 | Disaster SEP ended: Winter Storm [KY] DR-4913 | H883: =COUNTIF(Events!$A$2:$A$397,$A883) -> 0 | I883: {=_xlfn.TEXTJOIN(" | ",TRUE(),IF(Events!$A$2:$A$397=$A883,Events!$E$2:$E$397&IF(Events!$G$2:$G$397="National",""," ["&Events!$G$2:$G$397&"]"),""))}

Sheet Events
A1: Date | B1: Event_Type | C1: Affects | D1: Date_Type | E1: Description | F1: Source | G1: States | H1: Value_Mechanism
A2: 45292 | B2: Legislation | C2: Part D | D2: Effective | E2: IRA phase-in: 5% coinsurance in Part D catastrophic phase eliminated; full Low-Income Subsidy (Extra Help) expanded to 150% FPL | F2: https://www.cms.gov/newsroom/fact-sheets/2024-medicare-advantage-and-part-d-final-rule-cms-4201-f | G2: National | H2: Benefit/Cost Value
A3: 45292 | B3: State Regulation | C3: MS | D3: Effective | E3: Kentucky Medigap birthday rule takes effect (2023 HB 345, Ch. 182; KRS 304.14-525): enrollees may switch to another insurer's same-letter policy within 60 days after their birthday, no medical underwriting; law also added under-65 open enrollment protections | F3: https://insurance.ky.gov/ppc/Documents/2024.01.24%20Medicare%20Supplement%20Enrollment%20Changes.pdf | G3: KY | H3: Switching Window
A4: 45322 | B4: CMS Rule | C4: MA / Part D | D4: Announced | E4: CY2025 Advance Notice released: proposed +3.70% avg payment; year 2 of 3-year phase-in of 2024 CMS-HCC (V28) risk model at 67/33 blend; comments due 3/1/2024 | F4: https://www.cms.gov/newsroom/fact-sheets/2025-medicare-advantage-part-d-advance-notice-fact-sheet | G4: National | H4: Forward Signal
A5: 45383 | B5: Rate Announcement | C5: MA / Part D | D5: Announced | E5: CY2025 Rate Announcement: final MA capitation rates (+3.70% avg) and Part C/D payment policies | F5: https://www.cms.gov/newsroom/fact-sheets/2026-medicare-advantage-part-d-rate-announcement | G5: National | H5: Benefit/Cost Value
A6: 45386 | B6: CMS Rule | C6: MA / Part D / D-SNP / MS / C-SNP | D6: Announced | E6: CY2025 MA & Part D Final Rule (CMS-4205-F): fixed agent/broker compensation (+$100 initial), TPMO one-to-one consent for data sharing, mid-year unused-benefits notice, SSBCI evidence requirements, dual/LIS SEP overhaul, D-SNP look-alike threshold phase-down, behavioral health network adequacy || C-SNP: this rule created both main C-SNP push factors - the look-alike phase-down (70% for 2025, 60% for 2026) and the dual/LIS SEP overhaul - while C-SNPs are exempt from both. | F6: https://www.cms.gov/newsroom/fact-sheets/contract-year-2025-medicare-advantage-part-d-final-rule-cms-4205-f ; https://www.federalregister.gov/documents/2024/04/23/2024-07105/medicare-program-changes-to-the-medicare-advantage-and-the-medicare-prescription-drug-benefit | G6: National | H6: Plan Rules/Structure
A7: 45446 | B7: Litigation | C7: MA | D7: Announced | E7: D.D.C. rules for SCAN Health Plan: CMS's 2024 Star Ratings methodology (guardrail/Tukey sequencing) violated the APA; SCAN's rating ordered recalculated; Elevance won a parallel case ~6/11 | F7: https://www.scanhealthplan.com/about-scan/press-release-archive/scan-health-plan-prevails-in-2024-star-ratings-lawsuit-against-cms | G7: National | H7: Quality Ratings
A8: 45476 | B8: Litigation | C8: MA / MS | D8: Effective | E8: N.D. Tex. (Judge O'Connor) stays the CY2025 rule's broker fixed-compensation cap and FMO contract-term restrictions before AEP 2025 - these provisions of the 4/4/2024 final rule never took effect; broker steering incentives persisted (relative MA-vs-Medigap commission economics unchanged) | F8: https://www.fiercehealthcare.com/payers/court-stops-cms-broker-compensation-rule-medicare-advantage-plans | G8: National | H8: Distribution/Commission
A9: 45482 | B9: Litigation | C9: MA | D9: Effective | E9: Following SCAN/Elevance rulings, CMS recalculates 2024 Star Ratings industry-wide: 60+ plans across 40 insurers upgraded, ~$1.4B in additional quality bonus payments (date approximate - recalc rolled out late June/early July) | F9: https://www.beckerspayer.com/payer/unitedhealthcare-beats-cms-in-medicare-advantage-star-ratings/ | G9: National | H9: Quality Ratings
A10: 45519 | B10: Rate Announcement | C10: Part D | D10: Announced | E10: CMS publishes negotiated maximum fair prices (MFPs) for the first 10 Part D drugs (effective 1/1/2026) | F10: https://www.cms.gov/files/document/10522-inflation-reduction-act-timeline.pdf | G10: National | H10: Forward Signal
A11: 45565 | B11: Enrollment Milestone | C11: MA / Part D | D11: Deadline | E11: ANOC delivery deadline, the day enrollees are actually notified of their plan's CY2025 premium, benefit, and cost-sharing changes ahead of AEP. Synchronized mass-notification shock; CY2025 ANOCs carried the post-IRA changes ($2,000 OOP cap, Prescription Payment Plan, supplemental-benefit trims), making this the date the 2025 benefit-cut news reached consumers | F11: https://www.cms.gov/medicare/health-drug-plans/managed-care-marketing/models-standard-documents-educational-materials | G11: National | H11: Shopping Cycle
A12: 45566 | B12: Enrollment Milestone | C12: MA / Part D | D12: Effective | E12: CY2025 plan marketing begins; plan landscape/benefit info for 2025 released ahead of AEP; NOTE: the stayed fixed-compensation provisions did NOT apply - per CMS 7/18/2024 memo, pre-rule compensation regs governed AEP 2024; the $100/$50 administrative add-ons were removed from the CY2025 FMV amounts, leaving only the routine annual FMV update (~+2.3%), and administrative payments remained outside the compensation cap | F12: https://www.cms.gov/newsroom/fact-sheets/contract-year-2025-medicare-advantage-part-d-final-rule-cms-4205-f | G12: National | H12: Shopping Cycle
A13: 45575 | B13: Plan Landscape Release | C13: MA / Part D / MS | D13: Announced | E13: 2025 Star Ratings published on Medicare Plan Finder: sharp industry decline - only 7 MA-PD contracts earned 5 stars (vs 38 for 2024); avg rating fell to ~3.92; drives 2026 quality bonus payments | F13: https://www.cms.gov/newsroom/fact-sheets/2025-medicare-advantage-part-d-star-ratings | G13: National | H13: Quality Ratings
... A50: 46169 | B50: Litigation | C50: MA | D50: Announced | E50: Clover v. HHS: federal court in Georgia finds CMS improperly used two groups of 10 measures in calculating Clover's 2026 Star Rating - the ruling that triggered CMS's June 2026 industry-wide recalculation (recalc itself is post-window) | F50: https://www.healthcarefinancenews.com/news/scan-alignment-sue-cms-over-medicare-advantage-star-ratings | G50: National | H50: Quality Ratings

Sheet FEMA Disasters
A1: Disaster_Num | B1: State | C1: Decl_Type | D1: Incident_Type | E1: Title | F1: Incident_Begin | G1: Incident_End | H1: Declaration_Date | I1: IA_Declared | J1: Designated_Areas | K1: SEP_Start | L1: SEP_End
A2: 4775 | B2: WA | C2: DR | D2: Severe Storm | E2: SEVERE WINTER STORMS, STRAIGHT-LINE WINDS, FLOODING, LANDSLIDES, AND MUDSLIDES | F2: 45296 | G2: 45320 | H2: 45410 | I2: FALSE | J2: 17 | K2: =IF(OR(C2="DR",C2="EM"),MIN(F2,H2),"") -> 45296 | L2: =IF(K2="","",EOMONTH(K2,2)) -> 45382
A3: 4774 | B3: KS | C3: DR | D3: Winter Storm | E3: SEVERE WINTER STORM | F3: 45299 | G3: 45307 | H3: 45410 | I3: FALSE | J3: 17 | K3: =IF(OR(C3="DR",C3="EM"),MIN(F3,H3),"") -> 45299 | L3: =IF(K3="","",EOMONTH(K3,2)) -> 45382
A4: 4764 | B4: ME | C4: DR | D4: Severe Storm | E4: SEVERE STORMS AND FLOODING | F4: 45300 | G4: 45304 | H4: 45371 | I4: FALSE | J4: 8 | K4: =IF(OR(C4="DR",C4="EM"),MIN(F4,H4),"") -> 45300 | L4: =IF(K4="","",EOMONTH(K4,2)) -> 45382
A5: 4766 | B5: RI | C5: DR | D5: Severe Storm | E5: SEVERE STORMS AND FLOODING | F5: 45300 | G5: 45304 | H5: 45371 | I5: FALSE | J5: 4 | K5: =IF(OR(C5="DR",C5="EM"),MIN(F5,H5),"") -> 45300 | L5: =IF(K5="","",EOMONTH(K5,2)) -> 45382
A6: 4770 | B6: VT | C6: DR | D6: Severe Storm | E6: SEVERE WINTER STORM | F6: 45300 | G6: 45304 | H6: 45401 | I6: FALSE | J6: 5 | K6: =IF(OR(C6="DR",C6="EM"),MIN(F6,H6),"") -> 45300 | L6: =IF(K6="","",EOMONTH(K6,2)) -> 45382
A7: 4771 | B7: NH | C7: DR | D7: Severe Storm | E7: SEVERE STORMS AND FLOODING | F7: 45300 | G7: 45305 | H7: 45401 | I7: FALSE | J7: 2 | K7: =IF(OR(C7="DR",C7="EM"),MIN(F7,H7),"") -> 45300 | L7: =IF(K7="","",EOMONTH(K7,2)) -> 45382
A8: 3604 | B8: CT | C8: EM | D8: Severe Storm | E8: SEVERE STORMS, FLOODING, AND A POTENTIAL DAM BREACH | F8: 45301 | G8: 45304 | H8: 45304 | I8: FALSE | J8: 3 | K8: =IF(OR(C8="DR",C8="EM"),MIN(F8,H8),"") -> 45301 | L8: =IF(K8="","",EOMONTH(K8,2)) -> 45382
A9: 4768 | B9: OR | C9: DR | D9: Severe Storm | E9: SEVERE WINTER STORMS, STRAIGHT-LINE WINDS, LANDSLIDES, AND MUDSLIDES | F9: 45301 | G9: 45313 | H9: 45395 | I9: FALSE | J9: 13 | K9: =IF(OR(C9="DR",C9="EM"),MIN(F9,H9),"") -> 45301 | L9: =IF(K9="","",EOMONTH(K9,2)) -> 45382
A10: 4758 | B10: CA | C10: DR | D10: Flood | E10: SEVERE STORM AND FLOODING | F10: 45312 | G10: 45314 | H10: 45341 | I10: FALSE | J10: 1 | K10: =IF(OR(C10="DR",C10="EM"),MIN(F10,H10),"") -> 45312 | L10: =IF(K10="","",EOMONTH(K10,2)) -> 45382
A11: 4773 | B11: CA | C11: DR | D11: Severe Storm | E11: SEVERE WINTER STORM | F11: 45321 | G11: 45322 | H11: 45401 | I11: FALSE | J11: 1 | K11: =IF(OR(C11="DR",C11="EM"),MIN(F11,H11),"") -> 45321 | L11: =IF(K11="","",EOMONTH(K11,2)) -> 45382
A12: 4769 | B12: CA | C12: DR | D12: Severe Storm | E12: SEVERE WINTER STORMS, TORNADOES, FLOODING, LANDSLIDES, AND MUDSLIDES | F12: 45322 | G12: 45331 | H12: 45395 | I12: FALSE | J12: 9 | K12: =IF(OR(C12="DR",C12="EM"),MIN(F12,H12),"") -> 45322 | L12: =IF(K12="","",EOMONTH(K12,2)) -> 45382
A13: 4772 | B13: CA | C13: DR | D13: Severe Storm | E13: SEVERE STORMS AND FLOODING | F13: 45322 | G13: 45331 | H13: 45401 | I13: FALSE | J13: 1 | K13: =IF(OR(C13="DR",C13="EM"),MIN(F13,H13),"") -> 45322 | L13: =IF(K13="","",EOMONTH(K13,2)) -> 45382
... A38: 4794 | B38: FL | C38: DR | D38: Severe Storm | E38: SEVERE STORMS, STRAIGHT-LINE WINDS, AND TORNADOES | F38: 45422 | G38: 45422 | H38: 45460 | I38: FALSE | J38: 13 | K38: =IF(OR(C38="DR",C38="EM"),MIN(F38,H38),"") -> 45422 | L38: =IF(K38="","",EOMONTH(K38,2)) -> 45504
A39: 5492 | B39: NM | C39: FM | D39: Fire | E39: BLUE 2 FIRE | F39: 45428 | H39: 45438 | I39: FALSE | J39: 1 | L39: =IF(K39="","",EOMONTH(K39,2))
A40: 4791 | B40: OK | C40: DR | D40: Severe Storm | E40: SEVERE STORMS, STRAIGHT-LINE WINDS, TORNADOES, AND FLOODING | F40: 45431 | G40: 45440 | H40: 45457 | I40: FALSE | J40: 10 | K40: 45504 | L40: =IF(K40="","",EOMONTH(K40,2)) -> 45565
A41: 4803 | B41: MO | C41: DR | D41: Severe Storm | E41: SEVERE STORMS, STRAIGHT-LINE WINDS, TORNADOES, AND FLOODING | F41: 45431 | G41: 45439 | H41: 45496 | I41: FALSE | J41: 15 | K41: 45504 | L41: =IF(K41="","",EOMONTH(K41,2)) -> 45565
A42: 4811 | B42: KS | C42: DR | D42: Severe Storm | E42: SEVERE STORM, STRAIGHT-LINE WINDS, TORNADOES, AND FLOODING | F42: 45431 | G42: 45431 | H42: 45524 | I42: FALSE | J42: 14 | K42: 45504 | L42: =IF(K42="","",EOMONTH(K42,2)) -> 45565
A43: 4784 | B43: IA | C43: DR | D43: Severe Storm | E43: SEVERE STORMS, TORNADOES, AND FLOODING | F43: 45432 | G43: 45443 | H43: 45436 | I43: FALSE | J43: 29 | K43: 45504 | L43: =IF(K43="","",EOMONTH(K43,2)) -> 45565
A44: 4808 | B44: NE | C44: DR | D44: Severe Storm | E44: SEVERE STORMS, STRAIGHT-LINE WINDS, TORNADOES, AND FLOODING | F44: 45432 | G44: 45446 | H44: 45524 | I44: FALSE | J44: 19 | K44: 45535 | L44: =IF(K44="","",EOMONTH(K44,2)) -> 45596
A45: 4804 | B45: KY | C45: DR | D45: Severe Storm | E45: SEVERE STORMS, STRAIGHT-LINE WINDS, TORNADOES, LANDSLIDES, AND MUDSLIDES | F45: 45433 | G45: 45439 | H45: 45496 | I45: FALSE | J45: 58 | K45: 45504 | L45: =IF(K45="","",EOMONTH(K45,2)) -> 45565
A46: 4788 | B46: AR | C46: DR | D46: Severe Storm | E46: SEVERE STORMS, STRAIGHT-LINE WINDS, TORNADOES, AND FLOODING | F46: 45436 | G46: 45439 | H46: 45442 | I46: FALSE | J46: 11 | K46: 45504 | L46: =IF(K46="","",EOMONTH(K46,2)) -> 45565
A47: 5493 | B47: AZ | C47: FM | D47: Fire | E47: SIMMONS FIRE | F47: 45440 | G47: 45443 | H47: 45441 | I47: FALSE | J47: 1 | K47: 45504 | L47: =IF(K47="","",EOMONTH(K47,2)) -> 45565
A48: 5494 | B48: NV | C48: FM | D48: Fire | E48: TRAIL FIRE | F48: 45454 | G48: 45456 | H48: 45454 | I48: FALSE | J48: 1 | K48: 45535 | L48: =IF(K48="","",EOMONTH(K48,2)) -> 45596
A49: 5495 | B49: NV | C49: FM | D49: Fire | E49: SULLIVAN FIRE | F49: 45454 | G49: 45455 | H49: 45455 | I49: FALSE | J49: 1 | K49: 45535 | L49: =IF(K49="","",EOMONTH(K49,2)) -> 45596
A50: 5496 | B50: AZ | C50: FM | D50: Fire | E50: ROSE FIRE | F50: 45455 | G50: 45457 | H50: 45455 | I50: FALSE | J50: 1 | K50: 45535 | L50: =IF(K50="","",EOMONTH(K50,2)) -> 45596
A51: 4796 | B51: IA | C51: DR | D51: Severe Storm | E51: SEVERE STORMS, FLOODING, STRAIGHT-LINE WINDS, AND TORNADOES | F51: 45459 | G51: 45496 | H51: 45467 | I51: FALSE | J51: 29 | K51: 45565 | L51: =IF(K51="","",EOMONTH(K51,2)) -> 45626
... A54: 4795 | B54: NM | C54: DR | D54: Fire | E54: SOUTH FORK FIRE, SALT FIRE, AND FLOODING | F54: 45460 | G54: 45524 | H54: 45463 | I54: FALSE | J54: 5 | K54: 45596 | L54: =IF(K54="","",EOMONTH(K54,2)) -> 45657
A55: 5497 | B55: NM | C55: FM | D55: Fire | E55: SOUTH FORK FIRE | F55: 45460 | H55: 45460 | I55: FALSE | J55: 3 | L55: =IF(K55="","",EOMONTH(K55,2))
A56: 5498 | B56: NM | C56: FM | D56: Fire | E56: SALT FIRE | F56: 45460 | H56: 45461 | I56: FALSE | J56: 3 | L56: =IF(K56="","",EOMONTH(K56,2))
A57: 4822 | B57: NE | C57: DR | D57: Severe Storm | E57: SEVERE STORMS, STRAIGHT-LINE WINDS, TORNADOES, AND FLOODING | F57: 45462 | G57: 45481 | H57: 45559 | I57: FALSE | J57: 17 | K57: 45565 | L57: =IF(K57="","",EOMONTH(K57,2)) -> 45626
A58: 4809 | B58: NM | C58: DR | D58: Flood | E58: SEVERE STORMS AND FLOODING | F58: 45463 | G58: 45464 | H58: 45524 | I58: FALSE | J58: 1 | K58: 45535 | L58: =IF(K58="","",EOMONTH(K58,2)) -> 45596
A59: 4823 | B59: WA | C59: DR | D59: Fire | E59: WILDFIRES | F59: 45465 | G59: 45481 | H59: 45559 | I59: FALSE | J59: 1 | K59: 45565 | L59: =IF(K59="","",EOMONTH(K59,2)) -> 45626
A60: 5499 | B60: WA | C60: FM | D60: Fire | E60: SLIDE RANCH FIRE | F60: 45465 | G60: 45484 | H60: 45466 | I60: FALSE | J60: 2 | K60: 45565 | L60: =IF(K60="","",EOMONTH(K60,2)) -> 45626
A61: 5500 | B61: OR | C61: FM | D61: Fire | E61: DARLENE 3 FIRE | F61: 45468 | H61: 45468 | I61: FALSE | J61: 1 | L61: =IF(K61="","",EOMONTH(K61,2))
A62: 4824 | B62: KS | C62: DR | D62: Severe Storm | E62: SEVERE STORMS, STRAIGHT-LINE WINDS, TORNADOES, AND FLOODING | F62: 45469 | G62: 45480 | H62: 45559 | I62: FALSE | J62: 17 | K62: 45565 | L62: =IF(K62="","",EOMONTH(K62,2)) -> 45626
A63: 5501 | B63: AZ | C63: FM | D63: Fire | E63: BOULDER VIEW FIRE | F63: 45471 | G63: 45473 | H63: 45471 | I63: FALSE | J63: 1 | K63: 45535 | L63: =IF(K63="","",EOMONTH(K63,2)) -> 45596
A64: 5502 | B64: CA | C64: FM | D64: Fire | E64: THOMPSON FIRE | F64: 45475 | G64: 45479 | H64: 45475 | I64: FALSE | J64: 1 | K64: 45565 | L64: =IF(K64="","",EOMONTH(K64,2)) -> 45626
A65: 5503 | B65: CA | C65: FM | D65: Fire | E65: FRENCH FIRE | F65: 45477 | G65: 45480 | H65: 45478 | I65: FALSE | J65: 1 | K65: 45565 | L65: =IF(K65="","",EOMONTH(K65,2)) -> 45626
A66: 4798 | B66: TX | C66: DR | D66: Hurricane | E66: HURRICANE BERYL | F66: 45478 | G66: 45482 | H66: 45482 | I66: FALSE | J66: 67 | K66: 45565 | L66: =IF(K66="","",EOMONTH(K66,2)) -> 45626
A67: 5504 | B67: UT | C67: FM | D67: Fire | E67: SILVER KING FIRE | F67: 45480 | G67: 45506 | H67: 45480 | I67: FALSE | J67: 1 | K67: 45596 | L67: =IF(K67="","",EOMONTH(K67,2)) -> 45657
A68: 4810 | B68: VT | C68: DR | D68: Severe Storm | E68: SEVERE STORM, FLOODING, LANDSLIDES, AND MUDSLIDES | F68: 45482 | G68: 45484 | H68: 45524 | I68: FALSE | J68: 8 | K68: 45565 | L68: =IF(K68="","",EOMONTH(K68,2)) -> 45626
A69: 5505 | B69: AZ | C69: FM | D69: Fire | E69: SHAKE FIRE | F69: 45482 | G69: 45483 | H69: 45482 | I69: FALSE | J69: 1 | K69: 45565 | L69: =IF(K69="","",EOMONTH(K69,2)) -> 45626
A70: 5507 | B70: MT | C70: FM | D70: Fire | E70: HORSE GULCH FIRE | F70: 45482 | H70: 45485 | I70: FALSE | J70: 2 | L70: =IF(K70="","",EOMONTH(K70,2))
A71: 4812 | B71: NH | C71: DR | D71: Severe Storm | E71: SEVERE STORM AND FLOODING | F71: 45483 | G71: 45486 | H71: 45524 | I71: FALSE | J71: 2 | K71: 45565 | L71: =IF(K71="","",EOMONTH(K71,2)) -> 45626
A72: 4814 | B72: NY | C72: DR | D72: Flood | E72: SEVERE STORM, TORNADOES, AND FLOODING | F72: 45483 | G72: 45484 | H72: 45533 | I72: FALSE | J72: 5 | K72: 45565 | L72: =IF(K72="","",EOMONTH(K72,2)) -> 45626
A73: 4833 | B73: AZ | C73: DR | D73: Fire | E73: WATCH FIRE | F73: 45483 | G73: 45490 | H73: 45569 | I73: FALSE | J73: 1 | K73: 45565 | L73: =IF(K73="","",EOMONTH(K73,2)) -> 45626
A74: 4854 | B74: OR | C74: DR | D74: Fire | E74: WILDFIRES | F74: 45483 | G74: 45527 | H74: 45658 | I74: FALSE | J74: 5 | K74: 45596 | L74: =IF(K74="","",EOMONTH(K74,2)) -> 45657
A75: 5506 | B75: OR | C75: FM | D75: Fire | E75: LARCH CREEK FIRE | F75: 45483 | H75: 45484 | I75: FALSE | J75: 1 | L75: =IF(K75="","",EOMONTH(K75,2))
A76: 5508 | B76: AZ | C76: FM | D76: Fire | E76: WATCH FIRE | F76: 45483 | G76: 45488 | H76: 45486 | I76: FALSE | J76: 1 | K76: 45565 | L76: =IF(K76="","",EOMONTH(K76,2)) -> 45626
A77: 4819 | B77: IL | C77: DR | D77: Flood | E77: SEVERE STORMS, TORNADOES, STRAIGHT-LINE WINDS, AND FLOODNG | F77: 45486 | G77: 45489 | H77: 45555 | I77: FALSE | J77: 7 | K77: 45565 | L77: =IF(K77="","",EOMONTH(K77,2)) -> 45626
A78: 4842 | B78: SD | C78: DR | D78: Severe Storm | E78: SEVERE STORM, STRAIGHT-LINE WINDS, AND FLOODING | F78: 45486 | G78: 45487 | H78: 45597 | I78: FALSE | J78: 1 | K78: 45565 | L78: =IF(K78="","",EOMONTH(K78,2)) -> 45626
A79: 5510 | B79: ID | C79: FM | D79: Fire | E79: TEXAS FIRE | F79: 45488 | G79: 45494 | H79: 45489 | I79: FALSE | J79: 2 | K79: 45565 | L79: =IF(K79="","",EOMONTH(K79,2)) -> 45626
A80: 5509 | B80: NV | C80: FM | D80: Fire | E80: SPRING VALLEY FIRE | F80: 45489 | G80: 45490 | H80: 45489 | I80: FALSE | J80: 1 | K80: 45565 | L80: =IF(K80="","",EOMONTH(K80,2)) -> 45626
A81: 4849 | B81: WA | C81: DR | D81: Fire | E81: WILDFIRES | F81: 45490 | G81: 45525 | H81: 45622 | I81: FALSE | J81: 1 | K81: 45596 | L81: =IF(K81="","",EOMONTH(K81,2)) -> 45657
A82: 5511 | B82: OR | C82: FM | D82: Fire | E82: LONE ROCK FIRE | F82: 45490 | H82: 45491 | I82: FALSE | J82: 3 | L82: =IF(K82="","",EOMONTH(K82,2))
A83: 5518 | B83: WA | C83: FM | D83: Fire | E83: SWAWILLA FIRE | F83: 45490 | G83: 45494 | H83: 45497 | I83: FALSE | J83: 3 | K83: 45565 | L83: =IF(K83="","",EOMONTH(K83,2)) -> 45626
A84: 5512 | B84: OR | C84: FM | D84: Fire | E84: FALLS FIRE | F84: 45491 | H84: 45491 | I84: FALSE | J84: 2 | L84: =IF(K84="","",EOMONTH(K84,2))
A85: 5513 | B85: OR | C85: FM | D85: Fire | E85: BONEYARD FIRE | F85: 45493 | H85: 45494 | I85: FALSE | J85: 1 | L85: =IF(K85="","",EOMONTH(K85,2))
A86: 5514 | B86: OR | C86: FM | D86: Fire | E86: BATTLE MOUNTAIN FIRE COMPLEX | F86: 45494 | H86: 45494 | I86: FALSE | J86: 3 | L86: =IF(K86="","",EOMONTH(K86,2))
A87: 5515 | B87: CA | C87: FM | D87: Fire | E87: HAWARDEN FIRE | F87: 45494 | G87: 45495 | H87: 45494 | I87: FALSE | J87: 1 | K87: 45565 | L87: =IF(K87="","",EOMONTH(K87,2)) -> 45626
A88: 5516 | B88: OR | C88: FM | D88: Fire | E88: DURKEE FIRE | F88: 45494 | H88: 45495 | I88: FALSE | J88: 2 | L88: =IF(K88="","",EOMONTH(K88,2))
A89: 5517 | B89: WA | C89: FM | D89: Fire | E89: WEST WHITE SWAN FIRE | F89: 45495 | G89: 45501 | H89: 45496 | I89: FALSE | J89: 2 | K89: 45565 | L89: =IF(K89="","",EOMONTH(K89,2)) -> 45626
A90: 4813 | B90: MT | C90: DR | D90: Straight-Line Winds | E90: STRAIGHT-LINE WINDS | F90: 45497 | G90: 45497 | H90: 45527 | I90: FALSE | J90: 2 | K90: 45565 | L90: =IF(K90="","",EOMONTH(K90,2)) -> 45626
A91: 5519 | B91: CA | C91: FM | D91: Fire | E91: PARK FIRE | F91: 45497 | G91: 45524 | H91: 45498 | I91: FALSE | J91: 2 | K91: 45596 | L91: =IF(K91="","",EOMONTH(K91,2)) -> 45657
A92: 5520 | B92: ID | C92: FM | D92: Fire | E92: GWEN FIRE | F92: 45498 | G92: 45513 | H92: 45499 | I92: FALSE | J92: 3 | K92: 45596 | L92: =IF(K92="","",EOMONTH(K92,2)) -> 45657
A93: 5521 | B93: WA | C93: FM | D93: Fire | E93: RETREAT FIRE | F93: 45498 | G93: 45527 | H93: 45499 | I93: FALSE | J93: 1 | K93: 45596 | L93: =IF(K93="","",EOMONTH(K93,2)) -> 45657
A94: 5522 | B94: CA | C94: FM | D94: Fire | E94: BOREL FIRE | F94: 45498 | G94: 45514 | H94: 45500 | I94: FALSE | J94: 1 | K94: 45596 | L94: =IF(K94="","",EOMONTH(K94,2)) -> 45657
A95: 4826 | B95: VT | C95: DR | D95: Flood | E95: SEVERE STORMS, FLOODING, LANDSLIDES, AND MUDSLIDES | F95: 45502 | G95: 45504 | H95: 45561 | I95: FALSE | J95: 3 | K95: 45565 | L95: =IF(K95="","",EOMONTH(K95,2)) -> 45626
A96: 5523 | B96: WY | C96: FM | D96: Fire | E96: PLEASANT VALLEY FIRE | F96: 45503 | G96: 45508 | H96: 45503 | I96: FALSE | J96: 1 | K96: 45596 | L96: =IF(K96="","",EOMONTH(K96,2)) -> 45657
A97: 5525 | B97: CO | C97: FM | D97: Fire | E97: STONE MOUNTAIN FIRE | F97: 45503 | G97: 45534 | H97: 45504 | I97: FALSE | J97: 2 | K97: 45596 | L97: =IF(K97="","",EOMONTH(K97,2)) -> 45657
A98: 4838 | B98: NE | C98: DR | D98: Severe Storm | E98: SEVERE STORMS, STRAIGHT-LINE WINDS, TORNADOES, AND FLOODING | F98: 45504 | G98: 45504 | H98: 45586 | I98: FALSE | J98: 5 | K98: 45565 | L98: =IF(K98="","",EOMONTH(K98,2)) -> 45626
A99: 5524 | B99: CO | C99: FM | D99: Fire | E99: ALEXANDER MOUNTAIN FIRE | F99: 45504 | G99: 45513 | H99: 45504 | I99: FALSE | J99: 1 | K99: 45596 | L99: =IF(K99="","",EOMONTH(K99,2)) -> 45657
A100: 3605 | B100: FL | C100: EM | D100: Tropical Storm | E100: TROPICAL STORM DEBBY | F100: 45505 | G100: 45531 | H100: 45507 | I100: FALSE | J100: 61 | K100: 45596 | L100: =IF(K100="","",EOMONTH(K100,2)) -> 45657
... A102: 5526 | B102: CO | C102: FM | D102: Fire | E102: QUARRY FIRE | F102: 45505 | G102: 45511 | H102: 45505 | I102: FALSE | J102: 1 | K102: 45596 | L102: =IF(K102="","",EOMONTH(K102,2)) -> 45657
A103: 5527 | B103: OR | C103: FM | D103: Fire | E103: MILE MARKER 132 FIRE | F103: 45506 | H103: 45506 | I103: FALSE | J103: 1 | L103: =IF(K103="","",EOMONTH(K103,2))
A104: 3606 | B104: SC | C104: EM | D104: Tropical Storm | E104: HURRICANE DEBBY | F104: 45508 | G104: 45526 | H104: 45509 | I104: FALSE | J104: 46 | K104: 45596 | L104: =IF(K104="","",EOMONTH(K104,2)) -> 45657
A105: 3607 | B105: GA | C105: EM | D105: Tropical Storm | E105: HURRICANE DEBBY | F105: 45508 | G105: 45524 | H105: 45509 | I105: FALSE | J105: 55 | K105: 45596 | L105: =IF(K105="","",EOMONTH(K105,2)) -> 45657
A106: 4821 | B106: GA | C106: DR | D106: Tropical Storm | E106: TROPICAL STORM DEBBY | F106: 45508 | G106: 45524 | H106: 45559 | I106: FALSE | J106: 35 | K106: 45596 | L106: =IF(K106="","",EOMONTH(K106,2)) -> 45657
A107: 4835 | B107: SC | C107: DR | D107: Tropical Storm | E107: TROPICAL STORM DEBBY | F107: 45508 | G107: 45526 | H107: 45564 | I107: FALSE | J107: 14 | K107: 45596 | L107: =IF(K107="","",EOMONTH(K107,2)) -> 45657
A108: 5528 | B108: OR | C108: FM | D108: Fire | E108: ELK LANE FIRE | F108: 45508 | H108: 45510 | I108: FALSE | J108: 1 | L108: =IF(K108="","",EOMONTH(K108,2))
A109: 3608 | B109: NC | C109: EM | D109: Tropical Storm | E109: TROPICAL STORM DEBBY | F109: 45509 | G109: 45523 | H109: 45510 | I109: FALSE | J109: 74 | K109: 45596 | L109: =IF(K109="","",EOMONTH(K109,2)) -> 45657
A110: 4836 | B110: AK | C110: DR | D110: Flood | E110: FLOODING | F110: 45509 | G110: 45510 | H110: 45581 | I110: FALSE | J110: 1 | K110: 45596 | L110: =IF(K110="","",EOMONTH(K110,2)) -> 45657
A111: 4847 | B111: MT | C111: DR | D111: Severe Storm | E111: SEVERE STORM AND STRAIGHT-LINE WINDS | F111: 45510 | G111: 45510 | H111: 45610 | I111: FALSE | J111: 1 | K111: 45596 | L111: =IF(K111="","",EOMONTH(K111,2)) -> 45657
A112: 3609 | B112: VT | C112: EM | D112: Tropical Storm | E112: TROPICAL DEPRESSION DEBBY | F112: 45512 | G112: 45514 | H112: 45512 | I112: FALSE | J112: 14 | K112: 45596 | L112: =IF(K112="","",EOMONTH(K112,2)) -> 45657
A113: 4818 | B113: NY | C113: DR | D113: Tropical Storm | E113: SEVERE STORM AND FLOODING | F113: 45512 | G113: 45514 | H113: 45555 | I113: FALSE | J113: 1 | K113: 45596 | L113: =IF(K113="","",EOMONTH(K113,2)) -> 45657
A114: 4825 | B114: NY | C114: DR | D114: Tropical Storm | E114: REMNANTS OF TROPICAL STORM DEBBY | F114: 45512 | G114: 45514 | H114: 45559 | I114: FALSE | J114: 11 | K114: 45596 | L114: =IF(K114="","",EOMONTH(K114,2)) -> 45657
A115: 5529 | B115: OR | C115: FM | D115: Fire | E115: LEE FALLS FIRE | F115: 45512 | H115: 45513 | I115: FALSE | J115: 1 | L115: =IF(K115="","",EOMONTH(K115,2))
A116: 4815 | B116: PA | C116: DR | D116: Tropical Storm | E116: TROPICAL STORM DEBBY | F116: 45513 | G116: 45514 | H116: 45546 | I116: FALSE | J116: 13 | K116: 45596 | L116: =IF(K116="","",EOMONTH(K116,2)) -> 45657
A117: 5530 | B117: NV | C117: FM | D117: Fire | E117: GOLD RANCH FIRE | F117: 45515 | G117: 45517 | H117: 45516 | I117: FALSE | J117: 1 | K117: 45596 | L117: =IF(K117="","",EOMONTH(K117,2)) -> 45657
A118: 3610 | B118: PR | C118: EM | D118: Severe Storm | E118: TROPICAL STORM ERNESTO | F118: 45517 | G118: 45520 | H118: 45517 | I118: FALSE | J118: 78 | K118: 45596 | L118: =IF(K118="","",EOMONTH(K118,2)) -> 45657
A119: 3611 | B119: VI | C119: EM | D119: Tropical Storm | E119: TROPICAL STORM ERNESTO | F119: 45517 | G119: 45520 | H119: 45522 | I119: FALSE | J119: 3 | K119: 45596 | L119: =IF(K119="","",EOMONTH(K119,2)) -> 45657
A120: 4841 | B120: VI | C120: DR | D120: Tropical Storm | E120: TROPICAL STORM ERNESTO | F120: 45517 | G120: 45520 | H120: 45590 | I120: FALSE | J120: 3 | K120: 45596 | L120: =IF(K120="","",EOMONTH(K120,2)) -> 45657
A121: 4850 | B121: PR | C121: DR | D121: Tropical Storm | E121: TROPICAL STORM ERNESTO | F121: 45517 | G121: 45520 | H121: 45623 | I121: FALSE | J121: 38 | K121: 45596 | L121: =IF(K121="","",EOMONTH(K121,2)) -> 45657
A122: 4857 | B122: AK | C122: DR | D122: Severe Storm | E122: SEVERE STORM AND FLOODING | F122: 45519 | G122: 45522 | H122: 45667 | I122: FALSE | J122: 1 | K122: 45596 | L122: =IF(K122="","",EOMONTH(K122,2)) -> 45657
A123: 4853 | B123: AK | C123: DR | D123: Severe Storm | E123: SEVERE STORM AND FLOODING | F123: 45520 | G123: 45522 | H123: 45658 | I123: FALSE | J123: 1 | K123: 45596 | L123: =IF(K123="","",EOMONTH(K123,2)) -> 45657
A124: 3612 | B124: CT | C124: EM | D124: Severe Storm | E124: SEVERE STORMS, FLOODING, LANDSLIDES, AND MUDSLIDES | F124: 45522 | G124: 45523 | H124: 45525 | I124: FALSE | J124: 3 | K124: 45596 | L124: =IF(K124="","",EOMONTH(K124,2)) -> 45657
A125: 3613 | B125: NY | C125: EM | D125: Severe Storm | E125: SEVERE STORM AND FLOODING | F125: 45522 | G125: 45523 | H125: 45529 | I125: FALSE | J125: 1 | K125: 45596 | L125: =IF(K125="","",EOMONTH(K125,2)) -> 45657
A126: 4820 | B126: CT | C126: DR | D126: Severe Storm | E126: SEVERE STORM, FLOODING, LANDSLIDES, AND MUDSLIDES | F126: 45522 | G126: 45523 | H126: 45555 | I126: FALSE | J126: 3 | K126: 45596 | L126: =IF(K126="","",EOMONTH(K126,2)) -> 45657
A127: 4839 | B127: NY | C127: DR | D127: Severe Storm | E127: SEVERE STORM AND FLOODING | F127: 45522 | G127: 45523 | H127: 45586 | I127: FALSE | J127: 3 | K127: 45596 | L127: =IF(K127="","",EOMONTH(K127,2)) -> 45657
...

Sheet Fed Register
A1: Doc_Number | B1: Type | C1: Pub_Date | D1: Effective_Date | E1: Match | F1: Matched_Keywords | G1: Title | H1: Abstract | I1: URL | J1: Full_Text_Scanned | K1: Priority | L1: Trim_Note
A2: 2023-28831 | B2: Notice | C2: 45293 | E2: 0 | G2: Medicare and Medicaid Programs; Application from the Community Health Accreditation Program (CHAP) for Continued Approval of Its Home Health Agency Accreditation Program | H2: This notice announces our decision to approve the Community Health Accreditation Program (CHAP) for continued recognition as a national accrediting organization for home health agencies (HHAs) that wish to participate in the Medicare or Medicaid programs. | I2: https://www.federalregister.gov/documents/2024/01/02/2023-28831/medicare-and-medicaid-programs-application-from-the-community-health-accreditation-program-chap-for | J2: Y
A3: 2024-00205 | B3: Notice | C3: 45300 | E3: 0 | G3: Medicaid and Children's Health Insurance Program (CHIP) Generic Information Collection Activities: Proposed Collection; Comment Request | H3: On May 28, 2010, the Office of Management and Budget (OMB) issued Paperwork Reduction Act (PRA) guidance related to the "generic" clearance process. Generally, this is an expedited process by which agencies may obtain OMB's approval of collection of information requests that are "usually voluntary, low-burden, and uncontroversial collections," do not raise any substantive or policy issues, and do not require policy or methodological review. The process requires the submission of an overarching p | I3: https://www.federalregister.gov/documents/2024/01/09/2024-00205/medicaid-and-childrens-health-insurance-program-chip-generic-information-collection-activities | J3: Y
A4: 2024-00270 | B4: Notice | C4: 45301 | E4: 0 | G4: Agency Information Collection Activities: Proposed Collection; Comment Request | H4: The Centers for Medicare & Medicaid Services (CMS) is announcing an opportunity for the public to comment on CMS' intention to collect information from the public. Under the Paperwork Reduction Act of 1995 (PRA), Federal agencies are required to publish notice in the Federal Register concerning each proposed collection of information (including each proposed extension or reinstatement of an existing collection of information) and to allow 60 days for public comment on the proposed action. Intere | I4: https://www.federalregister.gov/documents/2024/01/10/2024-00270/agency-information-collection-activities-proposed-collection-comment-request | J4: Y
A5: 2024-00474 | B5: Notice | C5: 45302 | E5: 1 | F5: part d(4); medicare advantage(1) | G5: Agency Information Collection Activities: Submission for OMB Review; Comment Request | H5: The Centers for Medicare & Medicaid Services (CMS) is announcing an opportunity for the public to comment on CMS' intention to collect information from the public. Under the Paperwork Reduction Act of 1995 (PRA), Federal agencies are required to publish notice in the Federal Register concerning each proposed collection of information, including each proposed extension or reinstatement of an existing collection of information, and to allow a second opportunity for public comment on the notice. In | I5: https://www.federalregister.gov/documents/2024/01/11/2024-00474/agency-information-collection-activities-submission-for-omb-review-comment-request | J5: Y | K5: SKIP | L5: PRA paperwork notice
A6: 2024-00657 | B6: Notice | C6: 45307 | E6: 1 | F6: dual eligible(3) | G6: Agency Information Collection Activities: Submission for OMB Review; Comment Request | H6: The Centers for Medicare & Medicaid Services (CMS) is announcing an opportunity for the public to comment on CMS' intention to collect information from the public. Under the Paperwork Reduction Act of 1995 (PRA), federal agencies are required to publish notice in the Federal Register concerning each proposed collection of information, including each proposed extension or reinstatement of an existing collection of information, and to allow a second opportunity for public comment on the notice. In | I6: https://www.federalregister.gov/documents/2024/01/16/2024-00657/agency-information-collection-activities-submission-for-omb-review-comment-request | J6: Y | K6: SKIP | L6: PRA paperwork notice
A7: 2024-00897 | B7: Notice | C7: 45309 | E7: 1 | F7: ma organization(6); part c(1) | G7: Agency Information Collection Activities: Submission for OMB Review; Comment Request | H7: The Centers for Medicare & Medicaid Services (CMS) is announcing an opportunity for the public to comment on CMS' intention to collect information from the public. Under the Paperwork Reduction Act of 1995 (PRA), federal agencies are required to publish notice in the Federal Register concerning each proposed collection of information, including each proposed extension or reinstatement of an existing collection of information, and to allow a second opportunity for public comment on the notice. In | I7: https://www.federalregister.gov/documents/2024/01/18/2024-00897/agency-information-collection-activities-submission-for-omb-review-comment-request | J7: Y | K7: SKIP | L7: PRA paperwork notice
A8: 2024-01072 | B8: Proposed Rule | C8: 45313 | D8: 45233 | E8: 0 | G8: Federal Independent Dispute Resolution Operations; Reopening of Comment Period | H8: This document reopens the comment period for the proposed rules entitled "Federal Independent Dispute Resolution Operations" that appeared in the November 3, 2023, issue of the Federal Register. The comment period for the proposed rules, which closed on January 2, 2024, is reopened from January 22, 2024 to February 5, 2024. | I8: https://www.federalregister.gov/documents/2024/01/22/2024-01072/federal-independent-dispute-resolution-operations-reopening-of-comment-period | J8: Y
A9: 2024-01383 | B9: Notice | C9: 45316 | E9: 1 | F9: medicare advantage(2) | G9: Agency Information Collection Activities: Submission for OMB Review; Comment Request | H9: The Centers for Medicare & Medicaid Services (CMS) is announcing an opportunity for the public to comment on CMS' intention to collect information from the public. Under the Paperwork Reduction Act of 1995 (PRA), Federal agencies are required to publish notice in the Federal Register concerning each proposed collection of information, including each proposed extension or reinstatement of an existing collection of information, and to allow a second opportunity for public comment on the notice. In | I9: https://www.federalregister.gov/documents/2024/01/25/2024-01383/agency-information-collection-activities-submission-for-omb-review-comment-request | J9: Y | K9: SKIP | L9: PRA paperwork notice
A10: 2024-01582 | B10: Notice | C10: 45317 | E10: 1 | F10: part d(8); medicare advantage(4); part c(2) | G10: Agency Information Collection Activities: Proposed Collection; Comment Request | H10: The Centers for Medicare & Medicaid Services (CMS) is announcing an opportunity for the public to comment on CMS' intention to collect information from the public. Under the Paperwork Reduction Act of 1995 (PRA), federal agencies are required to publish notice in the Federal Register concerning each proposed collection of information (including each proposed extension or reinstatement of an existing collection of information) and to allow 60 days for public comment on the proposed action. Intere | I10: https://www.federalregister.gov/documents/2024/01/26/2024-01582/agency-information-collection-activities-proposed-collection-comment-request | J10: Y | K10: SKIP | L10: PRA paperwork notice
A11: 2024-01723 | B11: Notice | C11: 45320 | E11: 1 | F11: part d(10) | G11: Agency Information Collection Activities: Proposed Collection; Comment Request | H11: The Centers for Medicare & Medicaid Services (CMS) is announcing an opportunity for the public to comment on CMS' intention to collect information from the public. Under the Paperwork Reduction Act of 1995 (PRA), Federal agencies are required to publish notice in the Federal Register concerning each proposed collection of information (including each proposed extension or reinstatement of an existing collection of information) and to allow 60 days for public comment on the proposed action. Intere | I11: https://www.federalregister.gov/documents/2024/01/29/2024-01723/agency-information-collection-activities-proposed-collection-comment-request | J11: Y | K11: SKIP | L11: PRA paperwork notice
A12: 2024-01785 | B12: Notice | C12: 45321 | E12: 1 | F12: medicare advantage(2); part d(1) | G12: Medicare and Medicaid Programs; Quarterly Listing of Program Issuances-October Through December 2023 | H12: This quarterly notice lists CMS manual instructions, substantive and interpretive regulations, and other Federal Register notices that were published in the 3-month period, relating to the Medicare and Medicaid programs and other programs administered by CMS. | I12: https://www.federalregister.gov/documents/2024/01/30/2024-01785/medicare-and-medicaid-programs-quarterly-listing-of-program-issuances-october-through-december-2023 | J12: Y | K12: SKIP | L12: catalog of issuances
A13: 2024-00895 | B13: Rule | C13: 45330 | D13: 45390 | E13: 1 | F13: ma organization(237); part d(26); medicare advantage(15); d-snp(11); part c(9); special needs plan(4); dual eligible(2) | G13: Medicare and Medicaid Programs; Patient Protection and Affordable Care Act; Advancing Interoperability and Improving Prior Authorization Processes for Medicare Advantage Organizations, Medicaid Managed Care Plans, State Medicaid Agencies, Children's Health Insurance Program (CHIP) Agencies and CHIP Managed Care Entities, Issuers of Qualified Health Plans on the Federally-Facilitated Exchanges, Merit-Based Incentive Payment System (MIPS) Eligible Clinicians, and Eligible Hospitals and Critical Access Hospitals in the Medicare Promoting Interoperability Program | H13: This final rule will improve the electronic exchange of health care data and streamline processes related to prior authorization through new requirements for Medicare Advantage (MA) organizations, state Medicaid fee-for-service (FFS) programs, state Children's Health Insurance Program (CHIP) FFS programs, Medicaid managed care plans, CHIP managed care entities, and Qualified Health Plan (QHP) issuers on the Federally-facilitated Exchanges (FFEs). This final rule will also add new measures for el | I13: https://www.federalregister.gov/documents/2024/02/08/2024-00895/medicare-and-medicaid-programs-patient-protection-and-affordable-care-act-advancing-interoperability | J13: Y | K13: HIGH | L13: core MA/Part D policy doc (strong kw=269)
A14: 2024-01094 | B14: Rule | C14: 45322 | D14: 45322 | E14: 0 | G14: Medicare Program; Calendar Year (CY) 2024 Home Health (HH) Prospective Payment System Rate Update; HH Quality Reporting Program Requirements; HH Value-Based Purchasing Expanded Model Requirements; Home Intravenous Immune Globulin Items and Services; Hospice Informal Dispute Resolution and Special Focus Program Requirements, Certain Requirements for Durable Medical Equipment Prosthetics and Orthotics Supplies; and Provider and Supplier Enrollment Requirements; Correction | H14: This document corrects technical errors in the final rule that appeared in the November 13, 2023 Federal Register titled "Medicare Program; Calendar Year (CY) 2024 Home Health (HH) Prospective Payment System Rate Update; HH Quality Reporting Program Requirements; HH Value-Based Purchasing Expanded Model Requirements; Home Intravenous Immune Globulin Items and Services; Hospice Informal Dispute Resolution and Special Focus Program Requirements, Certain Requirements for Durable Medical Equipment P | I14: https://www.federalregister.gov/documents/2024/01/31/2024-01094/medicare-program-calendar-year-cy-2024-home-health-hh-prospective-payment-system-rate-update-hh | J14: Y
A15: 2024-01831 | B15: Notice | C15: 45322 | E15: 0 | G15: Agency Information Collection Activities: Proposed Collection; Comment Request | H15: The Centers for Medicare & Medicaid Services (CMS) is announcing an opportunity for the public to comment on CMS' intention to collect information from the public. Under the Paperwork Reduction Act of 1995 (PRA), Federal agencies are required to publish notice in the Federal Register concerning each proposed collection of information (including each proposed extension or reinstatement of an existing collection of information) and to allow 60 days for public comment on the proposed action. Intere | I15: https://www.federalregister.gov/documents/2024/01/31/2024-01831/agency-information-collection-activities-proposed-collection-comment-request | J15: Y
A16: 2024-01942 | B16: Rule | C16: 45323 | D16: 45318 | E16: 0 | G16: Clinical Laboratory Improvement Amendments of 1988 (CLIA) Fees; Histocompatibility, Personnel, and Alternative Sanctions for Certificate of Waiver Laboratories; Correction | H16: This document corrects technical and typographical errors in the final rule that appeared in the December 28, 2023, Federal Register entitled, "Clinical Laboratory Improvement Amendments of 1988 (CLIA) Fees; Histocompatibility, Personnel, and Alternative Sanctions for Certificate of Waiver Laboratories" (referred to hereafter as the "December 2023 final rule"). | I16: https://www.federalregister.gov/documents/2024/02/01/2024-01942/clinical-laboratory-improvement-amendments-of-1988-clia-fees-histocompatibility-personnel-and | J16: Y
A17: 2024-02095 | B17: Notice | C17: 45324 | E17: 1 | F17: part d(5); part c(1) | G17: Agency Information Collection Activities: Proposed Collection; Comment Request | H17: The Centers for Medicare & Medicaid Services (CMS) is announcing an opportunity for the public to comment on CMS' intention to collect information from the public. Under the Paperwork Reduction Act of 1995 (PRA), Federal agencies are required to publish notice in the Federal Register concerning each proposed collection of information (including each proposed extension or reinstatement of an existing collection of information) and to allow 60 days for public comment on the proposed action. Intere | I17: https://www.federalregister.gov/documents/2024/02/02/2024-02095/agency-information-collection-activities-proposed-collection-comment-request | J17: Y | K17: SKIP | L17: PRA paperwork notice
A18: 2024-02243 | B18: Notice | C18: 45327 | E18: 0 | G18: Agency Information Collection Activities: Proposed Collection; Comment Request | H18: On May 28, 2010, the Office of Management and Budget (OMB) issued Paperwork Reduction Act (PRA) guidance related to the "generic" clearance process. Generally, this is an expedited clearance process by which agencies may obtain OMB's approval of collection of information requests that are "usually voluntary, low- burden, and uncontroversial," do not raise any substantive or policy issues, and do not require policy or methodological review. The process requires the submission of an overarching pl | I18: https://www.federalregister.gov/documents/2024/02/05/2024-02243/agency-information-collection-activities-proposed-collection-comment-request | J18: Y
A19: 2024-02306 | B19: Notice | C19: 45328 | E19: 1 | F19: ma organization(2) | G19: Agency Information Collection Activities: Submission for OMB Review; Comment Request | H19: The Centers for Medicare & Medicaid Services (CMS) is announcing an opportunity for the public to comment on CMS' intention to collect information from the public. Under the Paperwork Reduction Act of 1995 (PRA), Federal agencies are required to publish notice in the Federal Register concerning each proposed collection of information, including each proposed extension or reinstatement of an existing collection of information, and to allow a second opportunity for public comment on the notice. In | I19: https://www.federalregister.gov/documents/2024/02/06/2024-02306/agency-information-collection-activities-submission-for-omb-review-comment-request | J19: Y | K19: SKIP | L19: PRA paperwork notice
A20: 2024-02342 | B20: Notice | C20: 45328 | E20: 0 | G20: Medicare and Medicaid Programs; Application by DNV Healthcare USA Inc. (DNV) for Continued CMS Approval of Its Psychiatric Hospital Accreditation Program | H20: This proposed notice acknowledges the receipt of a deeming application from DNV Healthcare USA Inc. (DNV) for continued Centers for Medicare & Medicaid Services (CMS) approval of its psychiatric hospital accreditation program. The statute requires that within 60 days of receipt of an organization's complete application, CMS must publish a notice that identifies the national accrediting body making the request, describes the nature of the request, and provides at least a 30-day public comment per | I20: https://www.federalregister.gov/documents/2024/02/06/2024-02342/medicare-and-medicaid-programs-application-by-dnv-healthcare-usa-inc-dnv-for-continued-cms-approval | J20: Y
A21: 2024-02444 | B21: Notice | C21: 45329 | E21: 1 | F21: medicare advantage(2); part d(2) | G21: Agency Information Collection Activities: Proposed Collection; Comment Request | H21: The Centers for Medicare & Medicaid Services (CMS) is announcing an opportunity for the public to comment on CMS' intention to collect information from the public. Under the Paperwork Reduction Act of 1995 (PRA), federal agencies are required to publish notice in the Federal Register concerning each proposed collection of information (including each proposed extension or reinstatement of an existing collection of information) and to allow 60 days for public comment on the proposed action. Intere | I21: https://www.federalregister.gov/documents/2024/02/07/2024-02444/agency-information-collection-activities-proposed-collection-comment-request | J21: Y | K21: SKIP | L21: PRA paperwork notice
A22: 2024-02445 | B22: Notice | C22: 45329 | E22: 0 | G22: Agency Information Collection Activities: Submission for OMB Review; Comment Request | H22: The Centers for Medicare & Medicaid Services (CMS) is announcing an opportunity for the public to comment on CMS' intention to collect information from the public. Under the Paperwork Reduction Act of 1995 (PRA), federal agencies are required to publish notice in the Federal Register concerning each proposed collection of information, including each proposed extension or reinstatement of an existing collection of information, and to allow a second opportunity for public comment on the notice. In | I22: https://www.federalregister.gov/documents/2024/02/07/2024-02445/agency-information-collection-activities-submission-for-omb-review-comment-request | J22: Y
A23: 2024-07105 | B23: Rule | C23: 45405 | D23: 45446 | E23: 1 | F23: part d(1594); d-snp(1275); ma organization(1179); c-snp(230); part c(202); medicare advantage(128); special needs plan(76); dual eligible(62); medigap(10); medicare supplement(2) | G23: Medicare Program; Changes to the Medicare Advantage and the Medicare Prescription Drug Benefit Program for Contract Year 2024-Remaining Provisions and Contract Year 2025 Policy and Technical Changes to the Medicare Advantage Program, Medicare Prescription Drug Benefit Program, Medicare Cost Plan Program, and Programs of All-Inclusive Care for the Elderly (PACE) | H23: This final rule will revise the Medicare Advantage (Part C), Medicare Prescription Drug Benefit (Part D), Medicare cost plan, and Programs of All-Inclusive Care for the Elderly (PACE) regulations to implement changes related to Star Ratings, marketing and communications, agent/broker compensation, health equity, dual eligible special needs plans (D-SNPs), utilization management, network adequacy, and other programmatic areas. This final rule also codifies existing sub-regulatory guidance in the | I23: https://www.federalregister.gov/documents/2024/04/23/2024-07105/medicare-program-changes-to-the-medicare-advantage-and-the-medicare-prescription-drug-benefit | J23: Y | K23: HIGH | L23: core MA/Part D policy doc (strong kw=2962)
A24: 2024-02631 | B24: Rule | C24: 45331 | D24: 45331 | E24: 0 | G24: Medicare Program: Hospital Outpatient Prospective Payment and Ambulatory Surgical Center Payment Systems; Quality Reporting Programs; Payment for Intensive Outpatient Services in Hospital Outpatient Departments, Community Mental Health Centers, Rural Health Clinics, Federally Qualified Health Centers, and Opioid Treatment Programs; Hospital Price Transparency; Changes to Community Mental Health Centers Conditions of Participation, Changes to the Inpatient Prospective Payment System Medicare Code Editor; Rural Emergency Hospital Conditions of Participation Technical Correction; Correction | H24: This document corrects technical and typographical errors in the final rule with comment period that appeared in the Federal Register on November 22, 2023, titled "Medicare Program: Hospital Outpatient Prospective Payment and Ambulatory Surgical Center Payment Systems; Quality Reporting Programs; Payment for Intensive Outpatient Services in Hospital Outpatient Departments, Community Mental Health Centers, Rural Health Clinics, Federally Qualified Health Centers, and Opioid Treatment Programs; Ho | I24: https://www.federalregister.gov/documents/2024/02/09/2024-02631/medicare-program-hospital-outpatient-prospective-payment-and-ambulatory-surgical-center-payment | J24: Y
A25: 2024-02662 | B25: Notice | C25: 45331 | E25: 0 | G25: Agency Information Collection Activities: Proposed Collection; Comment Request | H25: The Centers for Medicare & Medicaid Services (CMS) is announcing an opportunity for the public to comment on CMS' intention to collect information from the public. Under the Paperwork Reduction Act of 1995 (PRA), Federal agencies are required to publish notice in the Federal Register concerning each proposed collection of information (including each proposed extension or reinstatement of an existing collection of information) and to allow 60 days for public comment on the proposed action. Intere | I25: https://www.federalregister.gov/documents/2024/02/09/2024-02662/agency-information-collection-activities-proposed-collection-comment-request | J25: Y
A26: 2024-02705 | B26: Rule | C26: 45334 | D26: 45334 | E26: 1 | F26: medicare advantage(2) | G26: Medicare and Medicaid Programs; CY 2024 Payment Policies Under the Physician Fee Schedule and Other Changes to Part B Payment and Coverage Policies; Medicare Shared Savings Program Requirements; Medicare Advantage; Medicare and Medicaid Provider and Supplier Enrollment Policies; and Basic Health Program; Corrections | H26: This document corrects technical and typographical errors in the final rule that appeared in the November 16, 2023 issue of the Federal Register, entitled "Medicare and Medicaid Programs; CY 2024 Payment Policies Under the Physician Fee Schedule and Other Changes to Part B Payment and Coverage Policies; Medicare Shared Savings Program Requirements; Medicare Advantage; Medicare and Medicaid Provider and Supplier Enrollment Policies; and Basic Health Program" (referred to hereafter as the "CY 2024 | I26: https://www.federalregister.gov/documents/2024/02/12/2024-02705/medicare-and-medicaid-programs-cy-2024-payment-policies-under-the-physician-fee-schedule-and-other | J26: Y | K26: SKIP | L26: provider payment rule (MA mentions incidental)
A27: 2024-02137 | B27: Proposed Rule | C27: 45337 | E27: 0 | G27: Medicare Program; Strengthening Oversight of Accrediting Organizations (AOs) and Preventing AO Conflict of Interest, and Related Provisions | H27: This proposed rule would set forth a number of provisions to strengthen the oversight of accrediting organizations (AOs) by addressing conflicts of interest, establishing consistent standards, processes and definitions, and updating the validation and performance standards systems. Additionally, this proposed rule would revise the psychiatric hospital survey process, add a limitation on terminated deemed providers and suppliers when reentering the program, and provides technical corrections for | I27: https://www.federalregister.gov/documents/2024/02/15/2024-02137/medicare-program-strengthening-oversight-of-accrediting-organizations-aos-and-preventing-ao-conflict | J27: Y
A28: 2024-03294 | B28: Notice | C28: 45338 | E28: 0 | G28: Agency Information Collection Activities: Proposed Collection; Comment Request | H28: The Centers for Medicare & Medicaid Services (CMS) is announcing an opportunity for the public to comment on CMS' intention to collect information from the public. Under the Paperwork Reduction Act of 1995 (PRA), Federal agencies are required to publish notice in the Federal Register concerning each proposed collection of information (including each proposed extension or reinstatement of an existing collection of information) and to allow 60 days for public comment on the proposed action. Intere | I28: https://www.federalregister.gov/documents/2024/02/16/2024-03294/agency-information-collection-activities-proposed-collection-comment-request | J28: Y
A29: 2024-03344 | B29: Notice | C29: 45342 | E29: 1 | F29: medicare advantage(3); part c(3) | G29: Agency Information Collection Activities: Submission for OMB Review; Comment Request | H29: The Centers for Medicare & Medicaid Services (CMS) is announcing an opportunity for the public to comment on CMS' intention to collect information from the public. Under the Paperwork Reduction Act of 1995 (PRA), Federal agencies are required to publish notice in the Federal Register concerning each proposed collection of information, including each proposed extension or reinstatement of an existing collection of information, and to allow a second opportunity for public comment on the notice. In | I29: https://www.federalregister.gov/documents/2024/02/20/2024-03344/agency-information-collection-activities-submission-for-omb-review-comment-request | J29: Y | K29: SKIP | L29: PRA paperwork notice
A30: 2024-03348 | B30: Notice | C30: 45342 | E30: 0 | G30: Agency Information Collection Activities: Proposed Collection; Comment Request | H30: The Centers for Medicare & Medicaid Services (CMS) is announcing an opportunity for the public to comment on CMS' intention to collect information from the public. Under the Paperwork Reduction Act of 1995 (PRA), Federal agencies are required to publish notice in the Federal Register concerning each proposed collection of information (including each proposed extension or reinstatement of an existing collection of information) and to allow 60 days for public comment on the proposed action. Intere | I30: https://www.federalregister.gov/documents/2024/02/20/2024-03348/agency-information-collection-activities-proposed-collection-comment-request | J30: Y
A31: 2024-03363 | B31: Notice | C31: 45342 | E31: 0 | G31: Agency Information Collection Activities: Submission for OMB Review; Comment Request | H31: The Centers for Medicare & Medicaid Services (CMS) is announcing an opportunity for the public to comment on CMS' intention to collect information from the public. Under the Paperwork Reduction Act of 1995 (PRA), Federal agencies are required to publish notice in the Federal Register concerning each proposed collection of information, including each proposed extension or reinstatement of an existing collection of information, and to allow a second opportunity for public comment on the notice. In | I31: https://www.federalregister.gov/documents/2024/02/20/2024-03363/agency-information-collection-activities-submission-for-omb-review-comment-request | J31: Y
A32: 2024-03476 | B32: Notice | C32: 45343 | E32: 0 | G32: Agency Information Collection Activities: Submission for OMB Review; Comment Request | H32: The Centers for Medicare & Medicaid Services (CMS) is announcing an opportunity for the public to comment on CMS' intention to collect information from the public. Under the Paperwork Reduction Act of 1995 (PRA), federal agencies are required to publish notice in the Federal Register concerning each proposed collection of information, including each proposed extension or reinstatement of an existing collection of information, and to allow a second opportunity for public comment on the notice. In | I32: https://www.federalregister.gov/documents/2024/02/21/2024-03476/agency-information-collection-activities-submission-for-omb-review-comment-request | J32: Y
A33: 2024-03542 | B33: Rule | C33: 45345 | D33: 45405 | E33: 1 | F33: dual eligible(1) | G33: Medicaid Program; Disproportionate Share Hospital Third-Party Payer Rule | H33: This final rule primarily addresses recent legislative changes to the Social Security Act as a result of the Consolidated Appropriations Act, 2021 changes to the hospital-specific limit on Medicaid disproportionate share hospital (DSH) payments. This final rule affords States and hospitals more clarity on how the limit, the changes that took effect on October 1, 2021, will be calculated. Additionally, this final rule enhances administrative efficiency by making technical changes and clarificatio | I33: https://www.federalregister.gov/documents/2024/02/23/2024-03542/medicaid-program-disproportionate-share-hospital-third-party-payer-rule | J33: Y | K33: SKIP | L33: provider payment rule (MA mentions incidental)
A34: 2024-03675 | B34: Notice | C34: 45345 | E34: 0 | G34: Agency Information Collection Activities: Submission for OMB Review; Comment Request | H34: The Centers for Medicare & Medicaid Services (CMS) is announcing an opportunity for the public to comment on CMS' intention to collect information from the public. Under the Paperwork Reduction Act of 1995 (PRA), federal agencies are required to publish notice in the Federal Register concerning each proposed collection of information, including each proposed extension or reinstatement of an existing collection of information, and to allow a second opportunity for public comment on the notice. In | I34: https://www.federalregister.gov/documents/2024/02/23/2024-03675/agency-information-collection-activities-submission-for-omb-review-comment-request | J34: Y
A35: 2024-03676 | B35: Notice | C35: 45345 | E35: 0 | G35: Agency Information Collection Activities: Proposed Collection; Comment Request | H35: The Centers for Medicare & Medicaid Services (CMS) is announcing an opportunity for the public to comment on CMS' intention to collect information from the public. Under the Paperwork Reduction Act of 1995 (PRA), Federal agencies are required to publish notice in the Federal Register concerning each proposed collection of information (including each proposed extension or reinstatement of an existing collection of information) and to allow 60 days for public comment on the proposed action. Intere | I35: https://www.federalregister.gov/documents/2024/02/23/2024-03676/agency-information-collection-activities-proposed-collection-comment-request | J35: Y
A36: 2024-03821 | B36: Notice | C36: 45348 | E36: 0 | G36: Medicare and Medicaid Programs; Application From the Joint Commission for Continued CMS-Approval of Its Ambulatory Surgical Center Accreditation Program | H36: This notice acknowledges the receipt of an application from the Joint Commission for continued recognition as a national accrediting organization for Ambulatory Surgical Centers that wish to participate in the Medicare or Medicaid programs. | I36: https://www.federalregister.gov/documents/2024/02/26/2024-03821/medicare-and-medicaid-programs-application-from-the-joint-commission-for-continued-cms-approval-of | J36: Y
A37: 2024-03866 | B37: Notice | C37: 45348 | E37: 0 | G37: Agency Information Collection Activities: Submission for OMB Review; Comment Request | H37: The Centers for Medicare & Medicaid Services (CMS) is announcing an opportunity for the public to comment on CMS' intention to collect information from the public. Under the Paperwork Reduction Act of 1995 (PRA), Federal agencies are required to publish notice in the Federal Register concerning each proposed collection of information, including each proposed extension or reinstatement of an existing collection of information, and to allow a second opportunity for public comment on the notice. In | I37: https://www.federalregister.gov/documents/2024/02/26/2024-03866/agency-information-collection-activities-submission-for-omb-review-comment-request | J37: Y
A38: 2024-04151 | B38: Notice | C38: 45351 | E38: 0 | G38: Agency Information Collection Activities: Proposed Collection; Comment Request | H38: The Centers for Medicare & Medicaid Services (CMS) is announcing an opportunity for the public to comment on CMS' intention to collect information from the public. Under the Paperwork Reduction Act of 1995 (PRA), federal agencies are required to publish notice in the Federal Register concerning each proposed collection of information (including each proposed extension or reinstatement of an existing collection of information) and to allow 60 days for public comment on the proposed action. Intere | I38: https://www.federalregister.gov/documents/2024/02/29/2024-04151/agency-information-collection-activities-proposed-collection-comment-request | J38: Y
A39: 2024-04302 | B39: Notice | C39: 45351 | E39: 1 | F39: part d(4); medicare advantage(2); part c(2); ma organization(1) | G39: Agency Information Collection Activities: Proposed Collection; Comment Request | H39: The Centers for Medicare & Medicaid Services (CMS) is announcing an opportunity for the public to comment on CMS' intention to collect information from the public. Under the Paperwork Reduction Act of 1995 (PRA), Federal agencies are required to publish notice in the Federal Register concerning each proposed collection of information (including each proposed extension or reinstatement of an existing collection of information) and to allow 60 days for public comment on the proposed action. Intere | I39: https://www.federalregister.gov/documents/2024/02/29/2024-04302/agency-information-collection-activities-proposed-collection-comment-request | J39: Y | K39: SKIP | L39: PRA paperwork notice
A40: 2024-04341 | B40: Notice | C40: 45352 | E40: 1 | F40: part d(5) | G40: Agency Information Collection Activities: Submission for OMB Review; Comment Request | H40: The Centers for Medicare & Medicaid Services (CMS) is announcing an opportunity for the public to comment on CMS' intention to collect information from the public. Under the Paperwork Reduction Act of 1995 (PRA), Federal agencies are required to publish notice in the Federal Register concerning each proposed collection of information, including each proposed extension or reinstatement of an existing collection of information, and to allow a second opportunity for public comment on the notice. In | I40: https://www.federalregister.gov/documents/2024/03/01/2024-04341/agency-information-collection-activities-submission-for-omb-review-comment-request | J40: Y | K40: SKIP | L40: PRA paperwork notice
A41: 2024-04517 | B41: Notice | C41: 45355 | E41: 1 | F41: part c(2) | G41: National Plan and Provider Enumeration System (NPPES) Data Changes | H41: This notice provides information on changes to data elements that providers are required to submit to the National Plan and Provider Enumeration System (NPPES) to obtain and maintain a National Provider Identifier (NPI). The changes to the required data elements affect the data that is made available to the public from NPPES in downloadable files and in a query-only database on the internet. | I41: https://www.federalregister.gov/documents/2024/03/04/2024-04517/national-plan-and-provider-enumeration-system-nppes-data-changes | J41: Y | K41: SKIP | L41: admin systems notice
A42: 2024-04590 | B42: Rule | C42: 45356 | D42: 45356 | E42: 0 | G42: Clinical Laboratory Improvement Amendments of 1988 (CLIA) Fees; Histocompatibility, Personnel, and Alternative Sanctions for Certificate of Waiver Laboratories; Correction | H42: This document corrects technical and typographical errors in the final rule that appeared in the December 28, 2023, Federal Register entitled, "Clinical Laboratory Improvement Amendments of 1988 (CLIA) Fees; Histocompatibility, Personnel, and Alternative Sanctions for Certificate of Waiver Laboratories" (referred to hereafter as the "December 2023 final rule"). | I42: https://www.federalregister.gov/documents/2024/03/05/2024-04590/clinical-laboratory-improvement-amendments-of-1988-clia-fees-histocompatibility-personnel-and | J42: Y
A43: 2024-04591 | B43: Notice | C43: 45356 | E43: 0 | G43: Agency Information Collection Activities: Submission for OMB Review; Comment Request | H43: The Centers for Medicare & Medicaid Services (CMS) is announcing an opportunity for the public to comment on CMS' intention to collect information from the public. Under the Paperwork Reduction Act of 1995 (PRA), federal agencies are required to publish notice in the Federal Register concerning each proposed collection of information, including each proposed extension or reinstatement of an existing collection of information, and to allow a second opportunity for public comment on the notice. In | I43: https://www.federalregister.gov/documents/2024/03/05/2024-04591/agency-information-collection-activities-submission-for-omb-review-comment-request | J43: Y
A44: 2024-04674 | B44: Notice | C44: 45357 | D44: 45357 | E44: 0 | G44: Medicare Program; Announcement of the Re-Approval of COLA Under the Clinical Laboratory Improvement Amendments of 1988 | H44: This notice announces the application of COLA for re-approval as an accreditation organization for clinical laboratories under the Clinical Laboratory Improvement Amendments of 1988 (CLIA) program for the following specialty and subspecialty areas under CLIA: Microbiology, including Bacteriology, Mycobacteriology, Mycology, Parasitology, and Virology; Diagnostic Immunology, including Syphilis Serology, and General Immunology; Chemistry, including Routine Chemistry, Toxicology, and Endocrinology; | I44: https://www.federalregister.gov/documents/2024/03/06/2024-04674/medicare-program-announcement-of-the-re-approval-of-cola-under-the-clinical-laboratory-improvement | J44: Y
A45: 2024-04878 | B45: Notice | C45: 45358 | E45: 0 | G45: Agency Information Collection Activities: Proposed Collection; Comment Request | H45: The Centers for Medicare & Medicaid Services (CMS) is announcing an opportunity for the public to comment on CMS' intention to collect information from the public. Under the Paperwork Reduction Act of 1995 (PRA), Federal agencies are required to publish notice in the Federal Register concerning each proposed collection of information (including each proposed extension or reinstatement of an existing collection of information) and to allow 60 days for public comment on the proposed action. Intere | I45: https://www.federalregister.gov/documents/2024/03/07/2024-04878/agency-information-collection-activities-proposed-collection-comment-request | J45: Y
A46: 2024-05210 | B46: Rule | C46: 45362 | E46: 0 | G46: Principles of Reasonable Cost Reimbursement; Payment for End-Stage Renal Disease Services; Prospectively Determined Payment Rates for Skilled Nursing Facilities; Payment for Acute Kidney Injury Dialysis | I46: https://www.federalregister.gov/documents/2024/03/11/2024-05210/principles-of-reasonable-cost-reimbursement-payment-for-end-stage-renal-disease-services | J46: Y
A47: 2024-05291 | B47: Notice | C47: 45364 | E47: 1 | F47: medicare advantage(3); part d(1) | G47: Agency Information Collection Activities: Proposed Collection; Comment Request | H47: The Centers for Medicare & Medicaid Services (CMS) is announcing an opportunity for the public to comment on CMS' intention to collect information from the public. Under the Paperwork Reduction Act of 1995 (PRA), federal agencies are required to publish notice in the Federal Register concerning each proposed collection of information (including each proposed extension or reinstatement of an existing collection of information) and to allow 60 days for public comment on the proposed action. Intere | I47: https://www.federalregister.gov/documents/2024/03/13/2024-05291/agency-information-collection-activities-proposed-collection-comment-request | J47: Y | K47: SKIP | L47: PRA paperwork notice
A48: 2024-05332 | B48: Notice | C48: 45364 | E48: 0 | G48: Agency Information Collection Activities: Proposed Collection; Comment Request | H48: The Centers for Medicare & Medicaid Services (CMS) is announcing an opportunity for the public to comment on CMS' intention to collect information from the public. Under the Paperwork Reduction Act of 1995 (PRA), federal agencies are required to publish notice in the Federal Register concerning each proposed collection of information (including each proposed extension or reinstatement of an existing collection of information) and to allow 60 days for public comment on the proposed action. Intere | I48: https://www.federalregister.gov/documents/2024/03/13/2024-05332/agency-information-collection-activities-proposed-collection-comment-request | J48: Y
A49: 2024-05622 | B49: Notice | C49: 45369 | E49: 0 | G49: Agency Information Collection Activities: Submission for OMB Review; Comment Request | H49: The Centers for Medicare & Medicaid Services (CMS) is announcing an opportunity for the public to comment on CMS' intention to collect information from the public. Under the Paperwork Reduction Act of 1995 (PRA), federal agencies are required to publish notice in the Federal Register concerning each proposed collection of information, including each proposed extension or reinstatement of an existing collection of information, and to allow a second opportunity for public comment on the notice. In | I49: https://www.federalregister.gov/documents/2024/03/18/2024-05622/agency-information-collection-activities-submission-for-omb-review-comment-request | J49: Y
A50: 2024-05710 | B50: Notice | C50: 45369 | E50: 0 | G50: Agency Information Collection Activities: Proposed Collection; Comment Request | H50: The Centers for Medicare & Medicaid Services (CMS) is announcing an opportunity for the public to comment on CMS' intention to collect information from the public. Under the Paperwork Reduction Act of 1995 (PRA), federal agencies are required to publish notice in the Federal Register concerning each proposed collection of information (including each proposed extension or reinstatement of an existing collection of information) and to allow 60 days for public comment on the proposed action. Intere | I50: https://www.federalregister.gov/documents/2024/03/18/2024-05710/agency-information-collection-activities-proposed-collection-comment-request | J50: Y
A51: 2024-05712 | B51: Notice | C51: 45369 | E51: 1 | F51: ma organization(5); part d(2) | G51: Agency Information Collection Activities: Submission for OMB Review; Comment Request | H51: The Centers for Medicare & Medicaid Services (CMS) is announcing an opportunity for the public to comment on CMS' intention to collect information from the public. Under the Paperwork Reduction Act of 1995 (PRA), federal agencies are required to publish notice in the Federal Register concerning each proposed collection of information, including each proposed extension or reinstatement of an existing collection of information, and to allow a second opportunity for public comment on the notice. In | I51: https://www.federalregister.gov/documents/2024/03/18/2024-05712/agency-information-collection-activities-submission-for-omb-review-comment-request | J51: Y | K51: SKIP | L51: PRA paperwork notice
A52: 2024-05722 | B52: Notice | C52: 45369 | E52: 0 | G52: Medicaid and Children's Health Insurance Program (CHIP) Generic Information Collection Activities: Proposed Collection; Comment Request | H52: On May 28, 2010, the Office of Management and Budget (OMB) issued Paperwork Reduction Act (PRA) guidance related to the "generic" clearance process. Generally, this is an expedited process by which agencies may obtain OMB's approval of collection of information requests that are "usually voluntary, low-burden, and uncontroversial collections," do not raise any substantive or policy issues, and do not require policy or methodological review. The process requires the submission of an overarching p | I52: https://www.federalregister.gov/documents/2024/03/18/2024-05722/medicaid-and-childrens-health-insurance-program-chip-generic-information-collection-activities | J52: Y
A53: 2024-06144 | B53: Notice | C53: 45373 | D53: 45378 | E53: 0 | G53: Medicare Program; Application by the Utilization Review Accreditation Commission (URAC) for Continued CMS Approval of Its Home Infusion Therapy (HIT) Accreditation Program | H53: This final notice announces our decision to approve the Utilization Review Accreditation Commission (URAC) for continued recognition as a national accrediting organization that accredits suppliers of home infusion therapy (HIT) services that wish to participate in the Medicare or Medicaid programs. | I53: https://www.federalregister.gov/documents/2024/03/22/2024-06144/medicare-program-application-by-the-utilization-review-accreditation-commission-urac-for-continued | J53: Y
A54: 2024-06148 | B54: Notice | C54: 45376 | E54: 0 | G54: Medicare Program; Virtual Meeting of the Medicare Evidence Development and Coverage Advisory Committee-May 21, 2024 | H54: This notice announces a virtual public meeting of the Medicare Evidence Development & Coverage Advisory Committee (MEDCAC) ("Committee") will be held on Tuesday, May 21, 2024. The MEDCAC panel will consider which health outcomes in studies of devices for self- management of Type 1 and insulin-dependent Type 2 diabetes should be of interest to CMS. Given the increased emphasis on new and innovative medical products for difficult to manage conditions, some studies of new medical technologies have | I54: https://www.federalregister.gov/documents/2024/03/25/2024-06148/medicare-program-virtual-meeting-of-the-medicare-evidence-development-and-coverage-advisory | J54: Y
A55: 2024-06239 | B55: Notice | C55: 45376 | E55: 1 | F55: medicare advantage(2); ma organization(1) | G55: Agency Information Collection Activities: Proposed Collection; Comment Request | H55: The Centers for Medicare & Medicaid Services (CMS) is announcing an opportunity for the public to comment on CMS' intention to collect information from the public. Under the Paperwork Reduction Act of 1995 (PRA), Federal agencies are required to publish notice in the Federal Register concerning each proposed collection of information (including each proposed extension or reinstatement of an existing collection of information) and to allow 60 days for public comment on the proposed action. Intere | I55: https://www.federalregister.gov/documents/2024/03/25/2024-06239/agency-information-collection-activities-proposed-collection-comment-request | J55: Y | K55: SKIP | L55: PRA paperwork notice
A56: 2024-06424 | B56: Notice | C56: 45377 | E56: 0 | G56: Announcement of the Advisory Panel on Outreach and Education (APOE) In-Person Meeting | H56: This notice announces the next meeting of the APOE (the Panel) in accordance with the Federal Advisory Committee Act. The Panel advises and makes recommendations to the Secretary of the U.S. Department of Health and Human Services (HHS) (the Secretary) and the Administrator of the Centers for Medicare & Medicaid Services (CMS) on opportunities to enhance the effectiveness of consumer education strategies concerning the Health Insurance Marketplace[supreg], Medicare, Medicaid, and the Children's | I56: https://www.federalregister.gov/documents/2024/03/26/2024-06424/announcement-of-the-advisory-panel-on-outreach-and-education-apoe-in-person-meeting | J56: Y
A57: 2024-06439 | B57: Notice | C57: 45378 | E57: 0 | G57: Agency Information Collection Activities: Submission for OMB Review; Comment Request | H57: The Centers for Medicare & Medicaid Services (CMS) is announcing an opportunity for the public to comment on CMS' intention to collect information from the public. Under the Paperwork Reduction Act of 1995 (PRA), federal agencies are required to publish notice in the Federal Register concerning each proposed collection of information, including each proposed extension or reinstatement of an existing collection of information, and to allow a second opportunity for public comment on the notice. In | I57: https://www.federalregister.gov/documents/2024/03/27/2024-06439/agency-information-collection-activities-submission-for-omb-review-comment-request | J57: Y
A58: 2024-06645 | B58: Notice | C58: 45379 | E58: 0 | G58: Agency Information Collection Activities: Proposed Collection; Comment Request | H58: The Centers for Medicare & Medicaid Services (CMS) is announcing an opportunity for the public to comment on CMS' intention to collect information from the public. Under the Paperwork Reduction Act of 1995 (PRA), federal agencies are required to publish notice in the Federal Register concerning each proposed collection of information (including each proposed extension or reinstatement of an existing collection of information) and to allow 60 days for public comment on the proposed action. Intere | I58: https://www.federalregister.gov/documents/2024/03/28/2024-06645/agency-information-collection-activities-proposed-collection-comment-request | J58: Y
A59: 2024-06647 | B59: Notice | C59: 45379 | E59: 0 | G59: Agency Information Collection Activities: Submission for OMB Review; Comment Request | H59: The Centers for Medicare & Medicaid Services (CMS) is announcing an opportunity for the public to comment on CMS' intention to collect information from the public. Under the Paperwork Reduction Act of 1995 (PRA), federal agencies are required to publish notice in the Federal Register concerning each proposed collection of information, including each proposed extension or reinstatement of an existing collection of information, and to allow a second opportunity for public comment on the notice. In | I59: https://www.federalregister.gov/documents/2024/03/28/2024-06647/agency-information-collection-activities-submission-for-omb-review-comment-request | J59: Y
A60: 2024-06550 | B60: Proposed Rule | C60: 45380 | E60: 1 | F60: part c(2); medicare advantage(1) | G60: Medicare Program; Inpatient Rehabilitation Facility Prospective Payment System for Federal Fiscal Year 2025 and Updates to the IRF Quality Reporting Program | H60: This rule proposes updates to the prospective payment rates for inpatient rehabilitation facilities (IRFs) for Federal fiscal year (FY) 2025. As required by statute, this proposed rule includes the classification and weighting factors for the IRF prospective payment system's case-mix groups and a description of the methodologies and data used in computing the prospective payment rates for FY 2025. We are proposing updates to the Office of Management and Budget (OMB) market area delineations for | I60: https://www.federalregister.gov/documents/2024/03/29/2024-06550/medicare-program-inpatient-rehabilitation-facility-prospective-payment-system-for-federal-fiscal | J60: Y | K60: SKIP | L60: provider payment rule (MA mentions incidental)
A61: 2024-06802 | B61: Notice | C61: 45383 | D61: 45383 | E61: 0 | G61: Medicare, Medicaid, and CLIA Programs; Clinical Laboratory Improvement Amendments of 1988 Exemption of Laboratories Licensed by the State of Washington | H61: This notice announces that laboratories located in and licensed by the State of Washington that possess a valid license under the Medical Test Site law, chapter 70.42 of the Revised Code of Washington, are exempt from the requirements of the Clinical Laboratory Improvement Amendments of 1988 (CLIA) for a period of 4 years. | I61: https://www.federalregister.gov/documents/2024/04/01/2024-06802/medicare-medicaid-and-clia-programs-clinical-laboratory-improvement-amendments-of-1988-exemption-of | J61: Y
A62: 2024-27939 | B62: Proposed Rule | C62: 45636 | E62: 1 | F62: part d(1832); ma organization(684); d-snp(147); medicare advantage(96); part c(84); medigap(54); special needs plan(17); dual eligible(13); medicare supplement(2); c-snp(1) | G62: Medicare and Medicaid Programs; Contract Year 2026 Policy and Technical Changes to the Medicare Advantage Program, Medicare Prescription Drug Benefit Program, Medicare Cost Plan Program, and Programs of All-Inclusive Care for the Elderly | H62: This proposed rule would revise the Medicare Advantage (Part C), Medicare Prescription Drug Benefit (Part D), Medicaid, Medicare cost plan, and Programs of All-Inclusive Care for the Elderly (PACE) regulations to implement changes related to Star Ratings, marketing and communications, agent/broker compensation, health equity, drug coverage, dual eligible special needs plans (D-SNPs), utilization management, network adequacy, and other programmatic areas, including the Medicare Drug Price Negotia | I62: https://www.federalregister.gov/documents/2024/12/10/2024-27939/medicare-and-medicaid-programs-contract-year-2026-policy-and-technical-changes-to-the-medicare | J62: Y | K62: HIGH | L62: core MA/Part D policy doc (strong kw=1014)
A63: 2024-06764 | B63: Proposed Rule | C63: 45385 | E63: 1 | F63: part d(1) | G63: Medicare Program; FY 2025 Inpatient Psychiatric Facilities Prospective Payment System-Rate Update | H63: This rulemaking proposes to update the prospective payment rates, the outlier threshold, and the wage index for Medicare inpatient hospital services provided by Inpatient Psychiatric Facilities (IPF), which include psychiatric hospitals and excluded psychiatric units of an acute care hospital or critical access hospital. This rulemaking also proposes to revise the patient-level adjustment factors, the Emergency Department adjustment, and the payment amount for electroconvulsive therapy. These pr | I63: https://www.federalregister.gov/documents/2024/04/03/2024-06764/medicare-program-fy-2025-inpatient-psychiatric-facilities-prospective-payment-system-rate-update | J63: Y | K63: SKIP | L63: provider payment rule (MA mentions incidental)
A64: 2024-06812 | B64: Proposed Rule | C64: 45385 | E64: 1 | F64: dual eligible(13); part d(5); part c(2) | G64: Medicare Program; Prospective Payment System and Consolidated Billing for Skilled Nursing Facilities; Updates to the Quality Reporting Program and Value-Based Purchasing Program for Federal Fiscal Year 2025 | H64: This rule proposes changes and updates to the policies and payment rates used under the Skilled Nursing Facility (SNF) Prospective Payment System (PPS) for FY 2025. First, we are proposing to rebase and revise the SNF market basket to reflect a 2022 base year. Next, we are proposing to update the wage index used under the SNF PPS to reflect data collected during the most recent decennial census. Additionally, we are proposing several technical revisions to the code mappings used to classify pati | I64: https://www.federalregister.gov/documents/2024/04/03/2024-06812/medicare-program-prospective-payment-system-and-consolidated-billing-for-skilled-nursing-facilities | J64: Y | K64: SKIP | L64: provider payment rule (MA mentions incidental)
A65: 2024-06921 | B65: Proposed Rule | C65: 45386 | E65: 1 | F65: medicare advantage(1) | G65: Medicare Program; FY 2025 Hospice Wage Index and Payment Rate Update, Hospice Conditions of Participation Updates, and Hospice Quality Reporting Program Requirements | H65: This proposed rule would update the hospice wage index, payment rates, and aggregate cap amount for Fiscal Year (FY) 2025. This rule proposes changes to the Hospice Quality Reporting Program. This rule also proposes to adopt the most recent Office of Management and Budget statistical area delineations, which would change the hospice wage index. This rule proposes to clarify current policy related to the "election statement" and the "notice of election", as well as to add clarifying language rega | I65: https://www.federalregister.gov/documents/2024/04/04/2024-06921/medicare-program-fy-2025-hospice-wage-index-and-payment-rate-update-hospice-conditions-of | J65: Y | K65: SKIP | L65: provider payment rule (MA mentions incidental)
A66: 2024-07162 | B66: Notice | C66: 45386 | E66: 0 | G66: Agency Information Collection Activities: Proposed Collection; Comment Request | H66: The Centers for Medicare & Medicaid Services (CMS) is announcing an opportunity for the public to comment on CMS' intention to collect information from the public. Under the Paperwork Reduction Act of 1995 (PRA), Federal agencies are required to publish notice in the Federal Register concerning each proposed collection of information (including each proposed extension or reinstatement of an existing collection of information) and to allow 60 days for public comment on the proposed action. Intere | I66: https://www.federalregister.gov/documents/2024/04/04/2024-07162/agency-information-collection-activities-proposed-collection-comment-request | J66: Y
A67: 2024-07202 | B67: Notice | C67: 45387 | E67: 1 | F67: medicare advantage(2); part c(2); part d(2) | G67: Agency Information Collection Activities: Proposed Collection; Comment Request | H67: The Centers for Medicare & Medicaid Services (CMS) is announcing an opportunity for the public to comment on CMS' intention to collect information from the public. Under the Paperwork Reduction Act of 1995 (PRA), Federal agencies are required to publish notice in the Federal Register concerning each proposed collection of information (including each proposed extension or reinstatement of an existing collection of information) and to allow 60 days for public comment on the proposed action. Intere | I67: https://www.federalregister.gov/documents/2024/04/05/2024-07202/agency-information-collection-activities-proposed-collection-comment-request | J67: Y | K67: SKIP | L67: PRA paperwork notice
A68: 2024-07393 | B68: Notice | C68: 45390 | E68: 0 | G68: Agency Information Collection Activities: Submission for OMB Review; Comment Request | H68: The Centers for Medicare & Medicaid Services (CMS) is announcing an opportunity for the public to comment on CMS' intention to collect information from the public. Under the Paperwork Reduction Act of 1995 (PRA), Federal agencies are required to publish notice in the Federal Register concerning each proposed collection of information, including each proposed extension or reinstatement of an existing collection of information, and to allow a second opportunity for public comment on the notice. In | I68: https://www.federalregister.gov/documents/2024/04/08/2024-07393/agency-information-collection-activities-submission-for-omb-review-comment-request | J68: Y
A69: 2024-07415 | B69: Notice | C69: 45390 | E69: 0 | G69: Agency Information Collection Activities: Submission for OMB Review; Comment Request | H69: The Centers for Medicare & Medicaid Services (CMS) is announcing an opportunity for the public to comment on CMS' intention to collect information from the public. Under the Paperwork Reduction Act of 1995 (PRA), federal agencies are required to publish notice in the Federal Register concerning each proposed collection of information, including each proposed extension or reinstatement of an existing collection of information, and to allow a second opportunity for public comment on the notice. In | I69: https://www.federalregister.gov/documents/2024/04/08/2024-07415/agency-information-collection-activities-submission-for-omb-review-comment-request | J69: Y
A70: 2024-07429 | B70: Notice | C70: 45390 | E70: 1 | F70: part d(7); medicare advantage(2); part c(1) | G70: Agency Information Collection Activities: Submission for OMB Review; Comment Request | H70: The Centers for Medicare & Medicaid Services (CMS) is announcing an opportunity for the public to comment on CMS' intention to collect information from the public. Under the Paperwork Reduction Act of 1995 (PRA), Federal agencies are required to publish notice in the Federal Register concerning each proposed collection of information, including each proposed extension or reinstatement of an existing collection of information, and to allow a second opportunity for public comment on the notice. In | I70: https://www.federalregister.gov/documents/2024/04/08/2024-07429/agency-information-collection-activities-submission-for-omb-review-comment-request | J70: Y | K70: SKIP | L70: PRA paperwork notice
A71: 2024-07522 | B71: Rule | C71: 45392 | D71: 45392 | E71: 0 | G71: Medicare Program; Prospective Payment System and Consolidated Billing for Skilled Nursing Facilities; Updates to the Quality Reporting Program and Value-Based Purchasing Program for Federal Fiscal Year 2024; Corrections | H71: This document corrects technical errors in the final rule that appeared in the August 7, 2023 Federal Register, entitled "Medicare Program; Prospective Payment System and Consolidated Billing for Skilled Nursing Facilities; Updates to the Quality Reporting Program and Value-Based Purchasing Program for Federal Fiscal Year 2024". The effective date was October 1, 2023. | I71: https://www.federalregister.gov/documents/2024/04/10/2024-07522/medicare-program-prospective-payment-system-and-consolidated-billing-for-skilled-nursing-facilities | J71: Y
A72: 2024-07790 | B72: Notice | C72: 45394 | E72: 1 | F72: part d(7) | G72: Agency Information Collection Activities: Proposed Collection; Comment Request | H72: The Centers for Medicare & Medicaid Services (CMS) is announcing an opportunity for the public to comment on CMS' intention to collect information from the public. Under the Paperwork Reduction Act of 1995 (PRA), federal agencies are required to publish notice in the Federal Register concerning each proposed collection of information (including each proposed extension or reinstatement of an existing collection of information) and to allow 60 days for public comment on the proposed action. Intere | I72: https://www.federalregister.gov/documents/2024/04/12/2024-07790/agency-information-collection-activities-proposed-collection-comment-request | J72: Y | K72: SKIP | L72: PRA paperwork notice
A73: 2025-06008 | B73: Rule | C73: 45762 | D73: 45811 | E73: 1 | F73: part d(1225); ma organization(418); d-snp(175); part c(69); medicare advantage(38); dual eligible(14); special needs plan(13); c-snp(7); medicare supplement(1) | G73: Medicare and Medicaid Programs; Contract Year 2026 Policy and Technical Changes to the Medicare Advantage Program, Medicare Prescription Drug Benefit Program, Medicare Cost Plan Program, and Programs of All-Inclusive Care for the Elderly | H73: This final rule revises the Medicare Advantage (Part C), Medicare Prescription Drug Benefit (Part D), Medicare cost plan, and Programs of All-Inclusive Care for the Elderly (PACE) regulations to implement changes related to prescription drug coverage, the Medicare Prescription Payment Plan, dual eligible special needs plans (D-SNPs), Part C and D Star Ratings, and other programmatic areas, including the Medicare Drug Price Negotiation Program. This final rule also codifies existing sub-regulator | I73: https://www.federalregister.gov/documents/2025/04/15/2025-06008/medicare-and-medicaid-programs-contract-year-2026-policy-and-technical-changes-to-the-medicare | J73: Y | K73: HIGH | L73: core MA/Part D policy doc (strong kw=666)
A74: 2024-07884 | B74: Notice | C74: 45397 | D74: 45405 | E74: 0 | G74: Medicare Program; Application by the Accreditation Commission for Health Care (ACHC) for Continued CMS Approval of Its Home Infusion Therapy (HIT) Accreditation Program | H74: This final notice announces our decision to approve the Accreditation Commission for Health Care (ACHC) for continued recognition as a national accrediting organization that accredits suppliers of home infusion therapy (HIT) services that wish to participate in the Medicare or Medicaid programs. | I74: https://www.federalregister.gov/documents/2024/04/15/2024-07884/medicare-program-application-by-the-accreditation-commission-for-health-care-achc-for-continued-cms | J74: Y
A75: 2024-08005 | B75: Notice | C75: 45398 | E75: 0 | G75: Public Meeting on June 25, 2024 Regarding New and Reconsidered Clinical Diagnostic Laboratory Test Codes for the Clinical Laboratory Fee Schedule for Calendar Year 2025 | H75: This notice announces a public meeting to receive comments and recommendations (including data on which recommendations are based) on the appropriate basis for establishing payment amounts for new or substantially revised Healthcare Common Procedure Coding System codes being considered for Medicare payment under the Clinical Laboratory Fee Schedule for calendar year 2025. This meeting also provides a forum for those who submitted certain reconsideration requests regarding final determinations ma | I75: https://www.federalregister.gov/documents/2024/04/16/2024-08005/public-meeting-on-june-25-2024-regarding-new-and-reconsidered-clinical-diagnostic-laboratory-test | J75: Y
A76: 2024-08008 | B76: Notice | C76: 45398 | E76: 0 | G76: Medicare Program; Meeting Announcement for the Medicare Advisory Panel on Clinical Diagnostic Laboratory Tests, July 25-26, 2024 | H76: This notice announces the public meeting dates for the Medicare Advisory Panel on Clinical Diagnostic Laboratory Tests (the Panel) on Thursday, July 25, 2024 and Friday, July 26, 2024. The purpose of the Panel is to advise the Secretary of the Department of Health and Human Services and the Administrator of the Centers for Medicare & Medicaid Services on issues related to clinical diagnostic laboratory tests. | I76: https://www.federalregister.gov/documents/2024/04/16/2024-08008/medicare-program-meeting-announcement-for-the-medicare-advisory-panel-on-clinical-diagnostic | J76: Y
A77: 2024-08011 | B77: Notice | C77: 45398 | E77: 0 | G77: Agency Information Collection Activities: Proposed Collection; Comment Request | H77: The Centers for Medicare & Medicaid Services (CMS) is announcing an opportunity for the public to comment on CMS' intention to collect information from the public. Under the Paperwork Reduction Act of 1995 (PRA), federal agencies are required to publish notice in the Federal Register concerning each proposed collection of information (including each proposed extension or reinstatement of an existing collection of information) and to allow 60 days for public comment on the proposed action. Intere | I77: https://www.federalregister.gov/documents/2024/04/16/2024-08011/agency-information-collection-activities-proposed-collection-comment-request | J77: Y
A78: 2024-08164 | B78: Notice | C78: 45399 | E78: 0 | G78: Agency Information Collection Activities: Submission for OMB Review; Comment Request | H78: The Centers for Medicare & Medicaid Services (CMS) is announcing an opportunity for the public to comment on CMS' intention to collect information from the public. Under the Paperwork Reduction Act of 1995 (PRA), Federal agencies are required to publish notice in the Federal Register concerning each proposed collection of information, including each proposed extension or reinstatement of an existing collection of information, and to allow a second opportunity for public comment on the notice. In | I78: https://www.federalregister.gov/documents/2024/04/17/2024-08164/agency-information-collection-activities-submission-for-omb-review-comment-request | J78: Y
A79: 2024-08223 | B79: Notice | C79: 45400 | E79: 1 | F79: part d(1) | G79: Agency Information Collection Activities: Proposed Collection; Comment Request | H79: The Centers for Medicare & Medicaid Services (CMS) is announcing an opportunity for the public to comment on CMS' intention to collect information from the public. Under the Paperwork Reduction Act of 1995 (PRA), Federal agencies are required to publish notice in the Federal Register concerning each proposed collection of information (including each proposed extension or reinstatement of an existing collection of information) and to allow 60 days for public comment on the proposed action. Intere | I79: https://www.federalregister.gov/documents/2024/04/18/2024-08223/agency-information-collection-activities-proposed-collection-comment-request | J79: Y | K79: SKIP | L79: PRA paperwork notice
A80: 2024-08551 | B80: Notice | C80: 45404 | E80: 0 | G80: Medicare Program Public Meeting for New Revisions to the Healthcare Common Procedure Coding System (HCPCS) Coding-May 28-30, 2024 | H80: This notice announces the dates and times of the virtual Healthcare Common Procedure Coding System (HCPCS) public meeting to be held from May 28, 2024, through May 30, 2024, to discuss CMS' preliminary coding, Medicare benefit category, and payment determinations, if applicable, for new revisions to the HCPCS Level II code set for non-drug and non-biological items and services, as well as how to register for those meetings. | I80: https://www.federalregister.gov/documents/2024/04/22/2024-08551/medicare-program-public-meeting-for-new-revisions-to-the-healthcare-common-procedure-coding-system | J80: Y
A81: 2025-18236 | B81: Rule | C81: 45919 | D81: 45978 | E81: 1 | F81: ma organization(92); medicare advantage(9); part d(2); part c(1) | G81: Medicare and Medicaid Programs; Contract Year 2026 Policy and Technical Changes to the Medicare Advantage Program, Medicare Prescription Drug Benefit Program, Medicare Cost Plan Program, and Programs of All-Inclusive Care for the Elderly (PACE)-Finalization of Format Provider Directories for Medicare Plan Finder | H81: This final rule implements Medicare Advantage disclosure requirement changes. | I81: https://www.federalregister.gov/documents/2025/09/19/2025-18236/medicare-and-medicaid-programs-contract-year-2026-policy-and-technical-changes-to-the-medicare | J81: Y | K81: HIGH | L81: core MA/Part D policy doc (strong kw=101)
A82: 2024-08658 | B82: Notice | C82: 45405 | E82: 0 | G82: Agency Information Collection Activities: Submission for OMB Review; Comment Request | H82: On May 28, 2010, the Office of Management and Budget (OMB) issued Paperwork Reduction Act (PRA) guidance related to the "generic" clearance process. Generally, this is an expedited clearance process by which agencies may obtain OMB's approval of collection of information requests that are "usually voluntary, low- burden, and uncontroversial," do not raise any substantive or policy issues, and do not require policy or methodological review. The process requires the submission of an overarching pl | I82: https://www.federalregister.gov/documents/2024/04/23/2024-08658/agency-information-collection-activities-submission-for-omb-review-comment-request | J82: Y
A83: 2024-08809 | B83: Notice | C83: 45407 | D83: 45407 | E83: 0 | G83: Announcement of the Re-Approval of AABB (Association for the Advancement of Blood and Biotherapies) as an Accreditation Organization Under the Clinical Laboratory Improvement Amendments of 1988 | H83: This notice announces the application of the Association for the Advancement of Blood and Biotherapies (AABB) for re-approval as an accreditation organization for clinical laboratories under the Clinical Laboratory Improvement Amendments of 1988 (CLIA) program. This deeming authority is granted to AABB for the Blood Bank and Transfusion Service (BB/TS) program, the Immunohematology Reference Laboratory (IRL) program, the Molecular Testing (MT) program, and the Cellular Therapy (CT) program. We h | I83: https://www.federalregister.gov/documents/2024/04/25/2024-08809/announcement-of-the-re-approval-of-aabb-association-for-the-advancement-of-blood-and-biotherapies-as | J83: Y
A84: 2024-08828 | B84: Notice | C84: 45407 | E84: 1 | F84: medicare advantage(2); part d(2) | G84: Agency Information Collection Activities: Submission for OMB Review; Comment Request | H84: The Centers for Medicare & Medicaid Services (CMS) is announcing an opportunity for the public to comment on CMS' intention to collect information from the public. Under the Paperwork Reduction Act of 1995 (PRA), federal agencies are required to publish notice in the Federal Register concerning each proposed collection of information, including each proposed extension or reinstatement of an existing collection of information, and to allow a second opportunity for public comment on the notice. In | I84: https://www.federalregister.gov/documents/2024/04/25/2024-08828/agency-information-collection-activities-submission-for-omb-review-comment-request | J84: Y | K84: SKIP | L84: PRA paperwork notice
A85: 2024-08921 | B85: Notice | C85: 45408 | E85: 0 | G85: Agency Information Collection Activities: Proposed Collection; Comment Request | H85: The Centers for Medicare & Medicaid Services (CMS) is announcing an opportunity for the public to comment on CMS' intention to collect information from the public. Under the Paperwork Reduction Act of 1995 (PRA), Federal agencies are required to publish notice in the Federal Register concerning each proposed collection of information (including each proposed extension or reinstatement of an existing collection of information) and to allow 60 days for public comment on the proposed action. Intere | I85: https://www.federalregister.gov/documents/2024/04/26/2024-08921/agency-information-collection-activities-proposed-collection-comment-request | J85: Y
A86: 2024-09040 | B86: Notice | C86: 45408 | E86: 0 | G86: Agency Information Collection Activities: Proposed Collection; Comment Request | H86: The Centers for Medicare & Medicaid Services (CMS) is announcing an opportunity for the public to comment on CMS' intention to collect information from the public. Under the Paperwork Reduction Act of 1995 (PRA), federal agencies are required to publish notice in the Federal Register concerning each proposed collection of information (including each proposed extension or reinstatement of an existing collection of information) and to allow 60 days for public comment on the proposed action. Intere | I86: https://www.federalregister.gov/documents/2024/04/26/2024-09040/agency-information-collection-activities-proposed-collection-comment-request | J86: Y
A87: 2024-09041 | B87: Notice | C87: 45408 | E87: 0 | G87: Agency Information Collection Activities: Proposed Collection; Comment Request | H87: The Centers for Medicare & Medicaid Services (CMS) is announcing an opportunity for the public to comment on CMS' intention to collect information from the public. Under the Paperwork Reduction Act of 1995 (PRA), federal agencies are required to publish notice in the Federal Register concerning each proposed collection of information (including each proposed extension or reinstatement of an existing collection of information) and to allow 60 days for public comment on the proposed action. Intere | I87: https://www.federalregister.gov/documents/2024/04/26/2024-09041/agency-information-collection-activities-proposed-collection-comment-request | J87: Y
A88: 2024-09044 | B88: Notice | C88: 45408 | E88: 0 | G88: Medicare Program; Application by the National Association of Boards of Pharmacy (NABP) for Continued CMS Approval of its Home Infusion Therapy (HIT) Accreditation Program | H88: This notice acknowledges the receipt of an application from the National Association of Boards of Pharmacy (NABP) for continued approval by the Centers for Medicare & Medicaid Services (CMS) of NABP's national accrediting organization program for suppliers providing home infusion therapy (HIT) services and that wish to participate in the Medicare or Medicaid programs. The statute requires that within 60 days of receipt of an organization's complete application, CMS will publish a notice that ide | I88: https://www.federalregister.gov/documents/2024/04/26/2024-09044/medicare-program-application-by-the-national-association-of-boards-of-pharmacy-nabp-for-continued | J88: Y
A89: 2024-09165 | B89: Notice | C89: 45411 | E89: 0 | G89: Medicare and Medicaid Programs; Quarterly Listing of Program Issuances-January through March 2024 | H89: This quarterly notice lists CMS manual instructions, substantive and interpretive regulations, and other Federal Register notices that were published in the 3-month period, relating to the Medicare and Medicaid programs and other programs administered by CMS. | I89: https://www.federalregister.gov/documents/2024/04/29/2024-09165/medicare-and-medicaid-programs-quarterly-listing-of-program-issuances-january-through-march-2024 | J89: Y
A90: 2024-09172 | B90: Notice | C90: 45411 | E90: 0 | G90: Medicare Program; Application by The Compliance Team (TCT) for Continued CMS Approval of its Home Infusion Therapy (HIT) Accreditation Program | H90: This notice acknowledges the receipt of an application from The Compliance Team (TCT) for continued approval by the Centers for Medicare & Medicaid Services (CMS) of TCT's national accrediting organization program for suppliers providing home infusion therapy (HIT) services and that wish to participate in the Medicare or Medicaid programs. The statute requires that within 60 days of receipt of an organization's complete application, CMS will publish a notice that identifies the national accredit | I90: https://www.federalregister.gov/documents/2024/04/29/2024-09172/medicare-program-application-by-the-compliance-team-tct-for-continued-cms-approval-of-its-home | J90: Y
A91: 2024-09176 | B91: Notice | C91: 45412 | E91: 0 | G91: Medicare Program; Application by the Community Health Accreditation Partner (CHAP) for Continued CMS Approval of Its Home Infusion Therapy (HIT) Accreditation Program | H91: This notice acknowledges the receipt of an application from the Community Health Accreditation Partner (CHAP) for continued approval by the Centers for Medicare & Medicaid Services (CMS) of CHAP's national accrediting organization program for suppliers providing home infusion therapy (HIT) services and that wish to participate in the Medicare or Medicaid programs. The statute requires that within 60 days of receipt of an organization's complete application, CMS will publish a notice that identif | I91: https://www.federalregister.gov/documents/2024/04/30/2024-09176/medicare-program-application-by-the-community-health-accreditation-partner-chap-for-continued-cms | J91: Y
A92: 2024-09314 | B92: Notice | C92: 45412 | E92: 0 | G92: Agency Information Collection Activities: Submission for OMB Review; Comment Request | H92: The Centers for Medicare & Medicaid Services (CMS) is announcing an opportunity for the public to comment on CMS' intention to collect information from the public. Under the Paperwork Reduction Act of 1995 (PRA), federal agencies are required to publish notice in the Federal Register concerning each proposed collection of information, including each proposed extension or reinstatement of an existing collection of information, and to allow a second opportunity for public comment on the notice. In | I92: https://www.federalregister.gov/documents/2024/04/30/2024-09314/agency-information-collection-activities-submission-for-omb-review-comment-request | J92: Y
A93: 2024-09426 | B93: Notice | C93: 45413 | E93: 0 | G93: Medicare and Medicaid Programs: Application From the Joint Commission for Initial CMS-Approval of Its Rural Health Clinic (RHC) Accreditation Program | H93: This final notice announces our decision to approve The Joint Commission (TJC) for initial recognition as a national accrediting organization (AO) for rural health clinics (RHCs) that wish to participate in the Medicare or Medicaid programs. | I93: https://www.federalregister.gov/documents/2024/05/01/2024-09426/medicare-and-medicaid-programs-application-from-the-joint-commission-for-initial-cms-approval-of-its | J93: Y
A94: 2024-07567 | B94: Proposed Rule | C94: 45414 | E94: 1 | F94: medicare advantage(25); part d(16); dual eligible(4); part c(1) | G94: Medicare and Medicaid Programs and the Children's Health Insurance Program; Hospital Inpatient Prospective Payment Systems for Acute Care Hospitals and the Long-Term Care Hospital Prospective Payment System and Policy Changes and Fiscal Year 2025 Rates; Quality Programs Requirements; and Other Policy Changes | H94: This proposed rule would revise the Medicare hospital inpatient prospective payment systems (IPPS) for operating and capital- related costs of acute care hospitals; make changes relating to Medicare graduate medical education (GME) for teaching hospitals; update the payment policies and the annual payment rates for the Medicare prospective payment system (PPS) for inpatient hospital services provided by long-term care hospitals (LTCHs); and make other policy-related changes. | I94: https://www.federalregister.gov/documents/2024/05/02/2024-07567/medicare-and-medicaid-programs-and-the-childrens-health-insurance-program-hospital-inpatient | J94: Y | K94: SKIP | L94: provider payment rule (MA mentions incidental)
A95: 2024-09699 | B95: Notice | C95: 45415 | E95: 1 | F95: part d(3) | G95: Agency Information Collection Activities: Proposed Collection; Comment Request | H95: The Centers for Medicare & Medicaid Services (CMS) is announcing an opportunity for the public to comment on CMS' intention to collect information from the public. Under the Paperwork Reduction Act of 1995 (PRA), Federal agencies are required to publish notice in the Federal Register concerning each proposed collection of information (including each proposed extension or reinstatement of an existing collection of information) and to allow 60 days for public comment on the proposed action. Intere | I95: https://www.federalregister.gov/documents/2024/05/03/2024-09699/agency-information-collection-activities-proposed-collection-comment-request | J95: Y | K95: SKIP | L95: PRA paperwork notice
A96: 2025-21456 | B96: Proposed Rule | C96: 45989 | E96: 1 | F96: part d(1031); d-snp(307); ma organization(250); c-snp(118); medicare advantage(88); part c(74); dual eligible(27); special needs plan(21); medigap(4); medicare supplement(3) | G96: Medicare Program; Contract Year 2027 Policy and Technical Changes to the Medicare Advantage Program, Medicare Prescription Drug Benefit Program, and Medicare Cost Plan Program | H96: This proposed rule would revise the Medicare Advantage (Part C), Medicare Prescription Drug Benefit (Part D), and Medicare cost plan regulations to implement changes related to Star Ratings, marketing and communications, drug coverage, enrollment processes, special needs plans, and other programmatic areas. | I96: https://www.federalregister.gov/documents/2025/11/28/2025-21456/medicare-program-contract-year-2027-policy-and-technical-changes-to-the-medicare-advantage-program | J96: Y | K96: HIGH | L96: core MA/Part D policy doc (strong kw=818)
A97: 2024-09745 | B97: Notice | C97: 45418 | E97: 0 | G97: Agency Information Collection Activities: Proposed Collection; Comment Request | H97: The Centers for Medicare & Medicaid Services (CMS) is announcing an opportunity for the public to comment on CMS' intention to collect information from the public. Under the Paperwork Reduction Act of 1995 (PRA), Federal agencies are required to publish notice in the Federal Register concerning each proposed collection of information (including each proposed extension or reinstatement of an existing collection of information) and to allow 60 days for public comment on the proposed action. Intere | I97: https://www.federalregister.gov/documents/2024/05/06/2024-09745/agency-information-collection-activities-proposed-collection-comment-request | J97: Y
A98: 2024-09750 | B98: Notice | C98: 45418 | E98: 0 | G98: Inflation Reduction Act (IRA) Medicare Drug Price Negotiation Program Draft Guidance; Comment Request | H98: The Centers for Medicare & Medicaid Services (CMS) is announcing an opportunity for the public to comment on CMS' draft guidance for the second cycle of the Medicare Drug Price Negotiation Program and manufacturer effectuation of the maximum fair price for 2026 and 2027 for the implementation of the Inflation Reduction Act. This and other Inflation Reduction Act-related guidance can be viewed on the dedicated Inflation Reduction Act section of the CMS website at https://www.cms.gov/inflation-red | I98: https://www.federalregister.gov/documents/2024/05/06/2024-09750/inflation-reduction-act-ira-medicare-drug-price-negotiation-program-draft-guidance-comment-request | J98: Y
A99: 2024-09812 | B99: Notice | C99: 45418 | E99: 1 | F99: part d(9); medicare advantage(2) | G99: Agency Information Collection Activities: Proposed Collection; Comment Request | H99: The Centers for Medicare & Medicaid Services (CMS) is announcing an opportunity for the public to comment on CMS' intention to collect information from the public. Under the Paperwork Reduction Act of 1995 (PRA), Federal agencies are required to publish notice in the Federal Register concerning each proposed collection of information (including each proposed extension or reinstatement of an existing collection of information) and to allow 60 days for public comment on the proposed action. Intere | I99: https://www.federalregister.gov/documents/2024/05/06/2024-09812/agency-information-collection-activities-proposed-collection-comment-request | J99: Y | K99: SKIP | L99: PRA paperwork notice
A100: 2026-06600 | B100: Rule | C100: 46118 | D100: 46174 | E100: 1 | F100: part d(1204); d-snp(543); ma organization(435); medicare advantage(108); part c(104); c-snp(46); dual eligible(30); special needs plan(23); medicare supplement(2) | G100: Medicare Program; Contract Year 2027 and Certain Contract Year 2026 Policy and Technical Changes to the Medicare Advantage Program, Medicare Prescription Drug Benefit Program, and Medicare Cost Plan Program | H100: This final rule revises the Medicare Advantage (Part C), Medicare Prescription Drug Benefit (Part D), and Medicare cost plan regulations to implement changes related to Star Ratings, marketing and communications, drug coverage, enrollment processes, special needs plans, and other programmatic areas. | I100: https://www.federalregister.gov/documents/2026/04/06/2026-06600/medicare-program-contract-year-2027-and-certain-contract-year-2026-policy-and-technical-changes-to | J100: Y | K100: HIGH | L100: core MA/Part D policy doc (strong kw=1187)
...

Sheet Legend
A1: WORKBOOK OVERVIEW
A2: Purpose | B2: Daily calendar (Jan 1, 2024 - May 31, 2026) of dates that could affect the value or sales of Medicare Advantage (MA), Medicare Supplement (MS / Medigap), Dual Eligible Special Needs Plans (D-SNP), and Chronic Condition Special Needs Plans (C-SNP).
A3: Daily Grid | B3: One row per calendar day. Enrollment-period flags, disaster SEP notes, and event details for that day.
A4: Events | B4: One row per curated policy/market event. Only events that plausibly change plan value or consumer shopping behavior are included; procedural and administrative milestones are excluded.
A5: FEMA Disasters | B5: Raw pull of ALL FEMA disaster declarations in the window, via API. Comprehensive by design, so irrelevant/minor declarations (noise) are included - filter before analysis.
A6: Fed Register | B6: Raw pull of ALL CMS documents published in the Federal Register in the window, via API, keyword-scanned. Comprehensive by design - most rows are noise; filter on Match and Priority.
A8: DAILY GRID - COLUMNS
A9: Date | B9: One row per day, 1/1/2024 - 5/31/2026.
A10: Year / Month / Weekday | B10: Derived from Date, for filtering and pivots.
A11: AEP | B11: Equals 1 during the Annual Enrollment Period (Oct 15 - Dec 7 each year). Anyone with Medicare can switch between Original Medicare and Medicare Advantage, or change drug plans. Rows highlight blue.
A12: MA_OEP / GEP | B12: Equals 1 from Jan 1 - Mar 31 each year. MA OEP: people already in a Medicare Advantage plan get one switch to another MA plan or back to Original Medicare. GEP (same window): people who missed their initial signup can enroll in Part A and/or Part B. Both rows highlight green.
A13: SEP_Notes | B13: Disaster-related Special Enrollment Period notes, built automatically from the FEMA Disasters tab. Shows incident begin/end dates and SEP open dates, with disaster type, affected state, declaration type, and declaration number. SEPs let people affected by a disaster enroll or switch outside the normal windows. FM (Fire Management Assistance declarations) unincluded; only emergency or major-disaster declarations qualifies for SEPs.
A14: Has_Event | B14: Count of Events-tab rows dated on that day (0 = no event).
A15: Event_Detail | B15: Description of each event on that day, joined with " | " when several fall on the same date. Non-national events show state codes in brackets.
A16: Row color key | B16: Orange = policy event day | Blue = AEP | Green = MA OEP / GEP.
A18: EVENTS - COLUMNS
A19: Date | B19: The date of the event.
A20: Event_Type | B20: CMS Rule (federal regulation), Legislation (law passed by Congress or a state), State Regulation (state-level rule, e.g., Medigap birthday rules), Rate Announcement (payment/premium figures set), Litigation (court action that changed which policy was in effect), Enrollment Milestone (dates that structure the shopping cycle), Plan Landscape Release (Star Ratings / plan info publication), Other.
A21: Affects | B21: Which products the event touches: MA, MS, Part D, D-SNP, C-SNP, or All. Multiple products are separated by " / ".
A22: Date_Type | B22: Announced = the day the rule/notice was published (expect market/news/search reaction). Effective = the day the policy actually changes plan value. Deadline = a required-by date (e.g., ANOC delivery).
A23: Description | B23: What happened and why it matters. For D-SNP/C-SNP-relevant events, a mechanism note is appended after "||" explaining the expected effect on SNP enrollment.
A24: Source | B24: URL(s) documenting the event.
A25: States | B25: National, or semicolon-delimited state postal codes for state-level events.
A26: Value_Mechanism | B26: How the event changes plan value or shopping behavior. Categories defined below.
A28: VALUE_MECHANISM CATEGORIES
A29: Benefit/Cost Value | B29: Directly changes benefits, premiums, or out-of-pocket costs (IRA drug-cost milestones, Rate Announcements that fund benefits, Part B premium changes, negotiated drug prices taking effect, Medigap rating changes).
A30: Plan Rules/Structure | B30: Changes what plans can exist or who can enroll where (D-SNP look-alike thresholds, dual-SEP restructure, FIDE/HIDE requirements, CalAIM, OBBBA eligibility changes).
A31: Switching Window | B31: Creates or opens a guaranteed-issue or switching right on a specific date (state Medigap birthday rules, Rhode Island annual window).
A32: Quality Ratings | B32: Changes the displayed Star Ratings or quality bonus economics (annual ratings publications, ratings litigation and recalculations).
A33: Distribution/Commission | B33: Changes broker/agent compensation or steering economics.
A34: Shopping Cycle | B34: Structures when and how beneficiaries shop (plan marketing start dates, ANOC delivery deadlines, plan-finder information rules).
A35: Forward Signal | B35: Announced policy whose value impact lands after the event date (proposed rules, advance notices, drug-negotiation selections, bill signings ahead of effective dates). Expect news/search reaction on the date, not a sales-value change.
A37: FEMA DISASTERS - SOURCE AND COLUMNS
A38: Source | B38: OpenFEMA Disaster Declarations Summaries API (api.fema.gov). ALL declarations with incidents in the window were pulled programmatically - no manual curation, so noises are included. Filter by Decl_Type, Incident_Type, or IA_Declared before analysis.
A39: Disaster_Num / State / Title | B39: FEMA declaration number, affected state, and official incident title.
A40: Decl_Type | B40: DR = major disaster declaration; EM = emergency declaration; FM = fire management assistance (FM does not generate an enrollment SEP).
A41: Incident_Type | B41: FEMA's category (Severe Storm, Hurricane, Flood, Fire, etc.).
A42: Incident_Begin / Incident_End / Declaration_Date | B42: When the incident started and ended, and when FEMA formally declared it.
A43: IA_Declared | B43: TRUE if Individual Assistance was authorized (help to households, not just governments).
A44: Designated_Areas | B44: Count of counties/areas designated under the declaration.
A45: SEP_Start / SEP_End | B45: Enrollment SEP window implied by the declaration, per the CMS disaster/emergency SEP rule: for DR and EM declarations, SEP_Start = the earlier of the incident begin date and the declaration date; SEP_End = the last day of the second full calendar month after the SEP start month. These feed the Daily Grid SEP_Notes column.
A47: FED REGISTER - SOURCE AND COLUMNS
A48: Source | B48: Federal Register API (federalregister.gov). ALL CMS documents published Jan 2024 - May 2026 were pulled programmatically and their full text scanned for MA/Medigap/SNP keywords - no manual curation, so noises are included. Filter Match = 1, then use Priority.
A49: Doc_Number / Type / Pub_Date / Effective_Date | B49: Federal Register document ID, document type (Rule, Proposed Rule, Notice), publication date, and stated effective date if any.
A50: Match / Matched_Keywords | B50: Match = 1 if the document's text contains at least one tracked keyword. Matched_Keywords lists each keyword with its hit count - e.g., "medicare advantage(31); d-snp(6)" is a core document, while a lone "part d(1)" is a passing mention.
A51: Keyword list | B51: Medicare Advantage; MA organization; Part C; Part D; special needs plan; D-SNP; C-SNP; dual eligible; Medigap; Medicare supplement.
A52: Title / Abstract / URL / Full_Text_Scanned | B52: Document title, official abstract, link to the document, and whether full text was retrieved and scanned (Y/N).
A53: Priority | B53: Assigned only to Match = 1 documents. SKIP = procedural/administrative notices and annual provider payment rules (reimbursement rates, not consumer-facing plan features) - exception: kept if strong keyword count >= 200 in case a payment rule carries major MA policy. LOW = strong keyword count <= 10 (marginal; check keywords before dismissing). MEDIUM = count 10-99 (reviewed for relevance). HIGH = count >= 100 (core MA/Part D policy documents).
A54: Trim_Note | B54: Processing note (e.g., if a document's text was truncated during scanning).
