Workbook

Sheet Daily Grid
A1: Date | B1: Year | C1: Month | D1: Weekday | E1: AEP | F1: MA_OEP / GEP | G1: SEP_Notes | H1: Has_Event | I1: Event_Detail
A2: 45292 | B2: =YEAR($A2) -> 2024 | C2: =MONTH($A2) -> 1 | D2: =TEXT($A2,"ddd") -> Mon | E2: =IF(OR(AND(MONTH($A2)=10,DAY($A2)>=15),MONTH($A2)=11,AND(MONTH($A2)=12,DAY($A2)<=7)),1,0) -> 0 | F2: =IF(MONTH($A2)<=3,1,0) -> 1 | H2: =COUNTIF(Events!$A$2:$A$391,$A2) -> 1 | I2: =IFERROR(INDEX(Events!$E$2:$E$391,MATCH($A2,Events!$A$2:$A$391,0)),"") -> IRA phase-in: 5% coinsurance in Part D catastrophic phase eliminated; full Low-Income Subsidy (Extra Help) expanded to 150% FPL
A3: 45293 | B3: =YEAR($A3) -> 2024 | C3: =MONTH($A3) -> 1 | D3: =TEXT($A3,"ddd") -> Tue | E3: =IF(OR(AND(MONTH($A3)=10,DAY($A3)>=15),MONTH($A3)=11,AND(MONTH($A3)=12,DAY($A3)<=7)),1,0) -> 0 | F3: =IF(MONTH($A3)<=3,1,0) -> 1 | H3: =COUNTIF(Events!$A$2:$A$391,$A3) -> 0 | I3: =IFERROR(INDEX(Events!$E$2:$E$391,MATCH($A3,Events!$A$2:$A$391,0)),"")
A4: 45294 | B4: =YEAR($A4) -> 2024 | C4: =MONTH($A4) -> 1 | D4: =TEXT($A4,"ddd") -> Wed | E4: =IF(OR(AND(MONTH($A4)=10,DAY($A4)>=15),MONTH($A4)=11,AND(MONTH($A4)=12,DAY($A4)<=7)),1,0) -> 0 | F4: =IF(MONTH($A4)<=3,1,0) -> 1 | H4: =COUNTIF(Events!$A$2:$A$391,$A4) -> 0 | I4: =IFERROR(INDEX(Events!$E$2:$E$391,MATCH($A4,Events!$A$2:$A$391,0)),"")
A5: 45295 | B5: =YEAR($A5) -> 2024 | C5: =MONTH($A5) -> 1 | D5: =TEXT($A5,"ddd") -> Thu | E5: =IF(OR(AND(MONTH($A5)=10,DAY($A5)>=15),MONTH($A5)=11,AND(MONTH($A5)=12,DAY($A5)<=7)),1,0) -> 0 | F5: =IF(MONTH($A5)<=3,1,0) -> 1 | H5: =COUNTIF(Events!$A$2:$A$391,$A5) -> 0 | I5: =IFERROR(INDEX(Events!$E$2:$E$391,MATCH($A5,Events!$A$2:$A$391,0)),"")
A6: 45296 | B6: =YEAR($A6) -> 2024 | C6: =MONTH($A6) -> 1 | D6: =TEXT($A6,"ddd") -> Fri | E6: =IF(OR(AND(MONTH($A6)=10,DAY($A6)>=15),MONTH($A6)=11,AND(MONTH($A6)=12,DAY($A6)<=7)),1,0) -> 0 | F6: =IF(MONTH($A6)<=3,1,0) -> 1 | G6: Severe Storm begin: [WA] | H6: =COUNTIF(Events!$A$2:$A$391,$A6) -> 0 | I6: =IFERROR(INDEX(Events!$E$2:$E$391,MATCH($A6,Events!$A$2:$A$391,0)),"")
A7: 45297 | B7: =YEAR($A7) -> 2024 | C7: =MONTH($A7) -> 1 | D7: =TEXT($A7,"ddd") -> Sat | E7: =IF(OR(AND(MONTH($A7)=10,DAY($A7)>=15),MONTH($A7)=11,AND(MONTH($A7)=12,DAY($A7)<=7)),1,0) -> 0 | F7: =IF(MONTH($A7)<=3,1,0) -> 1 | H7: =COUNTIF(Events!$A$2:$A$391,$A7) -> 0 | I7: =IFERROR(INDEX(Events!$E$2:$E$391,MATCH($A7,Events!$A$2:$A$391,0)),"")
A8: 45298 | B8: =YEAR($A8) -> 2024 | C8: =MONTH($A8) -> 1 | D8: =TEXT($A8,"ddd") -> Sun | E8: =IF(OR(AND(MONTH($A8)=10,DAY($A8)>=15),MONTH($A8)=11,AND(MONTH($A8)=12,DAY($A8)<=7)),1,0) -> 0 | F8: =IF(MONTH($A8)<=3,1,0) -> 1 | H8: =COUNTIF(Events!$A$2:$A$391,$A8) -> 0 | I8: =IFERROR(INDEX(Events!$E$2:$E$391,MATCH($A8,Events!$A$2:$A$391,0)),"")
A9: 45299 | B9: =YEAR($A9) -> 2024 | C9: =MONTH($A9) -> 1 | D9: =TEXT($A9,"ddd") -> Mon | E9: =IF(OR(AND(MONTH($A9)=10,DAY($A9)>=15),MONTH($A9)=11,AND(MONTH($A9)=12,DAY($A9)<=7)),1,0) -> 0 | F9: =IF(MONTH($A9)<=3,1,0) -> 1 | H9: =COUNTIF(Events!$A$2:$A$391,$A9) -> 0 | I9: =IFERROR(INDEX(Events!$E$2:$E$391,MATCH($A9,Events!$A$2:$A$391,0)),"")
A10: 45300 | B10: =YEAR($A10) -> 2024 | C10: =MONTH($A10) -> 1 | D10: =TEXT($A10,"ddd") -> Tue | E10: =IF(OR(AND(MONTH($A10)=10,DAY($A10)>=15),MONTH($A10)=11,AND(MONTH($A10)=12,DAY($A10)<=7)),1,0) -> 0 | F10: =IF(MONTH($A10)<=3,1,0) -> 1 | H10: =COUNTIF(Events!$A$2:$A$391,$A10) -> 0 | I10: =IFERROR(INDEX(Events!$E$2:$E$391,MATCH($A10,Events!$A$2:$A$391,0)),"")
A11: 45301 | B11: =YEAR($A11) -> 2024 | C11: =MONTH($A11) -> 1 | D11: =TEXT($A11,"ddd") -> Wed | E11: =IF(OR(AND(MONTH($A11)=10,DAY($A11)>=15),MONTH($A11)=11,AND(MONTH($A11)=12,DAY($A11)<=7)),1,0) -> 0 | F11: =IF(MONTH($A11)<=3,1,0) -> 1 | H11: =COUNTIF(Events!$A$2:$A$391,$A11) -> 0 | I11: =IFERROR(INDEX(Events!$E$2:$E$391,MATCH($A11,Events!$A$2:$A$391,0)),"")
A12: 45302 | B12: =YEAR($A12) -> 2024 | C12: =MONTH($A12) -> 1 | D12: =TEXT($A12,"ddd") -> Thu | E12: =IF(OR(AND(MONTH($A12)=10,DAY($A12)>=15),MONTH($A12)=11,AND(MONTH($A12)=12,DAY($A12)<=7)),1,0) -> 0 | F12: =IF(MONTH($A12)<=3,1,0) -> 1 | H12: =COUNTIF(Events!$A$2:$A$391,$A12) -> 0 | I12: =IFERROR(INDEX(Events!$E$2:$E$391,MATCH($A12,Events!$A$2:$A$391,0)),"")
A13: 45303 | B13: =YEAR($A13) -> 2024 | C13: =MONTH($A13) -> 1 | D13: =TEXT($A13,"ddd") -> Fri | E13: =IF(OR(AND(MONTH($A13)=10,DAY($A13)>=15),MONTH($A13)=11,AND(MONTH($A13)=12,DAY($A13)<=7)),1,0) -> 0 | F13: =IF(MONTH($A13)<=3,1,0) -> 1 | H13: =COUNTIF(Events!$A$2:$A$391,$A13) -> 0 | I13: =IFERROR(INDEX(Events!$E$2:$E$391,MATCH($A13,Events!$A$2:$A$391,0)),"")
A14: 45304 | B14: =YEAR($A14) -> 2024 | C14: =MONTH($A14) -> 1 | D14: =TEXT($A14,"ddd") -> Sat | E14: =IF(OR(AND(MONTH($A14)=10,DAY($A14)>=15),MONTH($A14)=11,AND(MONTH($A14)=12,DAY($A14)<=7)),1,0) -> 0 | F14: =IF(MONTH($A14)<=3,1,0) -> 1 | H14: =COUNTIF(Events!$A$2:$A$391,$A14) -> 0 | I14: =IFERROR(INDEX(Events!$E$2:$E$391,MATCH($A14,Events!$A$2:$A$391,0)),"")
A15: 45305 | B15: =YEAR($A15) -> 2024 | C15: =MONTH($A15) -> 1 | D15: =TEXT($A15,"ddd") -> Sun | E15: =IF(OR(AND(MONTH($A15)=10,DAY($A15)>=15),MONTH($A15)=11,AND(MONTH($A15)=12,DAY($A15)<=7)),1,0) -> 0 | F15: =IF(MONTH($A15)<=3,1,0) -> 1 | H15: =COUNTIF(Events!$A$2:$A$391,$A15) -> 0 | I15: =IFERROR(INDEX(Events!$E$2:$E$391,MATCH($A15,Events!$A$2:$A$391,0)),"")
A16: 45306 | B16: =YEAR($A16) -> 2024 | C16: =MONTH($A16) -> 1 | D16: =TEXT($A16,"ddd") -> Mon | E16: =IF(OR(AND(MONTH($A16)=10,DAY($A16)>=15),MONTH($A16)=11,AND(MONTH($A16)=12,DAY($A16)<=7)),1,0) -> 0 | F16: =IF(MONTH($A16)<=3,1,0) -> 1 | H16: =COUNTIF(Events!$A$2:$A$391,$A16) -> 0 | I16: =IFERROR(INDEX(Events!$E$2:$E$391,MATCH($A16,Events!$A$2:$A$391,0)),"")
A17: 45307 | B17: =YEAR($A17) -> 2024 | C17: =MONTH($A17) -> 1 | D17: =TEXT($A17,"ddd") -> Tue | E17: =IF(OR(AND(MONTH($A17)=10,DAY($A17)>=15),MONTH($A17)=11,AND(MONTH($A17)=12,DAY($A17)<=7)),1,0) -> 0 | F17: =IF(MONTH($A17)<=3,1,0) -> 1 | H17: =COUNTIF(Events!$A$2:$A$391,$A17) -> 0 | I17: =IFERROR(INDEX(Events!$E$2:$E$391,MATCH($A17,Events!$A$2:$A$391,0)),"")
A18: 45308 | B18: =YEAR($A18) -> 2024 | C18: =MONTH($A18) -> 1 | D18: =TEXT($A18,"ddd") -> Wed | E18: =IF(OR(AND(MONTH($A18)=10,DAY($A18)>=15),MONTH($A18)=11,AND(MONTH($A18)=12,DAY($A18)<=7)),1,0) -> 0 | F18: =IF(MONTH($A18)<=3,1,0) -> 1 | H18: =COUNTIF(Events!$A$2:$A$391,$A18) -> 0 | I18: =IFERROR(INDEX(Events!$E$2:$E$391,MATCH($A18,Events!$A$2:$A$391,0)),"")
... A29: 45319 | B29: =YEAR($A29) -> 2024 | C29: =MONTH($A29) -> 1 | D29: =TEXT($A29,"ddd") -> Sun | E29: =IF(OR(AND(MONTH($A29)=10,DAY($A29)>=15),MONTH($A29)=11,AND(MONTH($A29)=12,DAY($A29)<=7)),1,0) -> 0 | F29: =IF(MONTH($A29)<=3,1,0) -> 1 | H29: =COUNTIF(Events!$A$2:$A$391,$A29) -> 0 | I29: =IFERROR(INDEX(Events!$E$2:$E$391,MATCH($A29,Events!$A$2:$A$391,0)),"")
A30: 45320 | B30: =YEAR($A30) -> 2024 | C30: =MONTH($A30) -> 1 | D30: =TEXT($A30,"ddd") -> Mon | E30: =IF(OR(AND(MONTH($A30)=10,DAY($A30)>=15),MONTH($A30)=11,AND(MONTH($A30)=12,DAY($A30)<=7)),1,0) -> 0 | F30: =IF(MONTH($A30)<=3,1,0) -> 1 | G30: Severe Storm End: [WA] | H30: =COUNTIF(Events!$A$2:$A$391,$A30) -> 0 | I30: =IFERROR(INDEX(Events!$E$2:$E$391,MATCH($A30,Events!$A$2:$A$391,0)),"")
A31: 45321 | B31: =YEAR($A31) -> 2024 | C31: =MONTH($A31) -> 1 | D31: =TEXT($A31,"ddd") -> Tue | E31: =IF(OR(AND(MONTH($A31)=10,DAY($A31)>=15),MONTH($A31)=11,AND(MONTH($A31)=12,DAY($A31)<=7)),1,0) -> 0 | F31: =IF(MONTH($A31)<=3,1,0) -> 1 | G31: SEP open: [WA] | H31: =COUNTIF(Events!$A$2:$A$391,$A31) -> 0 | I31: =IFERROR(INDEX(Events!$E$2:$E$391,MATCH($A31,Events!$A$2:$A$391,0)),"")
A32: 45322 | B32: =YEAR($A32) -> 2024 | C32: =MONTH($A32) -> 1 | D32: =TEXT($A32,"ddd") -> Wed | E32: =IF(OR(AND(MONTH($A32)=10,DAY($A32)>=15),MONTH($A32)=11,AND(MONTH($A32)=12,DAY($A32)<=7)),1,0) -> 0 | F32: =IF(MONTH($A32)<=3,1,0) -> 1 | H32: =COUNTIF(Events!$A$2:$A$391,$A32) -> 1 | I32: =IFERROR(INDEX(Events!$E$2:$E$391,MATCH($A32,Events!$A$2:$A$391,0)),"") -> CY2025 Advance Notice released: proposed +3.70% avg payment; year 2 of 3-year phase-in of 2024 CMS-HCC (V28) risk model at 67/33 blend; comments due 3/1/2024
A33: 45323 | B33: =YEAR($A33) -> 2024 | C33: =MONTH($A33) -> 2 | D33: =TEXT($A33,"ddd") -> Thu | E33: =IF(OR(AND(MONTH($A33)=10,DAY($A33)>=15),MONTH($A33)=11,AND(MONTH($A33)=12,DAY($A33)<=7)),1,0) -> 0 | F33: =IF(MONTH($A33)<=3,1,0) -> 1 | H33: =COUNTIF(Events!$A$2:$A$391,$A33) -> 0 | I33: =IFERROR(INDEX(Events!$E$2:$E$391,MATCH($A33,Events!$A$2:$A$391,0)),"")
A34: 45324 | B34: =YEAR($A34) -> 2024 | C34: =MONTH($A34) -> 2 | D34: =TEXT($A34,"ddd") -> Fri | E34: =IF(OR(AND(MONTH($A34)=10,DAY($A34)>=15),MONTH($A34)=11,AND(MONTH($A34)=12,DAY($A34)<=7)),1,0) -> 0 | F34: =IF(MONTH($A34)<=3,1,0) -> 1 | H34: =COUNTIF(Events!$A$2:$A$391,$A34) -> 0 | I34: =IFERROR(INDEX(Events!$E$2:$E$391,MATCH($A34,Events!$A$2:$A$391,0)),"")
A35: 45325 | B35: =YEAR($A35) -> 2024 | C35: =MONTH($A35) -> 2 | D35: =TEXT($A35,"ddd") -> Sat | E35: =IF(OR(AND(MONTH($A35)=10,DAY($A35)>=15),MONTH($A35)=11,AND(MONTH($A35)=12,DAY($A35)<=7)),1,0) -> 0 | F35: =IF(MONTH($A35)<=3,1,0) -> 1 | H35: =COUNTIF(Events!$A$2:$A$391,$A35) -> 0 | I35: =IFERROR(INDEX(Events!$E$2:$E$391,MATCH($A35,Events!$A$2:$A$391,0)),"")
A36: 45326 | B36: =YEAR($A36) -> 2024 | C36: =MONTH($A36) -> 2 | D36: =TEXT($A36,"ddd") -> Sun | E36: =IF(OR(AND(MONTH($A36)=10,DAY($A36)>=15),MONTH($A36)=11,AND(MONTH($A36)=12,DAY($A36)<=7)),1,0) -> 0 | F36: =IF(MONTH($A36)<=3,1,0) -> 1 | H36: =COUNTIF(Events!$A$2:$A$391,$A36) -> 0 | I36: =IFERROR(INDEX(Events!$E$2:$E$391,MATCH($A36,Events!$A$2:$A$391,0)),"")
A37: 45327 | B37: =YEAR($A37) -> 2024 | C37: =MONTH($A37) -> 2 | D37: =TEXT($A37,"ddd") -> Mon | E37: =IF(OR(AND(MONTH($A37)=10,DAY($A37)>=15),MONTH($A37)=11,AND(MONTH($A37)=12,DAY($A37)<=7)),1,0) -> 0 | F37: =IF(MONTH($A37)<=3,1,0) -> 1 | H37: =COUNTIF(Events!$A$2:$A$391,$A37) -> 0 | I37: =IFERROR(INDEX(Events!$E$2:$E$391,MATCH($A37,Events!$A$2:$A$391,0)),"")
A38: 45328 | B38: =YEAR($A38) -> 2024 | C38: =MONTH($A38) -> 2 | D38: =TEXT($A38,"ddd") -> Tue | E38: =IF(OR(AND(MONTH($A38)=10,DAY($A38)>=15),MONTH($A38)=11,AND(MONTH($A38)=12,DAY($A38)<=7)),1,0) -> 0 | F38: =IF(MONTH($A38)<=3,1,0) -> 1 | H38: =COUNTIF(Events!$A$2:$A$391,$A38) -> 0 | I38: =IFERROR(INDEX(Events!$E$2:$E$391,MATCH($A38,Events!$A$2:$A$391,0)),"")
A39: 45329 | B39: =YEAR($A39) -> 2024 | C39: =MONTH($A39) -> 2 | D39: =TEXT($A39,"ddd") -> Wed | E39: =IF(OR(AND(MONTH($A39)=10,DAY($A39)>=15),MONTH($A39)=11,AND(MONTH($A39)=12,DAY($A39)<=7)),1,0) -> 0 | F39: =IF(MONTH($A39)<=3,1,0) -> 1 | H39: =COUNTIF(Events!$A$2:$A$391,$A39) -> 0 | I39: =IFERROR(INDEX(Events!$E$2:$E$391,MATCH($A39,Events!$A$2:$A$391,0)),"")
A40: 45330 | B40: =YEAR($A40) -> 2024 | C40: =MONTH($A40) -> 2 | D40: =TEXT($A40,"ddd") -> Thu | E40: =IF(OR(AND(MONTH($A40)=10,DAY($A40)>=15),MONTH($A40)=11,AND(MONTH($A40)=12,DAY($A40)<=7)),1,0) -> 0 | F40: =IF(MONTH($A40)<=3,1,0) -> 1 | H40: =COUNTIF(Events!$A$2:$A$391,$A40) -> 0 | I40: =IFERROR(INDEX(Events!$E$2:$E$391,MATCH($A40,Events!$A$2:$A$391,0)),"")
A41: 45331 | B41: =YEAR($A41) -> 2024 | C41: =MONTH($A41) -> 2 | D41: =TEXT($A41,"ddd") -> Fri | E41: =IF(OR(AND(MONTH($A41)=10,DAY($A41)>=15),MONTH($A41)=11,AND(MONTH($A41)=12,DAY($A41)<=7)),1,0) -> 0 | F41: =IF(MONTH($A41)<=3,1,0) -> 1 | H41: =COUNTIF(Events!$A$2:$A$391,$A41) -> 0 | I41: =IFERROR(INDEX(Events!$E$2:$E$391,MATCH($A41,Events!$A$2:$A$391,0)),"")
A42: 45332 | B42: =YEAR($A42) -> 2024 | C42: =MONTH($A42) -> 2 | D42: =TEXT($A42,"ddd") -> Sat | E42: =IF(OR(AND(MONTH($A42)=10,DAY($A42)>=15),MONTH($A42)=11,AND(MONTH($A42)=12,DAY($A42)<=7)),1,0) -> 0 | F42: =IF(MONTH($A42)<=3,1,0) -> 1 | H42: =COUNTIF(Events!$A$2:$A$391,$A42) -> 0 | I42: =IFERROR(INDEX(Events!$E$2:$E$391,MATCH($A42,Events!$A$2:$A$391,0)),"")
A43: 45333 | B43: =YEAR($A43) -> 2024 | C43: =MONTH($A43) -> 2 | D43: =TEXT($A43,"ddd") -> Sun | E43: =IF(OR(AND(MONTH($A43)=10,DAY($A43)>=15),MONTH($A43)=11,AND(MONTH($A43)=12,DAY($A43)<=7)),1,0) -> 0 | F43: =IF(MONTH($A43)<=3,1,0) -> 1 | H43: =COUNTIF(Events!$A$2:$A$391,$A43) -> 0 | I43: =IFERROR(INDEX(Events!$E$2:$E$391,MATCH($A43,Events!$A$2:$A$391,0)),"")
... A883: 46173 | B883: =YEAR($A883) -> 2026 | C883: =MONTH($A883) -> 5 | D883: =TEXT($A883,"ddd") -> Sun | E883: =IF(OR(AND(MONTH($A883)=10,DAY($A883)>=15),MONTH($A883)=11,AND(MONTH($A883)=12,DAY($A883)<=7)),1,0) -> 0 | F883: =IF(MONTH($A883)<=3,1,0) -> 0 | H883: =COUNTIF(Events!$A$2:$A$391,$A883) -> 0 | I883: =IFERROR(INDEX(Events!$E$2:$E$391,MATCH($A883,Events!$A$2:$A$391,0)),"")

Sheet Events
A1: Date | B1: Event_Type | C1: Affects | D1: Date_Type | E1: Description | F1: Source
A2: 45292 | B2: Legislation | C2: Part D | D2: Effective | E2: IRA phase-in: 5% coinsurance in Part D catastrophic phase eliminated; full Low-Income Subsidy (Extra Help) expanded to 150% FPL | F2: https://www.cms.gov/newsroom/fact-sheets/2024-medicare-advantage-and-part-d-final-rule-cms-4201-f
A3: 45322 | B3: Rate Announcement | C3: MA / Part D | D3: Announced | E3: CY2025 Advance Notice released: proposed +3.70% avg payment; year 2 of 3-year phase-in of 2024 CMS-HCC (V28) risk model at 67/33 blend; comments due 3/1/2024 | F3: https://www.cms.gov/newsroom/fact-sheets/2025-medicare-advantage-part-d-advance-notice-fact-sheet
A4: 45383 | B4: Rate Announcement | C4: MA / Part D | D4: Announced | E4: CY2025 Rate Announcement: final MA capitation rates (+3.70% avg) and Part C/D payment policies | F4: https://www.cms.gov/newsroom/fact-sheets/2026-medicare-advantage-part-d-rate-announcement
A5: 45386 | B5: CMS Rule | C5: MA / Part D / D-SNP | D5: Announced | E5: CY2025 MA & Part D Final Rule (CMS-4205-F): fixed agent/broker compensation (+$100 initial), TPMO one-to-one consent for data sharing, mid-year unused-benefits notice, SSBCI evidence requirements, dual/LIS SEP overhaul, D-SNP look-alike threshold phase-down, behavioral health network adequacy | F5: https://www.cms.gov/newsroom/fact-sheets/contract-year-2025-medicare-advantage-part-d-final-rule-cms-4205-f
A6: 45446 | B6: CMS Rule | C6: MA / Part D | D6: Effective | E6: CY2025 Final Rule regulations take effect (most provisions apply to coverage beginning 1/1/2025; agent/broker compensation changes apply beginning with Fall 2024 AEP) | F6: https://www.federalregister.gov/documents/2024/04/23/2024-07105/medicare-program-changes-to-the-medicare-advantage-and-the-medicare-prescription-drug-benefit
A7: 45566 | B7: Enrollment Milestone | C7: MA / Part D | D7: Effective | E7: CY2025 plan marketing begins; plan landscape/benefit info for 2025 released ahead of AEP; new agent/broker fixed compensation applies to Fall 2024 AEP enrollments | F7: https://www.cms.gov/newsroom/fact-sheets/contract-year-2025-medicare-advantage-part-d-final-rule-cms-4205-f
A8: 45575 | B8: Plan Landscape Release | C8: MA / Part D | D8: Announced | E8: 2025 Star Ratings published on Medicare Plan Finder: sharp industry decline - only 7 MA-PD contracts earned 5 stars (vs 38 for 2024); avg rating fell to ~3.92; drives 2026 quality bonus payments | F8: https://www.cms.gov/newsroom/fact-sheets/2025-medicare-advantage-part-d-star-ratings
A9: 45622 | B9: CMS Rule | C9: MA / Part D / D-SNP | D9: Announced | E9: CY2026 Proposed Rule (CMS-4208-P): proposed anti-obesity med coverage in Part D, AI guardrails, prior-auth/UM limits (published in Federal Register 12/10/2024; comments due 1/27/2025; several proposals later NOT finalized) | F9: https://www.cms.gov/newsroom/fact-sheets/contract-year-2026-policy-and-technical-changes-medicare-advantage-program-medicare-prescription
A10: 45658 | B10: Legislation | C10: Part D / MA / D-SNP | D10: Effective | E10: IRA: $2,000 annual Part D OOP cap begins; coverage gap eliminated (3-phase benefit); Medicare Prescription Payment Plan launches; Manufacturer Discount Program replaces Coverage Gap Discount Program; CY2025 Final Rule provisions apply incl. monthly integrated-care SEP for duals (replaces quarterly dual SEP) and D-SNP look-alike threshold lowered to 70% | F10: https://www.cms.gov/newsroom/fact-sheets/2025-medicare-advantage-part-d-advance-notice-fact-sheet ; https://www.cms.gov/newsroom/fact-sheets/contract-year-2025-medicare-advantage-part-d-final-rule-cms-4205-f
A11: 45667 | B11: Rate Announcement | C11: MA / Part D | D11: Announced | E11: CY2026 Advance Notice released: proposed +4.33% avg payment (~$21B); final year of V28 risk model phase-in; comments due 2/10/2025 | F11: https://www.cms.gov/newsroom/fact-sheets/2026-medicare-advantage-part-d-advance-notice-fact-sheet
A12: 45751 | B12: CMS Rule | C12: MA / Part D / D-SNP | D12: Announced | E12: CY2026 Final Rule (CMS-4208-F): scaled back vs proposed (dropped anti-obesity meds, AI guardrails, health equity analysis); finalized inpatient prior-auth protections, appeals loophole fixes, SSBCI non-allowable list, Rx Payment Plan auto-renewal, D-SNP integrated ID cards/HRAs by 2027 | F12: https://www.cms.gov/newsroom/fact-sheets/contract-year-2026-policy-and-technical-changes-medicare-advantage-program-medicare-prescription-final
A13: 45754 | B13: Rate Announcement | C13: MA / Part D | D13: Announced | E13: CY2026 Rate Announcement: +5.06% avg payment (~$25B, up from proposed 4.33%); V28 risk model phase-in complete (100%); Final CY2026 Part D Redesign Instructions | F13: https://www.cms.gov/newsroom/fact-sheets/2026-medicare-advantage-part-d-rate-announcement
... A22: 46118 | B22: Rate Announcement | C22: MA / Part D | D22: Announced | E22: CY2027 Rate Announcement: finalized +2.48% avg payment (~$13B, sharply up from proposed 0.09% after industry lobbying); kept 2024 (V28) risk model instead of proposed update; finalized exclusion of unlinked chart-review diagnoses from risk scores | F22: https://www.cms.gov/files/document/2027-announcement.pdf ; https://www.aha.org/news/headline/2026-04-06-cms-finalizes-medicare-advantage-rates-cy-2027

Sheet FEMA Disasters
A1: Disaster_Num | B1: State | C1: Decl_Type | D1: Incident_Type | E1: Title | F1: Incident_Begin | G1: Incident_End | H1: Declaration_Date | I1: IA_Declared | J1: Designated_Areas | K1: SEP_End_Est
A2: 4775 | B2: WA | C2: DR | D2: Severe Storm | E2: SEVERE WINTER STORMS, STRAIGHT-LINE WINDS, FLOODING, LANDSLIDES, AND MUDSLIDES | F2: 45296 | G2: 45320 | H2: 45410 | I2: FALSE | J2: 17 | K2: 45382
A3: 4774 | B3: KS | C3: DR | D3: Winter Storm | E3: SEVERE WINTER STORM | F3: 45299 | G3: 45307 | H3: 45410 | I3: FALSE | J3: 17 | K3: 45382
A4: 4764 | B4: ME | C4: DR | D4: Severe Storm | E4: SEVERE STORMS AND FLOODING | F4: 45300 | G4: 45304 | H4: 45371 | I4: FALSE | J4: 8 | K4: 45382
A5: 4766 | B5: RI | C5: DR | D5: Severe Storm | E5: SEVERE STORMS AND FLOODING | F5: 45300 | G5: 45304 | H5: 45371 | I5: FALSE | J5: 4 | K5: 45382
A6: 4770 | B6: VT | C6: DR | D6: Severe Storm | E6: SEVERE WINTER STORM | F6: 45300 | G6: 45304 | H6: 45401 | I6: FALSE | J6: 5 | K6: 45382
A7: 4771 | B7: NH | C7: DR | D7: Severe Storm | E7: SEVERE STORMS AND FLOODING | F7: 45300 | G7: 45305 | H7: 45401 | I7: FALSE | J7: 2 | K7: 45382
A8: 3604 | B8: CT | C8: EM | D8: Severe Storm | E8: SEVERE STORMS, FLOODING, AND A POTENTIAL DAM BREACH | F8: 45301 | G8: 45304 | H8: 45304 | I8: FALSE | J8: 3 | K8: 45382
A9: 4768 | B9: OR | C9: DR | D9: Severe Storm | E9: SEVERE WINTER STORMS, STRAIGHT-LINE WINDS, LANDSLIDES, AND MUDSLIDES | F9: 45301 | G9: 45313 | H9: 45395 | I9: FALSE | J9: 13 | K9: 45382
A10: 4758 | B10: CA | C10: DR | D10: Flood | E10: SEVERE STORM AND FLOODING | F10: 45312 | G10: 45314 | H10: 45341 | I10: FALSE | J10: 1 | K10: 45382
A11: 4773 | B11: CA | C11: DR | D11: Severe Storm | E11: SEVERE WINTER STORM | F11: 45321 | G11: 45322 | H11: 45401 | I11: FALSE | J11: 1 | K11: 45382
A12: 4769 | B12: CA | C12: DR | D12: Severe Storm | E12: SEVERE WINTER STORMS, TORNADOES, FLOODING, LANDSLIDES, AND MUDSLIDES | F12: 45322 | G12: 45331 | H12: 45395 | I12: FALSE | J12: 9 | K12: 45412
A13: 4772 | B13: CA | C13: DR | D13: Severe Storm | E13: SEVERE STORMS AND FLOODING | F13: 45322 | G13: 45331 | H13: 45401 | I13: FALSE | J13: 1 | K13: 45412
... A38: 4794 | B38: FL | C38: DR | D38: Severe Storm | E38: SEVERE STORMS, STRAIGHT-LINE WINDS, AND TORNADOES | F38: 45422 | G38: 45422 | H38: 45460 | I38: FALSE | J38: 13 | K38: 45504
A39: 5492 | B39: NM | C39: FM | D39: Fire | E39: BLUE 2 FIRE | F39: 45428 | H39: 45438 | I39: FALSE | J39: 1
A40: 4791 | B40: OK | C40: DR | D40: Severe Storm | E40: SEVERE STORMS, STRAIGHT-LINE WINDS, TORNADOES, AND FLOODING | F40: 45431 | G40: 45440 | H40: 45457 | I40: FALSE | J40: 10 | K40: 45504
A41: 4803 | B41: MO | C41: DR | D41: Severe Storm | E41: SEVERE STORMS, STRAIGHT-LINE WINDS, TORNADOES, AND FLOODING | F41: 45431 | G41: 45439 | H41: 45496 | I41: FALSE | J41: 15 | K41: 45504
A42: 4811 | B42: KS | C42: DR | D42: Severe Storm | E42: SEVERE STORM, STRAIGHT-LINE WINDS, TORNADOES, AND FLOODING | F42: 45431 | G42: 45431 | H42: 45524 | I42: FALSE | J42: 14 | K42: 45504
A43: 4784 | B43: IA | C43: DR | D43: Severe Storm | E43: SEVERE STORMS, TORNADOES, AND FLOODING | F43: 45432 | G43: 45443 | H43: 45436 | I43: FALSE | J43: 29 | K43: 45504
A44: 4808 | B44: NE | C44: DR | D44: Severe Storm | E44: SEVERE STORMS, STRAIGHT-LINE WINDS, TORNADOES, AND FLOODING | F44: 45432 | G44: 45446 | H44: 45524 | I44: FALSE | J44: 19 | K44: 45535
A45: 4804 | B45: KY | C45: DR | D45: Severe Storm | E45: SEVERE STORMS, STRAIGHT-LINE WINDS, TORNADOES, LANDSLIDES, AND MUDSLIDES | F45: 45433 | G45: 45439 | H45: 45496 | I45: FALSE | J45: 58 | K45: 45504
A46: 4788 | B46: AR | C46: DR | D46: Severe Storm | E46: SEVERE STORMS, STRAIGHT-LINE WINDS, TORNADOES, AND FLOODING | F46: 45436 | G46: 45439 | H46: 45442 | I46: FALSE | J46: 11 | K46: 45504
A47: 5493 | B47: AZ | C47: FM | D47: Fire | E47: SIMMONS FIRE | F47: 45440 | G47: 45443 | H47: 45441 | I47: FALSE | J47: 1 | K47: 45504
A48: 5494 | B48: NV | C48: FM | D48: Fire | E48: TRAIL FIRE | F48: 45454 | G48: 45456 | H48: 45454 | I48: FALSE | J48: 1 | K48: 45535
A49: 5495 | B49: NV | C49: FM | D49: Fire | E49: SULLIVAN FIRE | F49: 45454 | G49: 45455 | H49: 45455 | I49: FALSE | J49: 1 | K49: 45535
A50: 5496 | B50: AZ | C50: FM | D50: Fire | E50: ROSE FIRE | F50: 45455 | G50: 45457 | H50: 45455 | I50: FALSE | J50: 1 | K50: 45535
A51: 4796 | B51: IA | C51: DR | D51: Severe Storm | E51: SEVERE STORMS, FLOODING, STRAIGHT-LINE WINDS, AND TORNADOES | F51: 45459 | G51: 45496 | H51: 45467 | I51: FALSE | J51: 29 | K51: 45565
... A54: 4795 | B54: NM | C54: DR | D54: Fire | E54: SOUTH FORK FIRE, SALT FIRE, AND FLOODING | F54: 45460 | G54: 45524 | H54: 45463 | I54: FALSE | J54: 5 | K54: 45596
A55: 5497 | B55: NM | C55: FM | D55: Fire | E55: SOUTH FORK FIRE | F55: 45460 | H55: 45460 | I55: FALSE | J55: 3
A56: 5498 | B56: NM | C56: FM | D56: Fire | E56: SALT FIRE | F56: 45460 | H56: 45461 | I56: FALSE | J56: 3
A57: 4822 | B57: NE | C57: DR | D57: Severe Storm | E57: SEVERE STORMS, STRAIGHT-LINE WINDS, TORNADOES, AND FLOODING | F57: 45462 | G57: 45481 | H57: 45559 | I57: FALSE | J57: 17 | K57: 45565
A58: 4809 | B58: NM | C58: DR | D58: Flood | E58: SEVERE STORMS AND FLOODING | F58: 45463 | G58: 45464 | H58: 45524 | I58: FALSE | J58: 1 | K58: 45535
A59: 4823 | B59: WA | C59: DR | D59: Fire | E59: WILDFIRES | F59: 45465 | G59: 45481 | H59: 45559 | I59: FALSE | J59: 1 | K59: 45565
A60: 5499 | B60: WA | C60: FM | D60: Fire | E60: SLIDE RANCH FIRE | F60: 45465 | G60: 45484 | H60: 45466 | I60: FALSE | J60: 2 | K60: 45565
A61: 5500 | B61: OR | C61: FM | D61: Fire | E61: DARLENE 3 FIRE | F61: 45468 | H61: 45468 | I61: FALSE | J61: 1
A62: 4824 | B62: KS | C62: DR | D62: Severe Storm | E62: SEVERE STORMS, STRAIGHT-LINE WINDS, TORNADOES, AND FLOODING | F62: 45469 | G62: 45480 | H62: 45559 | I62: FALSE | J62: 17 | K62: 45565
A63: 5501 | B63: AZ | C63: FM | D63: Fire | E63: BOULDER VIEW FIRE | F63: 45471 | G63: 45473 | H63: 45471 | I63: FALSE | J63: 1 | K63: 45535
A64: 5502 | B64: CA | C64: FM | D64: Fire | E64: THOMPSON FIRE | F64: 45475 | G64: 45479 | H64: 45475 | I64: FALSE | J64: 1 | K64: 45565
A65: 5503 | B65: CA | C65: FM | D65: Fire | E65: FRENCH FIRE | F65: 45477 | G65: 45480 | H65: 45478 | I65: FALSE | J65: 1 | K65: 45565
A66: 4798 | B66: TX | C66: DR | D66: Hurricane | E66: HURRICANE BERYL | F66: 45478 | G66: 45482 | H66: 45482 | I66: FALSE | J66: 67 | K66: 45565
A67: 5504 | B67: UT | C67: FM | D67: Fire | E67: SILVER KING FIRE | F67: 45480 | G67: 45506 | H67: 45480 | I67: FALSE | J67: 1 | K67: 45596
A68: 4810 | B68: VT | C68: DR | D68: Severe Storm | E68: SEVERE STORM, FLOODING, LANDSLIDES, AND MUDSLIDES | F68: 45482 | G68: 45484 | H68: 45524 | I68: FALSE | J68: 8 | K68: 45565
A69: 5505 | B69: AZ | C69: FM | D69: Fire | E69: SHAKE FIRE | F69: 45482 | G69: 45483 | H69: 45482 | I69: FALSE | J69: 1 | K69: 45565
A70: 5507 | B70: MT | C70: FM | D70: Fire | E70: HORSE GULCH FIRE | F70: 45482 | H70: 45485 | I70: FALSE | J70: 2
A71: 4812 | B71: NH | C71: DR | D71: Severe Storm | E71: SEVERE STORM AND FLOODING | F71: 45483 | G71: 45486 | H71: 45524 | I71: FALSE | J71: 2 | K71: 45565
A72: 4814 | B72: NY | C72: DR | D72: Flood | E72: SEVERE STORM, TORNADOES, AND FLOODING | F72: 45483 | G72: 45484 | H72: 45533 | I72: FALSE | J72: 5 | K72: 45565
A73: 4833 | B73: AZ | C73: DR | D73: Fire | E73: WATCH FIRE | F73: 45483 | G73: 45490 | H73: 45569 | I73: FALSE | J73: 1 | K73: 45565
A74: 4854 | B74: OR | C74: DR | D74: Fire | E74: WILDFIRES | F74: 45483 | G74: 45527 | H74: 45658 | I74: FALSE | J74: 5 | K74: 45596
A75: 5506 | B75: OR | C75: FM | D75: Fire | E75: LARCH CREEK FIRE | F75: 45483 | H75: 45484 | I75: FALSE | J75: 1
A76: 5508 | B76: AZ | C76: FM | D76: Fire | E76: WATCH FIRE | F76: 45483 | G76: 45488 | H76: 45486 | I76: FALSE | J76: 1 | K76: 45565
A77: 4819 | B77: IL | C77: DR | D77: Flood | E77: SEVERE STORMS, TORNADOES, STRAIGHT-LINE WINDS, AND FLOODNG | F77: 45486 | G77: 45489 | H77: 45555 | I77: FALSE | J77: 7 | K77: 45565
A78: 4842 | B78: SD | C78: DR | D78: Severe Storm | E78: SEVERE STORM, STRAIGHT-LINE WINDS, AND FLOODING | F78: 45486 | G78: 45487 | H78: 45597 | I78: FALSE | J78: 1 | K78: 45565
A79: 5510 | B79: ID | C79: FM | D79: Fire | E79: TEXAS FIRE | F79: 45488 | G79: 45494 | H79: 45489 | I79: FALSE | J79: 2 | K79: 45565
A80: 5509 | B80: NV | C80: FM | D80: Fire | E80: SPRING VALLEY FIRE | F80: 45489 | G80: 45490 | H80: 45489 | I80: FALSE | J80: 1 | K80: 45565
A81: 4849 | B81: WA | C81: DR | D81: Fire | E81: WILDFIRES | F81: 45490 | G81: 45525 | H81: 45622 | I81: FALSE | J81: 1 | K81: 45596
A82: 5511 | B82: OR | C82: FM | D82: Fire | E82: LONE ROCK FIRE | F82: 45490 | H82: 45491 | I82: FALSE | J82: 3
A83: 5518 | B83: WA | C83: FM | D83: Fire | E83: SWAWILLA FIRE | F83: 45490 | G83: 45494 | H83: 45497 | I83: FALSE | J83: 3 | K83: 45565
A84: 5512 | B84: OR | C84: FM | D84: Fire | E84: FALLS FIRE | F84: 45491 | H84: 45491 | I84: FALSE | J84: 2
A85: 5513 | B85: OR | C85: FM | D85: Fire | E85: BONEYARD FIRE | F85: 45493 | H85: 45494 | I85: FALSE | J85: 1
A86: 5514 | B86: OR | C86: FM | D86: Fire | E86: BATTLE MOUNTAIN FIRE COMPLEX | F86: 45494 | H86: 45494 | I86: FALSE | J86: 3
A87: 5515 | B87: CA | C87: FM | D87: Fire | E87: HAWARDEN FIRE | F87: 45494 | G87: 45495 | H87: 45494 | I87: FALSE | J87: 1 | K87: 45565
A88: 5516 | B88: OR | C88: FM | D88: Fire | E88: DURKEE FIRE | F88: 45494 | H88: 45495 | I88: FALSE | J88: 2
A89: 5517 | B89: WA | C89: FM | D89: Fire | E89: WEST WHITE SWAN FIRE | F89: 45495 | G89: 45501 | H89: 45496 | I89: FALSE | J89: 2 | K89: 45565
A90: 4813 | B90: MT | C90: DR | D90: Straight-Line Winds | E90: STRAIGHT-LINE WINDS | F90: 45497 | G90: 45497 | H90: 45527 | I90: FALSE | J90: 2 | K90: 45565
A91: 5519 | B91: CA | C91: FM | D91: Fire | E91: PARK FIRE | F91: 45497 | G91: 45524 | H91: 45498 | I91: FALSE | J91: 2 | K91: 45596
A92: 5520 | B92: ID | C92: FM | D92: Fire | E92: GWEN FIRE | F92: 45498 | G92: 45513 | H92: 45499 | I92: FALSE | J92: 3 | K92: 45596
A93: 5521 | B93: WA | C93: FM | D93: Fire | E93: RETREAT FIRE | F93: 45498 | G93: 45527 | H93: 45499 | I93: FALSE | J93: 1 | K93: 45596
A94: 5522 | B94: CA | C94: FM | D94: Fire | E94: BOREL FIRE | F94: 45498 | G94: 45514 | H94: 45500 | I94: FALSE | J94: 1 | K94: 45596
A95: 4826 | B95: VT | C95: DR | D95: Flood | E95: SEVERE STORMS, FLOODING, LANDSLIDES, AND MUDSLIDES | F95: 45502 | G95: 45504 | H95: 45561 | I95: FALSE | J95: 3 | K95: 45565
A96: 5523 | B96: WY | C96: FM | D96: Fire | E96: PLEASANT VALLEY FIRE | F96: 45503 | G96: 45508 | H96: 45503 | I96: FALSE | J96: 1 | K96: 45596
A97: 5525 | B97: CO | C97: FM | D97: Fire | E97: STONE MOUNTAIN FIRE | F97: 45503 | G97: 45534 | H97: 45504 | I97: FALSE | J97: 2 | K97: 45596
A98: 4838 | B98: NE | C98: DR | D98: Severe Storm | E98: SEVERE STORMS, STRAIGHT-LINE WINDS, TORNADOES, AND FLOODING | F98: 45504 | G98: 45504 | H98: 45586 | I98: FALSE | J98: 5 | K98: 45565
A99: 5524 | B99: CO | C99: FM | D99: Fire | E99: ALEXANDER MOUNTAIN FIRE | F99: 45504 | G99: 45513 | H99: 45504 | I99: FALSE | J99: 1 | K99: 45596
A100: 3605 | B100: FL | C100: EM | D100: Tropical Storm | E100: TROPICAL STORM DEBBY | F100: 45505 | G100: 45531 | H100: 45507 | I100: FALSE | J100: 61 | K100: 45596
... A102: 5526 | B102: CO | C102: FM | D102: Fire | E102: QUARRY FIRE | F102: 45505 | G102: 45511 | H102: 45505 | I102: FALSE | J102: 1 | K102: 45596
A103: 5527 | B103: OR | C103: FM | D103: Fire | E103: MILE MARKER 132 FIRE | F103: 45506 | H103: 45506 | I103: FALSE | J103: 1
A104: 3606 | B104: SC | C104: EM | D104: Tropical Storm | E104: HURRICANE DEBBY | F104: 45508 | G104: 45526 | H104: 45509 | I104: FALSE | J104: 46 | K104: 45596
A105: 3607 | B105: GA | C105: EM | D105: Tropical Storm | E105: HURRICANE DEBBY | F105: 45508 | G105: 45524 | H105: 45509 | I105: FALSE | J105: 55 | K105: 45596
A106: 4821 | B106: GA | C106: DR | D106: Tropical Storm | E106: TROPICAL STORM DEBBY | F106: 45508 | G106: 45524 | H106: 45559 | I106: FALSE | J106: 35 | K106: 45596
A107: 4835 | B107: SC | C107: DR | D107: Tropical Storm | E107: TROPICAL STORM DEBBY | F107: 45508 | G107: 45526 | H107: 45564 | I107: FALSE | J107: 14 | K107: 45596
A108: 5528 | B108: OR | C108: FM | D108: Fire | E108: ELK LANE FIRE | F108: 45508 | H108: 45510 | I108: FALSE | J108: 1
A109: 3608 | B109: NC | C109: EM | D109: Tropical Storm | E109: TROPICAL STORM DEBBY | F109: 45509 | G109: 45523 | H109: 45510 | I109: FALSE | J109: 74 | K109: 45596
A110: 4836 | B110: AK | C110: DR | D110: Flood | E110: FLOODING | F110: 45509 | G110: 45510 | H110: 45581 | I110: FALSE | J110: 1 | K110: 45596
A111: 4847 | B111: MT | C111: DR | D111: Severe Storm | E111: SEVERE STORM AND STRAIGHT-LINE WINDS | F111: 45510 | G111: 45510 | H111: 45610 | I111: FALSE | J111: 1 | K111: 45596
A112: 3609 | B112: VT | C112: EM | D112: Tropical Storm | E112: TROPICAL DEPRESSION DEBBY | F112: 45512 | G112: 45514 | H112: 45512 | I112: FALSE | J112: 14 | K112: 45596
A113: 4818 | B113: NY | C113: DR | D113: Tropical Storm | E113: SEVERE STORM AND FLOODING | F113: 45512 | G113: 45514 | H113: 45555 | I113: FALSE | J113: 1 | K113: 45596
A114: 4825 | B114: NY | C114: DR | D114: Tropical Storm | E114: REMNANTS OF TROPICAL STORM DEBBY | F114: 45512 | G114: 45514 | H114: 45559 | I114: FALSE | J114: 11 | K114: 45596
A115: 5529 | B115: OR | C115: FM | D115: Fire | E115: LEE FALLS FIRE | F115: 45512 | H115: 45513 | I115: FALSE | J115: 1
A116: 4815 | B116: PA | C116: DR | D116: Tropical Storm | E116: TROPICAL STORM DEBBY | F116: 45513 | G116: 45514 | H116: 45546 | I116: FALSE | J116: 13 | K116: 45596
A117: 5530 | B117: NV | C117: FM | D117: Fire | E117: GOLD RANCH FIRE | F117: 45515 | G117: 45517 | H117: 45516 | I117: FALSE | J117: 1 | K117: 45596
A118: 3610 | B118: PR | C118: EM | D118: Severe Storm | E118: TROPICAL STORM ERNESTO | F118: 45517 | G118: 45520 | H118: 45517 | I118: FALSE | J118: 78 | K118: 45596
A119: 3611 | B119: VI | C119: EM | D119: Tropical Storm | E119: TROPICAL STORM ERNESTO | F119: 45517 | G119: 45520 | H119: 45522 | I119: FALSE | J119: 3 | K119: 45596
A120: 4841 | B120: VI | C120: DR | D120: Tropical Storm | E120: TROPICAL STORM ERNESTO | F120: 45517 | G120: 45520 | H120: 45590 | I120: FALSE | J120: 3 | K120: 45596
A121: 4850 | B121: PR | C121: DR | D121: Tropical Storm | E121: TROPICAL STORM ERNESTO | F121: 45517 | G121: 45520 | H121: 45623 | I121: FALSE | J121: 38 | K121: 45596
A122: 4857 | B122: AK | C122: DR | D122: Severe Storm | E122: SEVERE STORM AND FLOODING | F122: 45519 | G122: 45522 | H122: 45667 | I122: FALSE | J122: 1 | K122: 45596
A123: 4853 | B123: AK | C123: DR | D123: Severe Storm | E123: SEVERE STORM AND FLOODING | F123: 45520 | G123: 45522 | H123: 45658 | I123: FALSE | J123: 1 | K123: 45596
A124: 3612 | B124: CT | C124: EM | D124: Severe Storm | E124: SEVERE STORMS, FLOODING, LANDSLIDES, AND MUDSLIDES | F124: 45522 | G124: 45523 | H124: 45525 | I124: FALSE | J124: 3 | K124: 45596
A125: 3613 | B125: NY | C125: EM | D125: Severe Storm | E125: SEVERE STORM AND FLOODING | F125: 45522 | G125: 45523 | H125: 45529 | I125: FALSE | J125: 1 | K125: 45596
A126: 4820 | B126: CT | C126: DR | D126: Severe Storm | E126: SEVERE STORM, FLOODING, LANDSLIDES, AND MUDSLIDES | F126: 45522 | G126: 45523 | H126: 45555 | I126: FALSE | J126: 3 | K126: 45596
A127: 4839 | B127: NY | C127: DR | D127: Severe Storm | E127: SEVERE STORM AND FLOODING | F127: 45522 | G127: 45523 | H127: 45586 | I127: FALSE | J127: 3 | K127: 45596
...

Sheet Legend
A2: AEP | B2: Equals 1 during the Annual Enrollment Period (Oct 15 - Dec 7 each year). Row highlights blue. | C2: Anyone with medicare change/switch between Original Medicare and Medicare Advantage, or alter prescription drug plans.
A3: MA_OEP | B3: Equals 1 during the Medicare Advantage Open Enrollment Period (Jan 1 - Mar 31 each year). Row highlights green. | C3: For individuals already in a Medicare Advantage plan, allows single change to switch to other Medicare Advantage plan or return to Original Medicare.
A4: GEP | B4: Equals 1 during General Enrollment Period, Same as MA_OEP, same column. Row highlights green. | C4: For individuals who missed their Initial Enrollment Period when first elligible, allowing to sign up for Part A and/or Part B.
A5: SEP_Notes | B5: Use for date-bound SEPs (e.g., disaster SEPs by state). Most SEPs are triggered by individual circumstances, not calendar dates. | C5: For individuals with special life events to outside standard windows.
A6: Has_Event / Event_Detail | B6: Counts and pulls the matching row from the Events tab automatically. Row highlights orange when an event lands on that date. If two events share a date, Event_Detail shows only the first - prefer one combined row per date on the Events tab.
A8: Events tab | B8: One row per policy/market event.
A9: Date_Type | B9: Announced' = the day the rule/notice was published (matters for market/search reaction). 'Effective' = the day the policy actually changes plan value.
A11: Color key | B11: Orange = policy event day | Blue = AEP | Green = MA OEP / GEP | Yellow = cells you edit
